Algoritmos/BCD - BINARIO/Archivos Verilog/counter_bin.v
module counter_bin(
    input clk,
    input rst,
    input load,
    input dec,
    output reg [3:0] count,
    output z
);

    always @(negedge clk) begin
        if (rst) begin
            count <= 4'd8;
        end else if (load) begin
            count <= 4'd8;
        end else if (dec) begin
            count <= count - 4'd1;
        end else begin
            count <= count;
        end
    end
    assign z = (count == 4'd0) ? 1'b1 : 1'b0;

endmodule

Algoritmos/bcd_binario/Core/TB/counter_bin_TB.v
`timescale 1ns / 1ps

module counter_bin_TB;
  reg clk;
  reg rst;
  reg load;
  reg dec;
  wire [3:0] count;
  wire z;

  counter_bin uut (
    .clk(clk),
    .rst(rst),
    .load(load),
    .dec(dec),
    .count(count),
    .z(z)
  );

  always #10 clk = ~clk; 

  initial begin
    $dumpfile("TB/counter_bin_TB.vcd");
    $dumpvars(0, counter_bin_TB);

    clk = 0; rst = 1; load = 0; dec = 0;
    #20 rst = 0;

    if (count !== 4'd8 || z !== 1'b0) begin
      $display("counter_bin_TB FAIL en inicialización de Reset"); $fatal(1);
    end

  
    dec = 1;
    repeat(8) @(negedge clk);
    dec = 0;

    
    if (count !== 4'd0 || z !== 1'b1) begin
      $display("counter_bin_TB FAIL: El contador no llegó a cero correctamente. count=%d, z=%b", count, z);
      $fatal(1);
    end

   
    load = 1; #20 load = 0;
    if (count !== 4'd8 || z !== 1'b0) begin
      $display("counter_bin_TB FAIL en señal de carga (load)"); $fatal(1);
    end

    $display("counter_bin_TB PASS");
    $finish;
  end
endmodule

Algoritmos/bcd_binario/Core/TB/counter_bin_TB.vcd
$date
	Thu Jul 16 06:09:49 2026
$end
$version
	Icarus Verilog
$end
$timescale
	1ps
$end
$scope module counter_bin_TB $end
$var wire 1 ! z $end
$var wire 4 " count [3:0] $end
$var reg 1 # clk $end
$var reg 1 $ dec $end
$var reg 1 % load $end
$var reg 1 & rst $end
$scope module uut $end
$var wire 1 # clk $end
$var wire 1 $ dec $end
$var wire 1 % load $end
$var wire 1 & rst $end
$var wire 1 ! z $end
$var reg 4 ' count [3:0] $end
$upscope $end
$upscope $end
$enddefinitions $end
$comment Show the parameter values. $end
$dumpall
$end
#0
$dumpvars
b1000 '
1&
0%
0$
0#
b1000 "
0!
$end
#10000
1#
#20000
b111 "
b111 '
0#
1$
0&
#30000
1#
#40000
b110 "
b110 '
0#
#50000
1#
#60000
b101 "
b101 '
0#
#70000
1#
#80000
b100 "
b100 '
0#
#90000
1#
#100000
b11 "
b11 '
0#
#110000
1#
#120000
b10 "
b10 '
0#
#130000
1#
#140000
b1 "
b1 '
0#
#150000
1#
#160000
1!
b0 "
b0 '
0$
0#
