Algoritmos/Raiz_Cuadrada/Core/Control.v
module control(clk,rst,start,z,z_a,load_ra,shift_ra,sub_ra,clear_b,shift_b,set_b0,load_c,calc_c,done);
    input      clk, rst, start;
    input      z;
    input      z_a;
    output reg load_ra, shift_ra, sub_ra;
    output reg clear_b, shift_b, set_b0;
    output reg load_c, calc_c;
    output reg done;
  
    parameter START  = 3'b000;
    parameter SHIFT_RA  = 3'b001; 
    parameter SHIFT_CB  = 3'b010; 
    parameter CHECK = 3'b011; 
    parameter CHECK_F  = 3'b100; 
    parameter DONE     = 3'b101;

    reg [2:0] state, next_state;

    always @(posedge clk or posedge rst) begin
        if (rst) state <= START;
        else  state <= next_state;
    end

    // Transiciones de estado
    always @(*) begin
        next_state = state;
        case (state)
            START:    if (start) next_state = SHIFT_RA;
            SHIFT_RA:   next_state = SHIFT_CB;
            SHIFT_CB:   next_state = CHECK;
            CHECK:    next_state = CHECK_F;
            CHECK_F:   if (z_a)   next_state = DONE;
                     else       next_state = SHIFT_RA;
            DONE: if (rst)  next_state = START;
            default: next_state = START;
        endcase
    end

    // Generación de Salidas
    always @(*) begin
        load_ra = 0; shift_ra = 0; sub_ra = 0;
        clear_b = 0; shift_b = 0;  set_b0 = 0;
        load_c  = 0; calc_c = 0;   done = 0;

        case (state)
            START: begin
                if (start) begin
                    load_ra = 1;
                    clear_b = 1;
                end
            end
            SHIFT_RA: begin
                shift_ra = 1;
                load_c   = 1;
            end
            SHIFT_CB: begin
                calc_c  = 1;
                shift_b = 1;
            end
            CHECK: begin
                if (z) begin
                    sub_ra = 1;
                    set_b0 = 1;
                end
            end
            DONE: begin
                done = 1;
            end
        endcase
    end
`define BENCH
`ifdef BENCH
  reg [8*40:1] state_name;
  always @(*) begin
    case (state)
      START:      state_name = "START";
      SHIFT_RA: state_name = "SHIFT_RA";
      SHIFT_CB: state_name = "SHIFT_CB";
      CHECK:       state_name = "CHECK";
      CHECK_F:     state_name = "CHK_CO";
      DONE:     state_name = "END";
    endcase
  end
`endif
endmodule

Algoritmos/Raiz_Cuadrada/Core/Corr_c.v
module Corrimiento_c (clk,rst,load_b,B,calc_c,C);
    input            clk;
    input            rst;
    input            load_b;
    input      [4:0] B;
    input            calc_c;
    output reg [7:0] C;
    
    always @(posedge clk or posedge rst) begin
        if (rst) begin
            C <= 8'b0;
        end 
      else begin
            if (load_b) 
                C <= {3'b0, B};          
            else if (calc_c) 
                C <= (C << 2) | 8'b1;    
        end
    end
endmodule

Algoritmos/Raiz_Cuadrada/Core/Corr_b.v
module Corr_b (clk,rst,shift,b0,B);
    input            clk;
    input            rst;
    input            clear;
    input            shift;
    input            b0;
  output reg [4:0] B;
  
    always @(posedge clk or posedge rst) begin
        if (rst) begin
            B <= 5'b0;
        end 
else begin
            if (shift)  B <= B << 1;   
            if (b0) B[0] <= 1'b1;  
        end
    end
endmodule

Algoritmos/Raiz_Cuadrada/Core/Corr_ra.v
module Corrimiento_ra (clk,rst,load,radical_in, shift,sub_en,C,A,R);
    input            clk;
    input            rst;
    input            load;
    input      [7:0] radical_in;
    input            shift;
    input            sub_en;
    input      [7:0] C;
    output reg [7:0] A;
    output reg [7:0] R;

    always @(posedge clk or posedge rst) begin
        if (rst ) begin
            A <= 8'b0;
            R <= 8'b0;
        end 
      else if (load) begin
            A <= radical_in;
            R <= 8'b0;
        end 
      else begin
            if (shift) 
                {R, A} <= {R, A} << 2; 
            else if (sub_en) 
                R <= R - C;            // Bloque: R = R - C
        end
    end
endmodule

Algoritmos/Raiz_Cuadrada/Core/Comp.v
module comparador (R,C,z);
    input  [7:0] R;
    input  [7:0] C;
    output       z;
    
    assign z = (R >= C);
endmodule

Algoritmos/Raiz_Cuadrada/Core/raiz.v
module raiz_cuadrada (
    input        clk, rst, start,
    input  [7:0] radical,
    output [4:0] resultado,
    output       done
);
    wire w_z, w_z_a;
    wire w_load_ra, w_shift_ra, w_sub_ra;
    wire w_clear_b, w_shift_b, w_set_b0;
    wire w_load_c, w_calc_c;
    wire [7:0] w_A, w_R, w_C;
    wire [4:0] w_B;

    assign w_z_a     = (w_A == 8'b0); 
    assign resultado = w_B;


    comparador comp   (.R(w_R), .C(w_C), .z(w_z));
    Corrimiento_ra   corr_ra(.clk(clk), .rst(rst), .load(w_load_ra),.radical_in(radical), .shift(w_shift_ra), .sub_en(w_sub_ra), .C(w_C), .A(w_A), .R(w_R));
    Corr_b      corr_b(.clk(clk), .rst(rst),.shift(w_shift_b), .b0(w_set_b0), .B(w_B));                
    Corrimiento_c      corr_c (.clk(clk), .rst(rst), .load_b(w_load_c),.B(w_B), .calc_c(w_calc_c), .C(w_C));                  
    control  ctrl(.clk(clk), .rst(rst), .start(start), .z(w_z), .z_a(w_z_a), .load_ra(w_load_ra), .shift_ra(w_shift_ra), .sub_ra(w_sub_ra), 
                       .clear_b(w_clear_b), .shift_b(w_shift_b), .set_b0(w_set_b0), .load_c(w_load_c), .calc_c(w_calc_c), .done(done));
endmodule

Algoritmos/Raiz_Cuadrada/Core/raiz_TB.v
`timescale 1ns / 1ps
`define SIMULATION

module Raiz_TB;
  reg        rst;
  reg        clk;
  reg        init;
  reg        start;
  reg  [7:0] radical;
  
  wire [4:0] resultado;
  wire [7:0] residuo;
  wire       done;

  raiz_cuadrada uut ( .clk(clk), .rst(rst), .start(start), .radical(radical), .resultado(resultado), .done(done));

  parameter PERIOD         = 20;
  parameter real DUTY_CYCLE = 0.5;
  parameter OFFSET         = 0;
  reg [20:0] i;

  event reset_trigger;
  event reset_done_trigger;

  initial begin 
    forever begin 
      @ (reset_trigger);
      @ (negedge clk);
      rst = 1;
      @ (negedge clk);
      rst = 0;
      -> reset_done_trigger;
    end
  end

  initial begin  
    clk = 0; rst = 1; init = 0; start = 0;
    radical = 8'd121; 
  end

  initial begin  
    #OFFSET;
    forever begin
      clk = 1'b0;
      #(PERIOD-(PERIOD*DUTY_CYCLE)) clk = 1'b1;
      #(PERIOD*DUTY_CYCLE);
    end
  end

  initial begin 
    #10 -> reset_trigger;
    @ (reset_done_trigger);
    
    @ (posedge clk);
    init = 1;
    @ (posedge clk);
    init = 0;
    
    for(i=0; i<2; i=i+1) begin
      @ (posedge clk);
    end
    
    start = 1;
    @ (posedge clk);
    start = 0;
    
  
    @ (posedge done);
    #20;
    $finish;
  end     

  
  always @(posedge done) begin
    $display(" Valor Radical  : %d", radical);
    $display(" RESULTADO FINAL : %d", resultado);
  end

  initial begin: TEST_CASE
    $dumpfile("Raiz_TB.vcd");

  initial begin: TEST_CASE
    $dumpfile("Raiz_TB.vcd");
    $dumpvars(-1, uut);
  end
endmodule

Algoritmos/Raiz_Cuadrada/Core/Raiz_TB.vcd
$date
	Wed Jun 03 19:55:17 2026
$end
$version
	Icarus Verilog
$end
$timescale
	1ps
$end
$scope module Raiz_TB $end
$scope module uut $end
$var wire 1 ! clk $end
$var wire 8 " radical [7:0] $end
$var wire 5 # resultado [4:0] $end
$var wire 1 $ rst $end
$var wire 1 % start $end
$var wire 1 & w_z_a $end
$var wire 1 ' w_z $end
$var wire 1 ( w_sub_ra $end
$var wire 1 ) w_shift_ra $end
$var wire 1 * w_shift_b $end
$var wire 1 + w_set_b0 $end
$var wire 1 , w_load_ra $end
$var wire 1 - w_load_c $end
$var wire 1 . w_clear_b $end
$var wire 1 / w_calc_c $end
$var wire 8 0 w_R [7:0] $end
$var wire 8 1 w_C [7:0] $end
$var wire 5 2 w_B [4:0] $end
$var wire 8 3 w_A [7:0] $end
$var wire 1 4 done $end
$scope module comp $end
$var wire 1 ' z $end
$var wire 8 5 R [7:0] $end
$var wire 8 6 C [7:0] $end
$upscope $end
$scope module corr_b $end
$var wire 1 7 clear $end
$var wire 1 ! clk $end
$var wire 1 $ rst $end
$var wire 1 * shift $end
$var wire 1 + b0 $end
$var reg 5 8 B [4:0] $end
$upscope $end
$scope module corr_c $end
$var wire 5 9 B [4:0] $end
$var wire 1 ! clk $end
$var wire 1 $ rst $end
$var wire 1 - load_b $end
$var wire 1 / calc_c $end
$var reg 8 : C [7:0] $end
$upscope $end
$scope module corr_ra $end
$var wire 8 ; C [7:0] $end
$var wire 1 ! clk $end
$var wire 8 < radical_in [7:0] $end
$var wire 1 $ rst $end
$var wire 1 ( sub_en $end
$var wire 1 ) shift $end
$var wire 1 , load $end
$var reg 8 = A [7:0] $end
$var reg 8 > R [7:0] $end
$upscope $end
$scope module ctrl $end
$var wire 1 ! clk $end
$var wire 1 $ rst $end
$var wire 1 % start $end
$var wire 1 ' z $end
$var wire 1 & z_a $end
$var parameter 3 ? CHECK $end
$var parameter 3 @ CHECK_F $end
$var parameter 3 A DONE $end
$var parameter 3 B SHIFT_CB $end
$var parameter 3 C SHIFT_RA $end
$var parameter 3 D START $end
$var reg 1 / calc_c $end
$var reg 1 . clear_b $end
$var reg 1 4 done $end
$var reg 1 - load_c $end
$var reg 1 , load_ra $end
$var reg 3 E next_state [2:0] $end
$var reg 1 + set_b0 $end
$var reg 1 * shift_b $end
$var reg 1 ) shift_ra $end
$var reg 3 F state [2:0] $end
$var reg 320 G state_name [320:1] $end
$var reg 1 ( sub_ra $end
$upscope $end
$upscope $end
$upscope $end
$enddefinitions $end
$comment Show the parameter values. $end
$dumpall
b0 D
b1 C
b10 B
b101 A
b100 @
b11 ?
$end
#0
$dumpvars
b101001101010100010000010101001001010100 G
b0 F
b0 E
b0 >
b0 =
b1111001 <
b0 ;
b0 :
b0 9
b0 8
z7
b0 6
b0 5
04
b0 3
b0 2
b0 1
b0 0
0/
0.
0-
0,
0+
0*
0)
0(
1'
1&
0%
1$
b0 #
b1111001 "
0!
$end
#10000
1!
#20000
0!
#30000
1!
#40000
0$
0!
#50000
1!
#60000
0!
#70000
1!
#80000
0!
#90000
1!
#100000
0!
#110000
1.
1,
b1 E
1%
1!
#120000
0!
#130000
b101001101001000010010010100011001010100010111110101001001000001 G
1-
1)
b1 F
0&
b1111001 3
b1111001 =
0.
0,
b10 E
0%
1!
#140000
0!
#150000
b101001101001000010010010100011001010100010111110100001101000010 G
1*
1/
0-
0)
b11 E
b1 0
b1 5
b1 >
b11100100 3
b11100100 =
b10 F
1!
#160000
0!
#170000
b100001101001000010001010100001101001011 G
1+
1(
0/
0*
b100 E
b11 F
b1 1
b1 6
b1 :
b1 ;
1!
#180000
0!
#190000
b10000110100100001001011010111110100001101001111 G
0+
0(
b1 E
0'
b0 0
b0 5
b0 >
b1 #
b1 2
b1 8
b1 9
b100 F
1!
#200000
0!
#210000
b101001101001000010010010100011001010100010111110101001001000001 G
1-
1)
b10 E
b1 F
1!
#220000
0!
#230000
b101001101001000010010010100011001010100010111110100001101000010 G
1*
1/
0-
0)
b11 E
1'
b11 0
b11 5
b11 >
b10010000 3
b10010000 =
b10 F
1!
#240000
0!
#250000
b100001101001000010001010100001101001011 G
b100 E
0/
0*
b11 F
0'
b101 1
b101 6
b101 :
b101 ;
b10 #
b10 2
b10 8
b10 9
1!
#260000
0!
#270000
b10000110100100001001011010111110100001101001111 G
b1 E
b100 F
1!
#280000
0!
#290000
b101001101001000010010010100011001010100010111110101001001000001 G
1-
1)
b10 E
b1 F
1!
#300000
0!
#310000
b101001101001000010010010100011001010100010111110100001101000010 G
1*
1/
0-
0)
b11 E
b1110 0
b1110 5
b1110 >
b1000000 3
b1000000 =
1'
b10 1
b10 6
b10 :
b10 ;
b10 F
1!
#320000
0!
#330000
b100001101001000010001010100001101001011 G
1+
1(
0/
0*
b100 E
b11 F
b1001 1
b1001 6
b1001 :
b1001 ;
b100 #
b100 2
b100 8
b100 9
1!
#340000
0!
#350000
b10000110100100001001011010111110100001101001111 G
0+
0(
b1 E
0'
b101 0
b101 5
b101 >
b101 #
b101 2
b101 8
b101 9
b100 F
1!
#360000
0!
#370000
b101001101001000010010010100011001010100010111110101001001000001 G
1-
1)
b10 E
b1 F
1!
#380000
0!
#390000
b101001101001000010010010100011001010100010111110100001101000010 G
1*
1/
0-
0)
b11 E
b10101 0
b10101 5
b10101 >
1&
b0 3
b0 =
1'
b101 1
b101 6
b101 :
b101 ;
b10 F
1!
#400000
0!
#410000
b100001101001000010001010100001101001011 G
1+
1(
0/
0*
b100 E
b11 F
b10101 1
b10101 6
b10101 :
b10101 ;
b1010 #
b1010 2
b1010 8
b1010 9
1!
#420000
0!
#430000
b10000110100100001001011010111110100001101001111 G
0+
0(
b101 E
0'
b0 0
b0 5
b0 >
b1011 #
b1011 2
b1011 8
b1011 9
b100 F
1!
#440000
0!
#450000
b10001010100111001000100 G
14
b101 F
1!
