Algoritmos/Paridad/core/control.v
module control (clk, rst, init, b0, z_co, done, shift, load, inc, dec);
  input  clk, rst, init;
  input  b0;          
  input  z_co;        

  output reg done; 
  output reg shift;  
  output reg load;    
  output reg inc;
  output reg dec;     

  
  parameter START  = 3'b000;
   parameter LOAD   = 3'b001;
   parameter CHECK_B0= 3'b010;
   parameter INC = 3'b011;
   parameter DEC= 3'b100;
    parameter SHIFT  = 3'b101;
  parameter CHECK_F = 3'b110;
   parameter END_ST = 3'b111;

  reg [2:0] state;
reg [3:0] count;


  always @(posedge clk or posedge rst) begin
    if (rst) begin
        state <= START;
        count <= 4'b0;
    end
    else begin
        case (state)

            START: begin
                if (init)
                    state <= LOAD;
                else
                    state <= START;
            end

            LOAD: begin
                state <= CHECK_B0;
            end

            CHECK_B0: begin
                if (b0)
                    state <= INC;
                else
                    state <= DEC;
            end

            INC: begin
                state <= DEC;
            end

            DEC: begin
                state <= SHIFT;
            end

            SHIFT: begin
                state <= CHECK_F;
            end

            CHECK_F: begin
                if (z_co)
                    state <= END_ST;
                else
                    state <= CHECK_B0;
            end

            END_ST: begin
                  if (init)
                    state <= START;

                else 
                    state <= END_ST;
            end

            default: begin
                state <= START;
            end

        endcase
    end
end
  

always @(*) begin
    case (state)

        START: begin
            done  = 0;
            shift = 0;
            load  = 0;
            inc   = 0;
            dec   = 0;
        end

        LOAD: begin
            done  = 0;
            shift = 0;
            load  = 1;
            inc   = 0;
            dec   = 0;
        end

        CHECK_B0: begin
            done  = 0;
            shift = 0;
            load  = 0;
            inc   = 0;
            dec   = 0;
        end

        INC: begin
            done  = 0;
            shift = 0;
            load  = 0;
            inc   = 1;
            dec   = 0;
        end

        DEC: begin
            done  = 0;
            shift = 0;
            load  = 0;
            inc   = 0;
            dec   = 1;
        end

        SHIFT: begin
            done  = 0;
            shift = 1;
            load  = 0;
            inc   = 0;
            dec   = 0;
        end

        CHECK_F: begin
            done  = 0;
            shift = 0;
            load  = 0;
            inc   = 0;
            dec   = 0;
        end

        END_ST: begin
            done  = 1;
            shift = 0;
            load  = 0;
            inc   = 0;
            dec   = 0;
        end

        default: begin
            done  = 0;
            shift = 0;
            load  = 0;
            inc   = 0;
            dec   = 0;
        end

    endcase
end

`define BENCH
`ifdef BENCH
  reg [8*16:1] state_name;
  always @(*) begin
    case (state)
      START : state_name = "START";
      LOAD  : state_name = "LOAD";
      CHECK_B0: state_name = "CHECK_B0";
      INC : state_name = "INC";
      DEC : state_name = "DEC";
      SHIFT : state_name = "SHIFT";
      CHECK_F: state_name = "CHECK_F";
      END_ST: state_name = "END";
      default: state_name = "UNKN";
    endcase
  end
`endif
endmodule

Algoritmos/Paridad/core/sum_r.v
module sum_r (clk, load, inc, r, rst);
  input  clk;
  input  load, rst;
  input  inc;
  output reg [4:0] r;

  always @(posedge clk) begin
    if (rst || load)
      r <= 5'd0;
    else if (inc)
      r <= r + 1'b1;
  end
endmodule

Algoritmos/Paridad/core/cont.v

module cont(clk, rst, load, dec, z_co);
  input  clk;
  input  rst;
  input   load;           
  input  dec;            
  output z_co;           
  reg [4:0] cont;       

  assign z_co = (cont == 5'b0);
  always @(posedge clk) begin
    if (rst)
    cont <= 5'd16;
    else if ( load)
      cont <= 5'd16;
  else if (dec)
      cont <= cont - 1'b1;
  end
endmodule

Algoritmos/Paridad/core/Corr_b.v
module Corr_b (clk, rst, in_B, shift, load, out_B, b0);
  input        clk;
  input        rst;
  input  [15:0] in_B;      
  input        shift;      
  input        load;       
  output reg [15:0] out_B;   
  output wire       b0;    

  assign b0 = out_B[0];
always @(posedge clk) begin
    if (rst)
        out_B<= 16'b0;
    else if (load)
      out_B <= in_B;
  else if (shift)
     out_B<= out_B>> 1;
  end
endmodule

Algoritmos/Paridad/core/paridad.v
module paridad (clk, rst, start, B, resultado, done);
  input        clk, rst, start;
  input  [15:0] B;
 output         resultado;  
  output        done;  
wire w_shift, w_load, w_inc, w_dec;
  wire w_z_co;
  wire [4:0] w_r;
  wire [15:0] w_out_b;
  wire        w_b0;

  Corr_b Corr_b (.clk  (clk), .rst(rst), .in_B(B),.shift(w_shift), .load(w_load),.out_B(w_out_b),.b0(w_b0));
  cont   cont (.clk(clk), .rst(rst),.load(w_load), .dec(w_dec),.z_co(w_z_co));
  sum_r sum_r (.clk(clk), .load(w_load), .inc(w_inc),.r(w_r),.rst(rst));
  
  control control (.clk(clk), .rst(rst), .init(start),.b0(w_b0), .z_co(w_z_co),.done(done), .shift(w_shift),.load(w_load), .inc(w_inc),.dec(w_dec));
  assign resultado = w_r[0];
endmodule

Algoritmos/Paridad/core/TB/paridad_TB.v
`timescale 1ns / 1ps

module paridad_TB;
reg  clk;
  reg  rst;
  reg  start;
  reg  [15:0] B;
  wire  resultado;
  wire   done;

  paridad uut (.clk(clk),.rst(rst),.start(start),.B(B),.resultado(resultado),.done(done));

  always #5 clk = ~clk;

  task run_case;
    input [15:0] value;
    input        expected;
    integer cycles;
    begin
      @(negedge clk);
      B     = value;
       start = 1;
      repeat (2) @(posedge clk);
    @(negedge clk);
      start = 0;
 cycles = 0;
      while ((done !== 1'b1) && (cycles < 300)) begin
        @(posedge clk);
        #1;
        cycles = cycles + 1;
      end

  if (done !== 1'b1) begin
        $display("paridad_TB FAIL: timeout para B=%h", value);
        $fatal(1);
      end

   if (resultado !== expected) begin
        $display("paridad_TB FAIL: B=%h esperado=%b obtenido=%b", value, expected, resultado);
        $fatal(1);
      end

      $display("paridad_TB OK: B=%h paridad_impar=%b (%0d ciclos)",value, resultado, cycles);
    end
  endtask

  initial begin
    $dumpfile("TB/paridad_TB.vcd");
     $dumpvars(0, paridad_TB);

     clk   = 0;
    rst   = 1;
     start = 0;
    B     = 0;

  repeat (2) @(posedge clk);
     @(negedge clk);
    rst = 0;

  run_case(16'h0000, 1'b0);
  run_case(16'h0001, 1'b1);
  run_case(16'hffff, 1'b0);
  run_case(16'hf0f0, 1'b0);
    run_case(16'hf0f1, 1'b1);
    run_case(16'haaaa, 1'b0);
    run_case(16'h8000, 1'b1);

    $display("paridad_TB PASS");
    $finish;
  end
endmodule

Algoritmos/Paridad/core/TB/paridad_TB.vcd
$date
	Tue Jul 14 18:06:30 2026
$end
$version
	Icarus Verilog
$end
$timescale
	1ps
$end
$scope module paridad_TB $end
$var wire 1 ! resultado $end
$var wire 1 " done $end
$var reg 16 # B [15:0] $end
$var reg 1 $ clk $end
$var reg 1 % rst $end
$var reg 1 & start $end
$scope module uut $end
$var wire 16 ' B [15:0] $end
$var wire 1 $ clk $end
$var wire 1 % rst $end
$var wire 1 & start $end
$var wire 1 ( w_z_co $end
$var wire 1 ) w_shift $end
$var wire 5 * w_r [4:0] $end
$var wire 16 + w_out_b [15:0] $end
$var wire 1 , w_load $end
$var wire 1 - w_inc $end
$var wire 1 . w_dec $end
$var wire 1 / w_b0 $end
$var wire 1 ! resultado $end
$var wire 1 " done $end
$scope module Corr_b $end
$var wire 1 $ clk $end
$var wire 16 0 in_B [15:0] $end
$var wire 1 % rst $end
$var wire 1 ) shift $end
$var wire 1 , load $end
$var wire 1 / b0 $end
$var reg 16 1 out_B [15:0] $end
$upscope $end
$scope module cont $end
$var wire 1 $ clk $end
$var wire 1 % rst $end
$var wire 1 ( z_co $end
$var wire 1 , load $end
$var wire 1 . dec $end
$var reg 5 2 cont [4:0] $end
$upscope $end
$scope module control $end
$var wire 1 / b0 $end
$var wire 1 $ clk $end
$var wire 1 & init $end
$var wire 1 % rst $end
$var wire 1 ( z_co $end
$var parameter 3 3 CHECK_B0 $end
$var parameter 3 4 CHECK_F $end
$var parameter 3 5 DEC $end
$var parameter 3 6 END_ST $end
$var parameter 3 7 INC $end
$var parameter 3 8 LOAD $end
$var parameter 3 9 SHIFT $end
$var parameter 3 : START $end
$var reg 4 ; count [3:0] $end
$var reg 1 . dec $end
$var reg 1 " done $end
$var reg 1 - inc $end
$var reg 1 , load $end
$var reg 1 ) shift $end
$var reg 3 < state [2:0] $end
$var reg 128 = state_name [128:1] $end
$upscope $end
$scope module sum_r $end
$var wire 1 $ clk $end
$var wire 1 - inc $end
$var wire 1 , load $end
$var wire 1 % rst $end
$var reg 5 > r [4:0] $end
$upscope $end
$upscope $end
$scope task run_case $end
$var reg 1 ? expected $end
$var reg 16 @ value [15:0] $end
$var integer 32 A cycles [31:0] $end
$upscope $end
$upscope $end
$enddefinitions $end
$comment Show the parameter values. $end
$dumpall
b0 :
b101 9
b1 8
b11 7
b111 6
b100 5
b110 4
b10 3
$end
#0
$dumpvars
bx A
bx @
x?
bx >
b101001101010100010000010101001001010100 =
b0 <
b0 ;
bx 2
bx 1
b0 0
x/
0.
0-
0,
bx +
bx *
0)
x(
b0 '
0&
1%
0$
b0 #
0"
x!
$end
#5000
0/
0!
b0 +
b0 1
0(
b10000 2
b0 *
b0 >
1$
#10000
0$
#15000
1$
#20000
0?
b0 @
0%
0$
#25000
1$
#30000
1&
0$
#35000
1,
b1001100010011110100000101000100 =
b1 <
1$
#40000
0$
#45000
b100001101001000010001010100001101001011010111110100001000110000 =
0,
b10 <
1$
#50000
b0 A
0&
0$
#55000
1.
b10001000100010101000011 =
b100 <
1$
#56000
b1 A
#60000
0$
#65000
b101001101001000010010010100011001010100 =
0.
1)
b101 <
b1111 2
1$
#66000
b10 A
#70000
0$
#75000
0)
b1000011010010000100010101000011010010110101111101000110 =
b110 <
1$
#76000
b11 A
#80000
0$
#85000
b100001101001000010001010100001101001011010111110100001000110000 =
b10 <
1$
#86000
b100 A
#90000
0$
#95000
1.
b10001000100010101000011 =
b100 <
1$
#96000
b101 A
#100000
0$
#105000
b101001101001000010010010100011001010100 =
0.
1)
b101 <
b1110 2
1$
#106000
b110 A
#110000
0$
#115000
0)
b1000011010010000100010101000011010010110101111101000110 =
b110 <
1$
#116000
b111 A
#120000
0$
#125000
b100001101001000010001010100001101001011010111110100001000110000 =
b10 <
1$
#126000
b1000 A
#130000
0$
#135000
1.
b10001000100010101000011 =
b100 <
1$
#136000
b1001 A
#140000
0$
#145000
b101001101001000010010010100011001010100 =
0.
1)
b101 <
b1101 2
1$
#146000
b1010 A
#150000
0$
#155000
0)
b1000011010010000100010101000011010010110101111101000110 =
b110 <
1$
#156000
b1011 A
#160000
0$
#165000
b100001101001000010001010100001101001011010111110100001000110000 =
b10 <
1$
#166000
b1100 A
#170000
0$
#175000
1.
b10001000100010101000011 =
b100 <
1$
#176000
b1101 A
#180000
0$
#185000
b101001101001000010010010100011001010100 =
0.
1)
b101 <
b1100 2
1$
#186000
b1110 A
#190000
0$
#195000
0)
b1000011010010000100010101000011010010110101111101000110 =
b110 <
1$
#196000
b1111 A
#200000
0$
#205000
b100001101001000010001010100001101001011010111110100001000110000 =
b10 <
1$
#206000
b10000 A
#210000
0$
#215000
1.
b10001000100010101000011 =
b100 <
1$
#216000
b10001 A
#220000
0$
#225000
b101001101001000010010010100011001010100 =
0.
1)
b101 <
b1011 2
1$
#226000
b10010 A
#230000
0$
#235000
0)
b1000011010010000100010101000011010010110101111101000110 =
b110 <
1$
#236000
b10011 A
#240000
0$
#245000
b100001101001000010001010100001101001011010111110100001000110000 =
b10 <
1$
#246000
b10100 A
#250000
0$
#255000
1.
b10001000100010101000011 =
b100 <
1$
#256000
b10101 A
#260000
0$
#265000
b101001101001000010010010100011001010100 =
0.
1)
b101 <
b1010 2
1$
#266000
b10110 A
#270000
0$
#275000
0)
b1000011010010000100010101000011010010110101111101000110 =
b110 <
1$
#276000
b10111 A
#280000
0$
#285000
b100001101001000010001010100001101001011010111110100001000110000 =
b10 <
1$
#286000
b11000 A
#290000
0$
#295000
1.
b10001000100010101000011 =
b100 <
1$
#296000
b11001 A
#300000
0$
#305000
b101001101001000010010010100011001010100 =
0.
1)
b101 <
b1001 2
1$
#306000
b11010 A
#310000
0$
#315000
0)
b1000011010010000100010101000011010010110101111101000110 =
b110 <
1$
#316000
b11011 A
#320000
0$
#325000
b100001101001000010001010100001101001011010111110100001000110000 =
b10 <
1$
#326000
b11100 A
#330000
0$
#335000
1.
b10001000100010101000011 =
b100 <
1$
#336000
b11101 A
#340000
0$
#345000
b101001101001000010010010100011001010100 =
0.
1)
b101 <
b1000 2
1$
#346000
b11110 A
#350000
0$
#355000
0)
b1000011010010000100010101000011010010110101111101000110 =
b110 <
1$
#356000
b11111 A
#360000
0$
#365000
b100001101001000010001010100001101001011010111110100001000110000 =
b10 <
1$
#366000
b100000 A
#370000
0$
#375000
1.
b10001000100010101000011 =
b100 <
1$
#376000
b100001 A
#380000
0$
#385000
b101001101001000010010010100011001010100 =
0.
1)
b101 <
b111 2
1$
#386000
b100010 A
#390000
0$
#395000
0)
b1000011010010000100010101000011010010110101111101000110 =
b110 <
1$
#396000
b100011 A
#400000
0$
#405000
b100001101001000010001010100001101001011010111110100001000110000 =
b10 <
1$
#406000
b100100 A
#410000
0$
#415000
1.
b10001000100010101000011 =
b100 <
1$
#416000
b100101 A
#420000
0$
#425000
b101001101001000010010010100011001010100 =
0.
1)
b101 <
b110 2
1$
#426000
b100110 A
#430000
0$
#435000
0)
b1000011010010000100010101000011010010110101111101000110 =
b110 <
1$
#436000
b100111 A
#440000
0$
#445000
b100001101001000010001010100001101001011010111110100001000110000 =
b10 <
1$
#446000
b101000 A
#450000
0$
#455000
1.
b10001000100010101000011 =
b100 <
1$
#456000
b101001 A
#460000
0$
#465000
b101001101001000010010010100011001010100 =
0.
1)
b101 <
b101 2
1$
#466000
b101010 A
#470000
0$
#475000
0)
b1000011010010000100010101000011010010110101111101000110 =
b110 <
1$
#476000
b101011 A
#480000
0$
#485000
b100001101001000010001010100001101001011010111110100001000110000 =
b10 <
1$
#486000
b101100 A
#490000
0$
#495000
1.
b10001000100010101000011 =
b100 <
1$
#496000
b101101 A
#500000
0$
#505000
b101001101001000010010010100011001010100 =
0.
1)
b101 <
b100 2
1$
#506000
b101110 A
#510000
0$
#515000
0)
b1000011010010000100010101000011010010110101111101000110 =
b110 <
1$
#516000
b101111 A
#520000
0$
#525000
b100001101001000010001010100001101001011010111110100001000110000 =
b10 <
1$
#526000
b110000 A
#530000
0$
#535000
1.
b10001000100010101000011 =
b100 <
1$
#536000
b110001 A
#540000
0$
#545000
b101001101001000010010010100011001010100 =
0.
1)
b101 <
b11 2
1$
#546000
b110010 A
#550000
0$
#555000
0)
b1000011010010000100010101000011010010110101111101000110 =
b110 <
1$
#556000
b110011 A
#560000
0$
#565000
b100001101001000010001010100001101001011010111110100001000110000 =
b10 <
1$
#566000
b110100 A
#570000
0$
#575000
1.
b10001000100010101000011 =
b100 <
1$
#576000
b110101 A
#580000
0$
#585000
b101001101001000010010010100011001010100 =
0.
1)
b101 <
b10 2
1$
#586000
b110110 A
#590000
0$
#595000
0)
b1000011010010000100010101000011010010110101111101000110 =
b110 <
1$
#596000
b110111 A
#600000
0$
#605000
b100001101001000010001010100001101001011010111110100001000110000 =
b10 <
1$
#606000
b111000 A
#610000
0$
#615000
1.
b10001000100010101000011 =
b100 <
1$
#616000
b111001 A
#620000
0$
#625000
b101001101001000010010010100011001010100 =
0.
1)
b101 <
b1 2
1$
#626000
b111010 A
#630000
0$
#635000
0)
b1000011010010000100010101000011010010110101111101000110 =
b110 <
1$
#636000
b111011 A
#640000
0$
#645000
b100001101001000010001010100001101001011010111110100001000110000 =
b10 <
1$
#646000
b111100 A
#650000
0$
#655000
1.
b10001000100010101000011 =
b100 <
1$
#656000
b111101 A
#660000
0$
#665000
b101001101001000010010010100011001010100 =
0.
1)
b101 <
1(
b0 2
1$
#666000
b111110 A
#670000
0$
#675000
0)
b1000011010010000100010101000011010010110101111101000110 =
b110 <
1$
#676000
b111111 A
#680000
0$
#685000
b10001010100111001000100 =
1"
b111 <
1$
#686000
1?
b1 @
b1000000 A
#690000
1&
b1 #
b1 '
b1 0
0$
#695000
0"
b101001101010100010000010101001001010100 =
b0 <
1$
#700000
0$
#705000
b1001100010011110100000101000100 =
1,
b1 <
1$
#710000
b0 A
0&
0$
#715000
0,
b100001101001000010001010100001101001011010111110100001000110000 =
1/
b10 <
0(
b10000 2
b1 +
b1 1
1$
#716000
b1 A
#720000
0$
#725000
b10010010100111001000011 =
1-
b11 <
1$
#726000
b10 A
#730000
0$
#735000
1.
0-
b10001000100010101000011 =
1!
b100 <
b1 *
b1 >
1$
#736000
b11 A
#740000
0$
#745000
b101001101001000010010010100011001010100 =
0.
1)
b101 <
b1111 2
1$
#746000
b100 A
#750000
0$
#755000
0)
b1000011010010000100010101000011010010110101111101000110 =
0/
b110 <
b0 +
b0 1
1$
#756000
b101 A
#760000
0$
#765000
b100001101001000010001010100001101001011010111110100001000110000 =
b10 <
1$
#766000
b110 A
#770000
0$
#775000
1.
b10001000100010101000011 =
b100 <
1$
#776000
b111 A
#780000
0$
#785000
b101001101001000010010010100011001010100 =
0.
1)
b101 <
b1110 2
1$
#786000
b1000 A
#790000
0$
#795000
0)
b1000011010010000100010101000011010010110101111101000110 =
b110 <
1$
#796000
b1001 A
#800000
0$
#805000
b100001101001000010001010100001101001011010111110100001000110000 =
b10 <
1$
#806000
b1010 A
#810000
0$
#815000
1.
b10001000100010101000011 =
b100 <
1$
#816000
b1011 A
#820000
0$
#825000
b101001101001000010010010100011001010100 =
0.
1)
b101 <
b1101 2
1$
#826000
b1100 A
#830000
0$
#835000
0)
b1000011010010000100010101000011010010110101111101000110 =
b110 <
1$
#836000
b1101 A
#840000
0$
#845000
b100001101001000010001010100001101001011010111110100001000110000 =
b10 <
1$
#846000
b1110 A
#850000
0$
#855000
1.
b10001000100010101000011 =
b100 <
1$
#856000
b1111 A
#860000
0$
#865000
b101001101001000010010010100011001010100 =
0.
1)
b101 <
b1100 2
1$
#866000
b10000 A
#870000
0$
#875000
0)
b1000011010010000100010101000011010010110101111101000110 =
b110 <
1$
#876000
b10001 A
#880000
0$
#885000
b100001101001000010001010100001101001011010111110100001000110000 =
b10 <
1$
#886000
b10010 A
#890000
0$
#895000
1.
b10001000100010101000011 =
b100 <
1$
#896000
b10011 A
#900000
0$
#905000
b101001101001000010010010100011001010100 =
0.
1)
b101 <
b1011 2
1$
#906000
b10100 A
#910000
0$
#915000
0)
b1000011010010000100010101000011010010110101111101000110 =
b110 <
1$
#916000
b10101 A
#920000
0$
#925000
b100001101001000010001010100001101001011010111110100001000110000 =
b10 <
1$
#926000
b10110 A
#930000
0$
#935000
1.
b10001000100010101000011 =
b100 <
1$
#936000
b10111 A
#940000
0$
#945000
b101001101001000010010010100011001010100 =
0.
1)
b101 <
b1010 2
1$
#946000
b11000 A
#950000
0$
#955000
0)
b1000011010010000100010101000011010010110101111101000110 =
b110 <
1$
#956000
b11001 A
#960000
0$
#965000
b100001101001000010001010100001101001011010111110100001000110000 =
b10 <
1$
#966000
b11010 A
#970000
0$
#975000
1.
b10001000100010101000011 =
b100 <
1$
#976000
b11011 A
#980000
0$
#985000
b101001101001000010010010100011001010100 =
0.
1)
b101 <
b1001 2
1$
#986000
b11100 A
#990000
0$
#995000
0)
b1000011010010000100010101000011010010110101111101000110 =
b110 <
1$
#996000
b11101 A
#1000000
0$
#1005000
b100001101001000010001010100001101001011010111110100001000110000 =
b10 <
1$
#1006000
b11110 A
#1010000
0$
#1015000
1.
b10001000100010101000011 =
b100 <
1$
#1016000
b11111 A
#1020000
0$
#1025000
b101001101001000010010010100011001010100 =
0.
1)
b101 <
b1000 2
1$
#1026000
b100000 A
#1030000
0$
#1035000
0)
b1000011010010000100010101000011010010110101111101000110 =
b110 <
1$
#1036000
b100001 A
#1040000
0$
#1045000
b100001101001000010001010100001101001011010111110100001000110000 =
b10 <
1$
#1046000
b100010 A
#1050000
0$
#1055000
1.
b10001000100010101000011 =
b100 <
1$
#1056000
b100011 A
#1060000
0$
#1065000
b101001101001000010010010100011001010100 =
0.
1)
b101 <
b111 2
1$
#1066000
b100100 A
#1070000
0$
#1075000
0)
b1000011010010000100010101000011010010110101111101000110 =
b110 <
1$
#1076000
b100101 A
#1080000
0$
#1085000
b100001101001000010001010100001101001011010111110100001000110000 =
b10 <
1$
#1086000
b100110 A
#1090000
0$
#1095000
1.
b10001000100010101000011 =
b100 <
1$
#1096000
b100111 A
#1100000
0$
#1105000
b101001101001000010010010100011001010100 =
0.
1)
b101 <
b110 2
1$
#1106000
b101000 A
#1110000
0$
#1115000
0)
b1000011010010000100010101000011010010110101111101000110 =
b110 <
1$
#1116000
b101001 A
#1120000
0$
#1125000
b100001101001000010001010100001101001011010111110100001000110000 =
b10 <
1$
#1126000
b101010 A
#1130000
0$
#1135000
1.
b10001000100010101000011 =
b100 <
1$
#1136000
b101011 A
#1140000
0$
#1145000
b101001101001000010010010100011001010100 =
0.
1)
b101 <
b101 2
1$
#1146000
b101100 A
#1150000
0$
#1155000
0)
b1000011010010000100010101000011010010110101111101000110 =
b110 <
1$
#1156000
b101101 A
#1160000
0$
#1165000
b100001101001000010001010100001101001011010111110100001000110000 =
b10 <
1$
#1166000
b101110 A
#1170000
0$
#1175000
1.
b10001000100010101000011 =
b100 <
1$
#1176000
b101111 A
#1180000
0$
#1185000
b101001101001000010010010100011001010100 =
0.
1)
b101 <
b100 2
1$
#1186000
b110000 A
#1190000
0$
#1195000
0)
b1000011010010000100010101000011010010110101111101000110 =
b110 <
1$
#1196000
b110001 A
#1200000
0$
#1205000
b100001101001000010001010100001101001011010111110100001000110000 =
b10 <
1$
#1206000
b110010 A
#1210000
0$
#1215000
1.
b10001000100010101000011 =
b100 <
1$
#1216000
b110011 A
#1220000
0$
#1225000
b101001101001000010010010100011001010100 =
0.
1)
b101 <
b11 2
1$
#1226000
b110100 A
#1230000
0$
#1235000
0)
b1000011010010000100010101000011010010110101111101000110 =
b110 <
1$
#1236000
b110101 A
#1240000
0$
#1245000
b100001101001000010001010100001101001011010111110100001000110000 =
b10 <
1$
#1246000
b110110 A
#1250000
0$
#1255000
1.
b10001000100010101000011 =
b100 <
1$
#1256000
b110111 A
#1260000
0$
#1265000
b101001101001000010010010100011001010100 =
0.
1)
b101 <
b10 2
1$
#1266000
b111000 A
#1270000
0$
#1275000
0)
b1000011010010000100010101000011010010110101111101000110 =
b110 <
1$
#1276000
b111001 A
#1280000
0$
#1285000
b100001101001000010001010100001101001011010111110100001000110000 =
b10 <
1$
#1286000
b111010 A
#1290000
0$
#1295000
1.
b10001000100010101000011 =
b100 <
1$
#1296000
b111011 A
#1300000
0$
#1305000
b101001101001000010010010100011001010100 =
0.
1)
b101 <
b1 2
1$
#1306000
b111100 A
#1310000
0$
#1315000
0)
b1000011010010000100010101000011010010110101111101000110 =
b110 <
1$
#1316000
b111101 A
#1320000
0$
#1325000
b100001101001000010001010100001101001011010111110100001000110000 =
b10 <
1$
#1326000
b111110 A
#1330000
0$
#1335000
1.
b10001000100010101000011 =
b100 <
1$
#1336000
b111111 A
#1340000
0$
#1345000
b101001101001000010010010100011001010100 =
0.
1)
b101 <
1(
b0 2
1$
#1346000
b1000000 A
#1350000
0$
#1355000
0)
b1000011010010000100010101000011010010110101111101000110 =
b110 <
1$
#1356000
b1000001 A
#1360000
0$
#1365000
b10001010100111001000100 =
1"
b111 <
1$
#1366000
0?
b1111111111111111 @
b1000010 A
#1370000
1&
b1111111111111111 #
b1111111111111111 '
b1111111111111111 0
0$
#1375000
0"
b101001101010100010000010101001001010100 =
b0 <
1$
#1380000
0$
#1385000
b1001100010011110100000101000100 =
1,
b1 <
1$
#1390000
b0 A
0&
0$
#1395000
0,
b100001101001000010001010100001101001011010111110100001000110000 =
0!
1/
b10 <
b0 *
b0 >
0(
b10000 2
b1111111111111111 +
b1111111111111111 1
1$
#1396000
b1 A
#1400000
0$
#1405000
b10010010100111001000011 =
1-
b11 <
1$
#1406000
b10 A
#1410000
0$
#1415000
1.
0-
b10001000100010101000011 =
1!
b100 <
b1 *
b1 >
1$
#1416000
b11 A
#1420000
0$
#1425000
b101001101001000010010010100011001010100 =
0.
1)
b101 <
b1111 2
1$
#1426000
b100 A
#1430000
0$
#1435000
0)
b1000011010010000100010101000011010010110101111101000110 =
b110 <
b111111111111111 +
b111111111111111 1
1$
#1436000
b101 A
#1440000
0$
#1445000
b100001101001000010001010100001101001011010111110100001000110000 =
b10 <
1$
#1446000
b110 A
#1450000
0$
#1455000
1-
b10010010100111001000011 =
b11 <
1$
#1456000
b111 A
#1460000
0$
#1465000
b10001000100010101000011 =
1.
0-
0!
b100 <
b10 *
b10 >
1$
#1466000
b1000 A
#1470000
0$
#1475000
0.
1)
b101001101001000010010010100011001010100 =
b101 <
b1110 2
1$
#1476000
b1001 A
#1480000
0$
#1485000
b1000011010010000100010101000011010010110101111101000110 =
0)
b110 <
b11111111111111 +
b11111111111111 1
1$
#1486000
b1010 A
#1490000
0$
#1495000
b100001101001000010001010100001101001011010111110100001000110000 =
b10 <
1$
#1496000
b1011 A
#1500000
0$
#1505000
b10010010100111001000011 =
1-
b11 <
1$
#1506000
b1100 A
#1510000
0$
#1515000
1.
0-
b10001000100010101000011 =
1!
b100 <
b11 *
b11 >
1$
#1516000
b1101 A
#1520000
0$
#1525000
b101001101001000010010010100011001010100 =
0.
1)
b101 <
b1101 2
1$
#1526000
b1110 A
#1530000
0$
#1535000
0)
b1000011010010000100010101000011010010110101111101000110 =
b110 <
b1111111111111 +
b1111111111111 1
1$
#1536000
b1111 A
#1540000
0$
#1545000
b100001101001000010001010100001101001011010111110100001000110000 =
b10 <
1$
#1546000
b10000 A
#1550000
0$
#1555000
1-
b10010010100111001000011 =
b11 <
1$
#1556000
b10001 A
#1560000
0$
#1565000
b10001000100010101000011 =
1.
0-
0!
b100 <
b100 *
b100 >
1$
#1566000
b10010 A
#1570000
0$
#1575000
0.
1)
b101001101001000010010010100011001010100 =
b101 <
b1100 2
1$
#1576000
b10011 A
#1580000
0$
#1585000
b1000011010010000100010101000011010010110101111101000110 =
0)
b110 <
b111111111111 +
b111111111111 1
1$
#1586000
b10100 A
#1590000
0$
#1595000
b100001101001000010001010100001101001011010111110100001000110000 =
b10 <
1$
#1596000
b10101 A
#1600000
0$
#1605000
b10010010100111001000011 =
1-
b11 <
1$
#1606000
b10110 A
#1610000
0$
#1615000
1.
0-
b10001000100010101000011 =
1!
b100 <
b101 *
b101 >
1$
#1616000
b10111 A
#1620000
0$
#1625000
b101001101001000010010010100011001010100 =
0.
1)
b101 <
b1011 2
1$
#1626000
b11000 A
#1630000
0$
#1635000
0)
b1000011010010000100010101000011010010110101111101000110 =
b110 <
b11111111111 +
b11111111111 1
1$
#1636000
b11001 A
#1640000
0$
#1645000
b100001101001000010001010100001101001011010111110100001000110000 =
b10 <
1$
#1646000
b11010 A
#1650000
0$
#1655000
1-
b10010010100111001000011 =
b11 <
1$
#1656000
b11011 A
#1660000
0$
#1665000
b10001000100010101000011 =
1.
0-
0!
b100 <
b110 *
b110 >
1$
#1666000
b11100 A
#1670000
0$
#1675000
0.
1)
b101001101001000010010010100011001010100 =
b101 <
b1010 2
1$
#1676000
b11101 A
#1680000
0$
#1685000
b1000011010010000100010101000011010010110101111101000110 =
0)
b110 <
b1111111111 +
b1111111111 1
1$
#1686000
b11110 A
#1690000
0$
#1695000
b100001101001000010001010100001101001011010111110100001000110000 =
b10 <
1$
#1696000
b11111 A
#1700000
0$
#1705000
b10010010100111001000011 =
1-
b11 <
1$
#1706000
b100000 A
#1710000
0$
#1715000
1.
0-
b10001000100010101000011 =
1!
b100 <
b111 *
b111 >
1$
#1716000
b100001 A
#1720000
0$
#1725000
b101001101001000010010010100011001010100 =
0.
1)
b101 <
b1001 2
1$
#1726000
b100010 A
#1730000
0$
#1735000
0)
b1000011010010000100010101000011010010110101111101000110 =
b110 <
b111111111 +
b111111111 1
1$
#1736000
b100011 A
#1740000
0$
#1745000
b100001101001000010001010100001101001011010111110100001000110000 =
b10 <
1$
#1746000
b100100 A
#1750000
0$
#1755000
1-
b10010010100111001000011 =
b11 <
1$
#1756000
b100101 A
#1760000
0$
#1765000
b10001000100010101000011 =
1.
0-
0!
b100 <
b1000 *
b1000 >
1$
#1766000
b100110 A
#1770000
0$
#1775000
0.
1)
b101001101001000010010010100011001010100 =
b101 <
b1000 2
1$
#1776000
b100111 A
#1780000
0$
#1785000
b1000011010010000100010101000011010010110101111101000110 =
0)
b110 <
b11111111 +
b11111111 1
1$
#1786000
b101000 A
#1790000
0$
#1795000
b100001101001000010001010100001101001011010111110100001000110000 =
b10 <
1$
#1796000
b101001 A
#1800000
0$
#1805000
b10010010100111001000011 =
1-
b11 <
1$
#1806000
b101010 A
#1810000
0$
#1815000
1.
0-
b10001000100010101000011 =
1!
b100 <
b1001 *
b1001 >
1$
#1816000
b101011 A
#1820000
0$
#1825000
b101001101001000010010010100011001010100 =
0.
1)
b101 <
b111 2
1$
#1826000
b101100 A
#1830000
0$
#1835000
0)
b1000011010010000100010101000011010010110101111101000110 =
b110 <
b1111111 +
b1111111 1
1$
#1836000
b101101 A
#1840000
0$
#1845000
b100001101001000010001010100001101001011010111110100001000110000 =
b10 <
1$
#1846000
b101110 A
#1850000
0$
#1855000
1-
b10010010100111001000011 =
b11 <
1$
#1856000
b101111 A
#1860000
0$
#1865000
b10001000100010101000011 =
1.
0-
0!
b100 <
b1010 *
b1010 >
1$
#1866000
b110000 A
#1870000
0$
#1875000
0.
1)
b101001101001000010010010100011001010100 =
b101 <
b110 2
1$
#1876000
b110001 A
#1880000
0$
#1885000
b1000011010010000100010101000011010010110101111101000110 =
0)
b110 <
b111111 +
b111111 1
1$
#1886000
b110010 A
#1890000
0$
#1895000
b100001101001000010001010100001101001011010111110100001000110000 =
b10 <
1$
#1896000
b110011 A
#1900000
0$
#1905000
b10010010100111001000011 =
1-
b11 <
1$
#1906000
b110100 A
#1910000
0$
