Algoritmos/division/Core/Control.v
module control (clk, rst, start, z, z_co, done, sh, load, load_ac, r0, dec);
  
  input  clk;
   input  rst;
  input  start;
  input  z;       
  input  z_co;     
  
output reg done;
output reg sh;
  output reg load;
  output reg load_ac;
output reg r0;
  output reg dec;
 
  parameter START   = 3'b000;
  parameter SHIFT   = 3'b001;
  parameter CHECK   = 3'b010;
  parameter SUB     = 3'b011;
  parameter CHK_CO  = 3'b100;
  parameter END_ST  = 3'b101;
 
  reg [2:0] state;
  reg [3:0] count;
  
  always @(posedge clk or posedge rst ) begin
    if (rst) begin
        state <= START;
        count <= 4'b0;
    end
    else begin
        case (state)
        

         START: begin
                if(start)
                    state <= SHIFT;
              else
                    state <= START;
            end

         SHIFT: begin
                state <= CHECK;
            end

            CHECK: begin
               if(z)
                    state <= SUB;
                else
                    state <= CHK_CO;
            end

            SUB: begin
               state <= CHK_CO;
            end

            CHK_CO: begin
              if(z_co)
                    state <= END_ST;
                else
                    state <= SHIFT;
            end

            END_ST: begin
              if(start)
                    state <= START;
                else
                  state <= END_ST;
            end

            default: begin
               state <= START;
            end

        endcase
    end
end
  
  always @(*) begin
      case (state)
      
     START:   begin 
          done=0;
          sh=0; 
        load=1; 
          load_ac=0; 
          r0=0; 
          dec=0; 
        end
    SHIFT:   begin 
          done=0; 
          sh=1; 
         load=0; 
          load_ac=0; 
          r0=0; 
          dec=1; 
        end
    CHECK:   begin 
         done=0; 
          sh=0; 
         load=0; 
          load_ac=0; 
          r0=0; 
          dec=0; 
        end
      SUB:     begin 
          done=0; 
          sh=0; 
          load=0; 
          load_ac=1; 
          r0=1; 
          dec=0; 
        end
    CHK_CO:  begin 
          done=0; 
          sh=0; 
          load=0; 
          load_ac=0; 
          r0=0; 
          dec=0; 
        end
      END_ST:  begin 
          done=1; 
          sh=0; 
           load=0; 
          load_ac=0; 
          r0=0; 
          dec=0; 
        end
        default: begin 
          done=0; 
          sh=0; 
          load=0; 
          load_ac=0; 
          r0=0; 
          dec=0; 
        end
      endcase
    end
  

`define BENCH
`ifdef BENCH
  reg [8*40:1] state_name;
  always @(*) begin
    case (state)
      START:      state_name = "START";
      SHIFT: state_name = "SHIFT";
      CHECK:       state_name = "CHECK";
      SUB:       state_name = "SUB";
      CHK_CO:     state_name = "CHK_CO";
      END_ST:     state_name = "END";
    endcase
  end
`endif
endmodule

Algoritmos/division/Core/cont.v
module contador(clk, rst, load, dec, z_co);
  input  clk;
  input  rst;   
  input  load;    
  input  dec;     
  output z_co;    
 
reg [4:0] count;
 
  assign z_co = (count == 5'b0);
 
  always @(posedge clk) begin
    if (rst)
      count <= 5'd16;         
 else if (load)
      count <= 5'd16;         
    else if (dec)
      count <= count - 1'b1;  
  end
endmodule

Algoritmos/division/Core/Comp_aca.v
module comparador_aca (Ac, A, z);
  input  [15:0] Ac;
  input  [15:0] A;
  output        z;
 
  assign z = (Ac >= A) ? 1'b1 : 1'b0;
endmodule

Algoritmos/division/Core/Corr_r.v
module corrimiento_r (clk, rst, shift, load, r0, s_r);
  input        clk;
  input        rst;
  input        shift;
  input        load;
  input        r0;
  output reg [15:0] s_r;
 
  always @(negedge clk) begin
    if (rst)
      s_r = 16'b0;
    else if (load)
      s_r = 16'b0;
    else begin
      if (shift) s_r = s_r << 1;
      else if (r0)    s_r[0] = 1'b1;
    end
  end
endmodule

Algoritmos/division/Core/res.v
module resta_ac (Ac, A, ac_out);
  input  [15:0] Ac;
  input  [15:0] A;
  output [15:0] ac_out;
 
  assign ac_out = Ac - A;
endmodule

Algoritmos/division/Core/Corr_acb.v
module Corrimiento_acb (clk, rst, in_B, ac_sub, shift, load, load_ac, s_acb);
  input        clk;
  input        init;
  input  [15:0] in_B;     
  input  [15:0] ac_sub;   
  input        shift;    
  input        load;      
  input        load_ac;   
  output reg [31:0] s_acb;
  
  always @(negedge clk) begin
    if (rst)
      s_acb = 32'b0;                       
    else if (load)
      s_acb = {16'b0, in_B};              
    else begin
      if (shift)   s_acb = s_acb << 1;     
      if (load_ac) s_acb[31:16] = ac_sub;  
    end
  end
endmodule

Algoritmos/division/Core/div.v
module div(clk, rst, start, A, B, cociente, done);
  input        clk, rst;   
  input        start;   
  input  [15:0] A;      
  input  [15:0] B;      
  output [15:0] cociente;
  output        done;
 
  wire w_sh;            
  wire w_load;          
  wire w_load_ac;       
  wire w_r0;            
  wire w_dec;           
  wire w_z;             
  wire w_z_co;          
  wire w_msb;           
  wire [31:0] w_acb;    
  wire [15:0] w_ac_sub; 
 
  Corrimiento_acb    corr_acb (.clk(clk), .rst(rst),.in_B(B), .ac_sub(w_ac_sub),.shift(w_sh), .load(w_load), .load_ac(w_load_ac),.s_acb(w_acb));
  resta_ac     dec (.Ac(w_acb[31:16]), .A(A), .ac_out(w_ac_sub));
  corrimiento_r      corr_r   (.clk(clk), .rst(rst),.shift(w_sh), .load(w_load), .r0(w_r0),.s_r(cociente));
  comparador_aca   comp(.Ac(w_acb[31:16]), .A(A), .z(w_z));
  contador cnt      (.clk(clk), .rst(rst),.load(w_load), .dec(w_dec), .z_co(w_z_co));
  control ctrl    (.clk(clk), .rst(rst),.start(start), .z(w_z), .z_co(w_z_co),.done(done), .sh(w_sh), .load(w_load),.load_ac(w_load_ac), .r0(w_r0), .dec(w_dec));
  
endmodule

Algoritmos/division/Core/TB/div_TB.v
`timescale 1ns / 1ps

module div_TB;
  reg         clk;
  reg         rst;
  reg         start;
  reg  [15:0] A;
  reg  [15:0] B;
  wire [15:0] cociente;
  wire        done;

  div uut (.clk(clk),.rst(rst),.start(start),.A(A),.B(B),.cociente(cociente),.done(done) );

  always #5 clk = ~clk;

  task run_case;
    input [15:0] dividend;
    input [15:0] divisor;
    input [15:0] expected;
    integer cycles;
    begin
      @(negedge clk);
      A     = divisor;
      B     = dividend;
      start = 1;

      // The current FSM needs two edges to restart from its END state.
      repeat (2) @(posedge clk);
      @(negedge clk);
      start = 0;

      cycles = 0;
      while ((done !== 1'b1) && (cycles < 200)) begin
        @(posedge clk);
        #1;
        cycles = cycles + 1;
      end

      if (done !== 1'b1) begin
        $display("div_TB FAIL: timeout para %0d / %0d", dividend, divisor);
        $fatal(1);
      end

      if (cociente !== expected) begin
        $display("div_TB FAIL: %0d / %0d esperado=%0d obtenido=%0d",
                 dividend, divisor, expected, cociente);
        $fatal(1);
      end

      $display("div_TB OK: %0d / %0d = %0d (%0d ciclos)",
               dividend, divisor, cociente, cycles);
    end
  endtask

  initial begin
    $dumpfile("TB/div_TB.vcd");
    $dumpvars(0, div_TB);

    clk   = 0;
    rst   = 1;
    start = 0;
    A     = 0;
    B     = 0;

    repeat (2) @(posedge clk);
    @(negedge clk);
    rst = 0;

    run_case(16'd50,    16'd2,   16'd25);
    run_case(16'd27,    16'd5,   16'd5);
    run_case(16'd7,     16'd10,  16'd0);
    run_case(16'd0,     16'd7,   16'd0);
    run_case(16'hffff,  16'd1,   16'hffff);
    run_case(16'hffff,  16'd255, 16'd257);

    $display("div_TB PASS");
    $finish;
  end
endmodule

Algoritmos/division/Core/TB/div_TB.vcd
$date
	Tue Jul 14 18:04:48 2026
$end
$version
	Icarus Verilog
$end
$timescale
	1ps
$end
$scope module div_TB $end
$var wire 1 ! done $end
$var wire 16 " cociente [15:0] $end
$var reg 16 # A [15:0] $end
$var reg 16 $ B [15:0] $end
$var reg 1 % clk $end
$var reg 1 & rst $end
$var reg 1 ' start $end
$scope module uut $end
$var wire 16 ( A [15:0] $end
$var wire 16 ) B [15:0] $end
$var wire 1 % clk $end
$var wire 1 & rst $end
$var wire 1 ' start $end
$var wire 1 * w_z_co $end
$var wire 1 + w_z $end
$var wire 1 , w_sh $end
$var wire 1 - w_r0 $end
$var wire 1 . w_load_ac $end
$var wire 1 / w_load $end
$var wire 1 0 w_dec $end
$var wire 32 1 w_acb [31:0] $end
$var wire 16 2 w_ac_sub [15:0] $end
$var wire 1 ! done $end
$var wire 16 3 cociente [15:0] $end
$scope module cnt $end
$var wire 1 % clk $end
$var wire 1 & rst $end
$var wire 1 * z_co $end
$var wire 1 / load $end
$var wire 1 0 dec $end
$var reg 5 4 count [4:0] $end
$upscope $end
$scope module comp $end
$var wire 16 5 A [15:0] $end
$var wire 16 6 Ac [15:0] $end
$var wire 1 + z $end
$upscope $end
$scope module corr_acb $end
$var wire 1 % clk $end
$var wire 16 7 in_B [15:0] $end
$var wire 1 & rst $end
$var wire 1 , shift $end
$var wire 1 . load_ac $end
$var wire 1 / load $end
$var wire 16 8 ac_sub [15:0] $end
$var reg 32 9 s_acb [31:0] $end
$upscope $end
$scope module corr_r $end
$var wire 1 % clk $end
$var wire 1 & rst $end
$var wire 1 , shift $end
$var wire 1 - r0 $end
$var wire 1 / load $end
$var reg 16 : s_r [15:0] $end
$upscope $end
$scope module ctrl $end
$var wire 1 % clk $end
$var wire 1 & rst $end
$var wire 1 ' start $end
$var wire 1 + z $end
$var wire 1 * z_co $end
$var parameter 3 ; CHECK $end
$var parameter 3 < CHK_CO $end
$var parameter 3 = END_ST $end
$var parameter 3 > SHIFT $end
$var parameter 3 ? START $end
$var parameter 3 @ SUB $end
$var reg 4 A count [3:0] $end
$var reg 1 0 dec $end
$var reg 1 ! done $end
$var reg 1 / load $end
$var reg 1 . load_ac $end
$var reg 1 - r0 $end
$var reg 1 , sh $end
$var reg 3 B state [2:0] $end
$var reg 320 C state_name [320:1] $end
$upscope $end
$scope module dec $end
$var wire 16 D A [15:0] $end
$var wire 16 E Ac [15:0] $end
$var wire 16 F ac_out [15:0] $end
$upscope $end
$upscope $end
$scope task run_case $end
$var reg 16 G dividend [15:0] $end
$var reg 16 H divisor [15:0] $end
$var reg 16 I expected [15:0] $end
$var integer 32 J cycles [31:0] $end
$upscope $end
$upscope $end
$enddefinitions $end
$comment Show the parameter values. $end
$dumpall
b11 @
b0 ?
b1 >
b101 =
b100 <
b10 ;
$end
#0
$dumpvars
bx J
bx I
bx H
bx G
bx F
bx E
b0 D
b101001101010100010000010101001001010100 C
b0 B
b0 A
b0 :
bx 9
bx 8
b0 7
bx 6
b0 5
bx 4
b0 3
bx 2
bx 1
00
1/
0.
0-
0,
x+
x*
b0 )
b0 (
0'
1&
0%
b0 $
b0 #
b0 "
0!
$end
#5000
1+
b0 6
b0 2
b0 8
b0 F
b0 E
b0 1
b0 9
0*
b10000 4
1%
#10000
0%
#15000
1%
#20000
b11001 I
b10 H
b110010 G
0&
0%
#25000
1%
#30000
0+
1'
b110010 $
b110010 )
b110010 7
b1111111111111110 2
b1111111111111110 8
b1111111111111110 F
b10 #
b10 (
b10 5
b10 D
0%
#35000
10
0/
1,
b101001101001000010010010100011001010100 C
b1 B
b110010 1
b110010 9
1%
#40000
0%
#45000
b100001101001000010001010100001101001011 C
00
0,
b10 B
b1100100 1
b1100100 9
b1111 4
1%
#50000
b0 J
0'
0%
#55000
b10000110100100001001011010111110100001101001111 C
b100 B
1%
#56000
b1 J
#60000
0%
#65000
b101001101001000010010010100011001010100 C
10
1,
b1 B
1%
#66000
b10 J
#70000
0%
#75000
00
0,
b100001101001000010001010100001101001011 C
b10 B
b1110 4
b11001000 1
b11001000 9
1%
#76000
b11 J
#80000
0%
#85000
b10000110100100001001011010111110100001101001111 C
b100 B
1%
#86000
b100 J
#90000
0%
#95000
10
1,
b101001101001000010010010100011001010100 C
b1 B
1%
#96000
b101 J
#100000
0%
#105000
b100001101001000010001010100001101001011 C
00
0,
b10 B
b110010000 1
b110010000 9
b1101 4
1%
#106000
b110 J
#110000
0%
#115000
b10000110100100001001011010111110100001101001111 C
b100 B
1%
#116000
b111 J
#120000
0%
#125000
b101001101001000010010010100011001010100 C
10
1,
b1 B
1%
#126000
b1000 J
#130000
0%
#135000
00
0,
b100001101001000010001010100001101001011 C
b10 B
b1100 4
b1100100000 1
b1100100000 9
1%
#136000
b1001 J
#140000
0%
#145000
b10000110100100001001011010111110100001101001111 C
b100 B
1%
#146000
b1010 J
#150000
0%
#155000
10
1,
b101001101001000010010010100011001010100 C
b1 B
1%
#156000
b1011 J
#160000
0%
#165000
b100001101001000010001010100001101001011 C
00
0,
b10 B
b11001000000 1
b11001000000 9
b1011 4
1%
#166000
b1100 J
#170000
0%
#175000
b10000110100100001001011010111110100001101001111 C
b100 B
1%
#176000
b1101 J
#180000
0%
#185000
b101001101001000010010010100011001010100 C
10
1,
b1 B
1%
#186000
b1110 J
#190000
0%
#195000
00
0,
b100001101001000010001010100001101001011 C
b10 B
b1010 4
b110010000000 1
b110010000000 9
1%
#196000
b1111 J
#200000
0%
#205000
b10000110100100001001011010111110100001101001111 C
b100 B
1%
#206000
b10000 J
#210000
0%
#215000
10
1,
b101001101001000010010010100011001010100 C
b1 B
1%
#216000
b10001 J
#220000
0%
#225000
b100001101001000010001010100001101001011 C
00
0,
b10 B
b1100100000000 1
b1100100000000 9
b1001 4
1%
#226000
b10010 J
#230000
0%
#235000
b10000110100100001001011010111110100001101001111 C
b100 B
1%
#236000
b10011 J
#240000
0%
#245000
b101001101001000010010010100011001010100 C
10
1,
b1 B
1%
#246000
b10100 J
#250000
0%
#255000
00
0,
b100001101001000010001010100001101001011 C
b10 B
b1000 4
b11001000000000 1
b11001000000000 9
1%
#256000
b10101 J
#260000
0%
#265000
b10000110100100001001011010111110100001101001111 C
b100 B
1%
#266000
b10110 J
#270000
0%
#275000
10
1,
b101001101001000010010010100011001010100 C
b1 B
1%
#276000
b10111 J
#280000
0%
#285000
b100001101001000010001010100001101001011 C
00
0,
b10 B
b110010000000000 1
b110010000000000 9
b111 4
1%
#286000
b11000 J
#290000
0%
#295000
b10000110100100001001011010111110100001101001111 C
b100 B
1%
#296000
b11001 J
#300000
0%
#305000
b101001101001000010010010100011001010100 C
10
1,
b1 B
1%
#306000
b11010 J
#310000
0%
#315000
00
0,
b100001101001000010001010100001101001011 C
b10 B
b110 4
b1100100000000000 1
b1100100000000000 9
1%
#316000
b11011 J
#320000
0%
#325000
b10000110100100001001011010111110100001101001111 C
b100 B
1%
#326000
b11100 J
#330000
0%
#335000
10
1,
b101001101001000010010010100011001010100 C
b1 B
1%
#336000
b11101 J
#340000
0%
#345000
b100001101001000010001010100001101001011 C
00
0,
b1 6
b1111111111111111 2
b1111111111111111 8
b1111111111111111 F
b1 E
b10 B
b11001000000000000 1
b11001000000000000 9
b101 4
1%
#346000
b11110 J
#350000
0%
#355000
b10000110100100001001011010111110100001101001111 C
b100 B
1%
#356000
b11111 J
#360000
0%
#365000
b101001101001000010010010100011001010100 C
10
1,
b1 B
1%
#366000
b100000 J
#370000
0%
#375000
1+
00
0,
b100001101001000010001010100001101001011 C
b11 6
b1 2
b1 8
b1 F
b11 E
b10 B
b100 4
b110010000000000000 1
b110010000000000000 9
1%
#376000
b100001 J
#380000
0%
#385000
b10100110101010101000010 C
1-
1.
b11 B
1%
#386000
b100010 J
#390000
b1 "
b1 3
b1 :
0%
#395000
0+
0-
0.
b10000110100100001001011010111110100001101001111 C
b1 6
b1111111111111111 2
b1111111111111111 8
b1111111111111111 F
b1 E
b100 B
b10010000000000000 1
b10010000000000000 9
1%
#396000
b100011 J
#400000
0%
#405000
b101001101001000010010010100011001010100 C
10
1,
b1 B
1%
#406000
b100100 J
#410000
b10 "
b10 3
b10 :
0%
#415000
1+
00
0,
b100001101001000010001010100001101001011 C
b10 6
b0 2
b0 8
b0 F
b10 E
b10 B
b11 4
b100100000000000000 1
b100100000000000000 9
1%
#416000
b100101 J
#420000
0%
#425000
b10100110101010101000010 C
1-
1.
b11 B
1%
#426000
b100110 J
#430000
b11 "
b11 3
b11 :
0%
#435000
0+
0-
0.
b10000110100100001001011010111110100001101001111 C
b0 6
b1111111111111110 2
b1111111111111110 8
b1111111111111110 F
b0 E
b100 B
b100000000000000 1
b100000000000000 9
1%
#436000
b100111 J
#440000
0%
#445000
b101001101001000010010010100011001010100 C
10
1,
b1 B
1%
#446000
b101000 J
#450000
b110 "
b110 3
b110 :
0%
#455000
00
0,
b100001101001000010001010100001101001011 C
b10 B
b10 4
b1000000000000000 1
b1000000000000000 9
1%
#456000
b101001 J
#460000
0%
#465000
b10000110100100001001011010111110100001101001111 C
b100 B
1%
#466000
b101010 J
#470000
0%
#475000
10
1,
b101001101001000010010010100011001010100 C
b1 B
1%
#476000
b101011 J
#480000
b1100 "
b1100 3
b1100 :
0%
#485000
b100001101001000010001010100001101001011 C
00
0,
b1 6
b1111111111111111 2
b1111111111111111 8
b1111111111111111 F
b1 E
b10 B
b10000000000000000 1
b10000000000000000 9
b1 4
1%
#486000
b101100 J
#490000
0%
#495000
b10000110100100001001011010111110100001101001111 C
b100 B
1%
#496000
b101101 J
#500000
0%
#505000
b101001101001000010010010100011001010100 C
10
1,
b1 B
1%
#506000
b101110 J
#510000
b11000 "
b11000 3
b11000 :
0%
#515000
1+
00
0,
b100001101001000010001010100001101001011 C
b10 6
b0 2
b0 8
b0 F
b10 E
b10 B
1*
b0 4
b100000000000000000 1
b100000000000000000 9
1%
#516000
b101111 J
#520000
0%
#525000
b10100110101010101000010 C
1-
1.
b11 B
1%
#526000
b110000 J
#530000
b11001 "
b11001 3
b11001 :
0%
#535000
0+
0-
0.
b10000110100100001001011010111110100001101001111 C
b0 6
b1111111111111110 2
b1111111111111110 8
b1111111111111110 F
b0 E
b100 B
b0 1
b0 9
1%
#536000
b110001 J
#540000
0%
#545000
b10001010100111001000100 C
1!
b101 B
1%
#546000
b101 I
b101 H
b11011 G
b110010 J
#550000
1'
b11011 $
b11011 )
b11011 7
b1111111111111011 2
b1111111111111011 8
b1111111111111011 F
b101 #
b101 (
b101 5
b101 D
0%
#555000
1/
0!
b101001101010100010000010101001001010100 C
b0 B
1%
#560000
b0 "
b0 3
b0 :
0%
#565000
b101001101001000010010010100011001010100 C
10
0/
1,
b1 B
b11011 1
b11011 9
0*
b10000 4
1%
#570000
b0 J
0'
0%
#575000
00
0,
b100001101001000010001010100001101001011 C
b10 B
b1111 4
b110110 1
b110110 9
1%
#576000
b1 J
#580000
0%
#585000
b10000110100100001001011010111110100001101001111 C
b100 B
1%
#586000
b10 J
#590000
0%
#595000
10
1,
b101001101001000010010010100011001010100 C
b1 B
1%
#596000
b11 J
#600000
0%
#605000
b100001101001000010001010100001101001011 C
00
0,
b10 B
b1101100 1
b1101100 9
b1110 4
1%
#606000
b100 J
#610000
0%
#615000
b10000110100100001001011010111110100001101001111 C
b100 B
1%
#616000
b101 J
#620000
0%
#625000
b101001101001000010010010100011001010100 C
10
1,
b1 B
1%
#626000
b110 J
#630000
0%
#635000
00
0,
b100001101001000010001010100001101001011 C
b10 B
b1101 4
b11011000 1
b11011000 9
1%
#636000
b111 J
#640000
0%
#645000
b10000110100100001001011010111110100001101001111 C
b100 B
1%
#646000
b1000 J
#650000
0%
#655000
10
1,
b101001101001000010010010100011001010100 C
b1 B
1%
#656000
b1001 J
#660000
0%
#665000
b100001101001000010001010100001101001011 C
00
0,
b10 B
b110110000 1
b110110000 9
b1100 4
1%
#666000
b1010 J
#670000
0%
#675000
b10000110100100001001011010111110100001101001111 C
b100 B
1%
#676000
b1011 J
#680000
0%
#685000
b101001101001000010010010100011001010100 C
10
1,
b1 B
1%
#686000
b1100 J
#690000
0%
#695000
00
0,
b100001101001000010001010100001101001011 C
b10 B
b1011 4
b1101100000 1
b1101100000 9
1%
#696000
b1101 J
#700000
0%
#705000
b10000110100100001001011010111110100001101001111 C
b100 B
1%
#706000
b1110 J
#710000
0%
#715000
10
1,
b101001101001000010010010100011001010100 C
b1 B
1%
#716000
b1111 J
#720000
0%
#725000
b100001101001000010001010100001101001011 C
00
0,
b10 B
b11011000000 1
b11011000000 9
b1010 4
1%
#726000
b10000 J
#730000
0%
#735000
b10000110100100001001011010111110100001101001111 C
b100 B
1%
#736000
b10001 J
#740000
0%
#745000
b101001101001000010010010100011001010100 C
10
1,
b1 B
1%
#746000
b10010 J
#750000
0%
#755000
00
0,
b100001101001000010001010100001101001011 C
b10 B
b1001 4
b110110000000 1
b110110000000 9
1%
#756000
b10011 J
#760000
0%
#765000
b10000110100100001001011010111110100001101001111 C
b100 B
1%
#766000
b10100 J
#770000
0%
#775000
10
1,
b101001101001000010010010100011001010100 C
b1 B
1%
#776000
b10101 J
#780000
0%
#785000
b100001101001000010001010100001101001011 C
00
0,
b10 B
b1101100000000 1
b1101100000000 9
b1000 4
1%
#786000
b10110 J
#790000
0%
#795000
b10000110100100001001011010111110100001101001111 C
b100 B
1%
#796000
b10111 J
#800000
0%
#805000
b101001101001000010010010100011001010100 C
10
1,
b1 B
1%
#806000
b11000 J
#810000
0%
#815000
00
0,
b100001101001000010001010100001101001011 C
b10 B
b111 4
b11011000000000 1
b11011000000000 9
1%
#816000
b11001 J
#820000
0%
#825000
b10000110100100001001011010111110100001101001111 C
b100 B
1%
#826000
b11010 J
#830000
0%
#835000
10
1,
b101001101001000010010010100011001010100 C
b1 B
1%
#836000
b11011 J
#840000
0%
#845000
b100001101001000010001010100001101001011 C
00
0,
b10 B
b110110000000000 1
b110110000000000 9
b110 4
1%
#846000
b11100 J
#850000
0%
#855000
b10000110100100001001011010111110100001101001111 C
b100 B
1%
#856000
b11101 J
#860000
0%
#865000
b101001101001000010010010100011001010100 C
10
1,
b1 B
1%
#866000
b11110 J
#870000
0%
#875000
00
0,
b100001101001000010001010100001101001011 C
b10 B
b101 4
b1101100000000000 1
b1101100000000000 9
1%
#876000
b11111 J
#880000
0%
#885000
b10000110100100001001011010111110100001101001111 C
b100 B
1%
#886000
b100000 J
#890000
0%
#895000
10
1,
b101001101001000010010010100011001010100 C
b1 B
1%
#896000
b100001 J
#900000
0%
#905000
b100001101001000010001010100001101001011 C
00
0,
b1 6
b1111111111111100 2
b1111111111111100 8
b1111111111111100 F
b1 E
b10 B
b11011000000000000 1
b11011000000000000 9
b100 4
1%
#906000
b100010 J
#910000
0%
#915000
b10000110100100001001011010111110100001101001111 C
b100 B
1%
#916000
b100011 J
#920000
0%
#925000
b101001101001000010010010100011001010100 C
10
1,
b1 B
1%
#926000
b100100 J
#930000
0%
#935000
00
0,
b100001101001000010001010100001101001011 C
b11 6
b1111111111111110 2
b1111111111111110 8
b1111111111111110 F
b11 E
b10 B
b11 4
b110110000000000000 1
b110110000000000000 9
1%
#936000
b100101 J
#940000
0%
#945000
b10000110100100001001011010111110100001101001111 C
b100 B
1%
#946000
b100110 J
#950000
0%
#955000
10
1,
b101001101001000010010010100011001010100 C
b1 B
1%
#956000
b100111 J
#960000
0%
#965000
1+
b100001101001000010001010100001101001011 C
00
0,
b110 6
b1 2
b1 8
b1 F
b110 E
b10 B
b1101100000000000000 1
b1101100000000000000 9
b10 4
1%
#966000
b101000 J
#970000
0%
#975000
1-
1.
b10100110101010101000010 C
b11 B
1%
#976000
b101001 J
#980000
b1 "
b1 3
b1 :
0%
#985000
0+
b10000110100100001001011010111110100001101001111 C
0-
0.
b1 6
b1111111111111100 2
b1111111111111100 8
b1111111111111100 F
b1 E
b100 B
b11100000000000000 1
b11100000000000000 9
1%
#986000
b101010 J
#990000
0%
#995000
10
1,
b101001101001000010010010100011001010100 C
b1 B
1%
#996000
b101011 J
#1000000
b10 "
b10 3
b10 :
0%
#1005000
b100001101001000010001010100001101001011 C
00
0,
b11 6
b1111111111111110 2
b1111111111111110 8
b1111111111111110 F
b11 E
b10 B
b111000000000000000 1
b111000000000000000 9
b1 4
1%
#1006000
b101100 J
#1010000
0%
#1015000
b10000110100100001001011010111110100001101001111 C
b100 B
1%
#1016000
b101101 J
#1020000
0%
#1025000
b101001101001000010010010100011001010100 C
10
1,
b1 B
1%
#1026000
b101110 J
#1030000
b100 "
b100 3
b100 :
0%
#1035000
1+
00
0,
b100001101001000010001010100001101001011 C
b111 6
b10 2
b10 8
b10 F
b111 E
b10 B
1*
b0 4
b1110000000000000000 1
b1110000000000000000 9
1%
#1036000
b101111 J
#1040000
0%
#1045000
b10100110101010101000010 C
1-
1.
b11 B
1%
#1046000
b110000 J
#1050000
b101 "
b101 3
b101 :
0%
#1055000
0+
0-
0.
b10000110100100001001011010111110100001101001111 C
b10 6
b1111111111111101 2
b1111111111111101 8
b1111111111111101 F
b10 E
b100 B
b100000000000000000 1
b100000000000000000 9
1%
#1056000
b110001 J
#1060000
0%
#1065000
b10001010100111001000100 C
1!
b101 B
1%
#1066000
b0 I
b1010 H
b111 G
b110010 J
#1070000
1'
b111 $
b111 )
b111 7
b1111111111111000 2
b1111111111111000 8
b1111111111111000 F
b1010 #
b1010 (
b1010 5
b1010 D
0%
#1075000
1/
0!
b101001101010100010000010101001001010100 C
b0 B
1%
#1080000
b0 "
b0 3
b0 :
0%
#1085000
b101001101001000010010010100011001010100 C
10
0/
1,
b0 6
b1111111111110110 2
b1111111111110110 8
b1111111111110110 F
b0 E
b1 B
b111 1
b111 9
0*
b10000 4
1%
#1090000
b0 J
0'
0%
#1095000
00
0,
b100001101001000010001010100001101001011 C
b10 B
b1111 4
b1110 1
b1110 9
1%
#1096000
b1 J
#1100000
0%
#1105000
b10000110100100001001011010111110100001101001111 C
b100 B
1%
#1106000
b10 J
#1110000
0%
#1115000
10
1,
b101001101001000010010010100011001010100 C
b1 B
1%
#1116000
b11 J
#1120000
0%
#1125000
b100001101001000010001010100001101001011 C
00
0,
b10 B
b11100 1
b11100 9
b1110 4
1%
#1126000
b100 J
#1130000
0%
#1135000
b10000110100100001001011010111110100001101001111 C
b100 B
1%
#1136000
b101 J
#1140000
0%
#1145000
b101001101001000010010010100011001010100 C
10
1,
b1 B
1%
#1146000
b110 J
#1150000
0%
#1155000
00
0,
b100001101001000010001010100001101001011 C
b10 B
b1101 4
b111000 1
b111000 9
1%
#1156000
b111 J
#1160000
0%
#1165000
b10000110100100001001011010111110100001101001111 C
b100 B
1%
#1166000
b1000 J
#1170000
0%
#1175000
10
1,
b101001101001000010010010100011001010100 C
b1 B
1%
#1176000
b1001 J
#1180000
0%
#1185000
b100001101001000010001010100001101001011 C
00
0,
b10 B
b1110000 1
b1110000 9
b1100 4
1%
#1186000
b1010 J
#1190000
0%
#1195000
b10000110100100001001011010111110100001101001111 C
b100 B
1%
#1196000
b1011 J
#1200000
0%
#1205000
b101001101001000010010010100011001010100 C
10
1,
b1 B
1%
#1206000
b1100 J
#1210000
0%
#1215000
00
0,
b100001101001000010001010100001101001011 C
b10 B
b1011 4
b11100000 1
b11100000 9
1%
#1216000
b1101 J
#1220000
0%
#1225000
b10000110100100001001011010111110100001101001111 C
b100 B
1%
#1226000
b1110 J
#1230000
0%
#1235000
10
1,
b101001101001000010010010100011001010100 C
b1 B
1%
#1236000
b1111 J
#1240000
0%
#1245000
b100001101001000010001010100001101001011 C
00
0,
b10 B
b111000000 1
b111000000 9
b1010 4
1%
#1246000
b10000 J
#1250000
0%
#1255000
b10000110100100001001011010111110100001101001111 C
b100 B
1%
#1256000
b10001 J
#1260000
0%
#1265000
b101001101001000010010010100011001010100 C
10
1,
b1 B
1%
#1266000
b10010 J
#1270000
0%
#1275000
00
0,
b100001101001000010001010100001101001011 C
b10 B
b1001 4
b1110000000 1
b1110000000 9
1%
#1276000
b10011 J
#1280000
0%
#1285000
b10000110100100001001011010111110100001101001111 C
b100 B
1%
#1286000
b10100 J
#1290000
0%
#1295000
10
1,
b101001101001000010010010100011001010100 C
b1 B
1%
#1296000
b10101 J
#1300000
0%
#1305000
b100001101001000010001010100001101001011 C
00
0,
b10 B
b11100000000 1
b11100000000 9
b1000 4
1%
#1306000
b10110 J
#1310000
0%
#1315000
b10000110100100001001011010111110100001101001111 C
b100 B
1%
#1316000
b10111 J
#1320000
0%
#1325000
b101001101001000010010010100011001010100 C
10
1,
b1 B
1%
#1326000
b11000 J
#1330000
0%
#1335000
00
0,
b100001101001000010001010100001101001011 C
b10 B
b111 4
b111000000000 1
b111000000000 9
1%
#1336000
b11001 J
#1340000
0%
#1345000
b10000110100100001001011010111110100001101001111 C
b100 B
1%
#1346000
b11010 J
#1350000
0%
#1355000
10
1,
b101001101001000010010010100011001010100 C
b1 B
1%
#1356000
b11011 J
#1360000
0%
#1365000
b100001101001000010001010100001101001011 C
00
0,
b10 B
b1110000000000 1
b1110000000000 9
b110 4
1%
#1366000
b11100 J
#1370000
0%
#1375000
b10000110100100001001011010111110100001101001111 C
b100 B
1%
#1376000
b11101 J
#1380000
0%
#1385000
b101001101001000010010010100011001010100 C
10
1,
b1 B
1%
#1386000
b11110 J
#1390000
0%
#1395000
00
0,
b100001101001000010001010100001101001011 C
b10 B
b101 4
b11100000000000 1
b11100000000000 9
1%
#1396000
b11111 J
#1400000
0%
#1405000
b10000110100100001001011010111110100001101001111 C
b100 B
1%
#1406000
b100000 J
#1410000
0%
#1415000
10
1,
b101001101001000010010010100011001010100 C
b1 B
1%
#1416000
b100001 J
#1420000
0%
#1425000
b100001101001000010001010100001101001011 C
00
0,
b10 B
b111000000000000 1
b111000000000000 9
b100 4
1%
#1426000
b100010 J
#1430000
0%
#1435000
b10000110100100001001011010111110100001101001111 C
b100 B
1%
#1436000
b100011 J
#1440000
0%
#1445000
b101001101001000010010010100011001010100 C
10
1,
b1 B
1%
#1446000
b100100 J
#1450000
0%
#1455000
00
0,
b100001101001000010001010100001101001011 C
b10 B
b11 4
b1110000000000000 1
b1110000000000000 9
1%
#1456000
b100101 J
#1460000
0%
#1465000
b10000110100100001001011010111110100001101001111 C
b100 B
1%
#1466000
b100110 J
#1470000
0%
#1475000
10
1,
b101001101001000010010010100011001010100 C
b1 B
1%
#1476000
b100111 J
#1480000
0%
#1485000
b100001101001000010001010100001101001011 C
00
0,
b1 6
b1111111111110111 2
b1111111111110111 8
b1111111111110111 F
b1 E
b10 B
b11100000000000000 1
b11100000000000000 9
b10 4
1%
#1486000
b101000 J
#1490000
0%
