Algoritmos/division/Core/Control.v
module control (clk, rst, start, z, z_co, done, sh, load, load_ac, r0, dec);
  
  input  clk;
   input  rst;
  input  start;
  input  z;       
  input  z_co;     
  
output reg done;
output reg sh;
  output reg load;
  output reg load_ac;
output reg r0;
  output reg dec;
 
  parameter START   = 3'b000;
  parameter SHIFT   = 3'b001;
  parameter CHECK   = 3'b010;
  parameter SUB     = 3'b011;
  parameter CHK_CO  = 3'b100;
  parameter END_ST  = 3'b101;
 
  reg [2:0] state;
  reg [3:0] count;
  
  always @(posedge clk or posedge rst ) begin
    if (rst) begin
        state <= START;
        count <= 4'b0;
    end
    else begin
        case (state)
        

         START: begin
                if(start)
                    state <= SHIFT;
              else
                    state <= START;
            end

         SHIFT: begin
                state <= CHECK;
            end

            CHECK: begin
               if(z)
                    state <= SUB;
                else
                    state <= CHK_CO;
            end

            SUB: begin
               state <= CHK_CO;
            end

            CHK_CO: begin
              if(z_co)
                    state <= END_ST;
                else
                    state <= SHIFT;
            end

            END_ST: begin
              if(start)
                    state <= START;
                else
                  state <= END_ST;
            end

            default: begin
               state <= START;
            end

        endcase
    end
end
  
  always @(*) begin
      case (state)
      
     START:   begin 
          done=0;
          sh=0; 
        load=1; 
          load_ac=0; 
          r0=0; 
          dec=0; 
        end
    SHIFT:   begin 
          done=0; 
          sh=1; 
         load=0; 
          load_ac=0; 
          r0=0; 
          dec=1; 
        end
    CHECK:   begin 
         done=0; 
          sh=0; 
         load=0; 
          load_ac=0; 
          r0=0; 
          dec=0; 
        end
      SUB:     begin 
          done=0; 
          sh=0; 
          load=0; 
          load_ac=1; 
          r0=1; 
          dec=0; 
        end
    CHK_CO:  begin 
          done=0; 
          sh=0; 
          load=0; 
          load_ac=0; 
          r0=0; 
          dec=0; 
        end
      END_ST:  begin 
          done=1; 
          sh=0; 
           load=0; 
          load_ac=0; 
          r0=0; 
          dec=0; 
        end
        default: begin 
          done=0; 
          sh=0; 
          load=0; 
          load_ac=0; 
          r0=0; 
          dec=0; 
        end
      endcase
    end
  

`define BENCH
`ifdef BENCH
  reg [8*40:1] state_name;
  always @(*) begin
    case (state)
      START:      state_name = "START";
      SHIFT: state_name = "SHIFT";
      CHECK:       state_name = "CHECK";
      SUB:       state_name = "SUB";
      CHK_CO:     state_name = "CHK_CO";
      END_ST:     state_name = "END";
    endcase
  end
`endif
endmodule

Algoritmos/division/Core/cont.v
module contador(clk, rst, load, dec, z_co);
  input  clk;
  input  rst;   
  input  load;    
  input  dec;     
  output z_co;    
 
  reg [4:0] count;
 
  assign z_co = (count == 5'b0);
 
  always @(negedge clk) begin
    if (rst)
      count <= 5'd16;         
    else if (load)
      count <= 5'd16;         
    else if (dec)
      count <= count - 1'b1;  
  end
endmodule

Algoritmos/division/Core/Comp_aca.v
module comparador_aca (Ac, A, z);
  input  [15:0] Ac;
  input  [15:0] A;
  output        z;
 
  assign z = (Ac >= A) ? 1'b1 : 1'b0;
endmodule

Algoritmos/division/Core/Corr_r.v
module corrimiento_r (clk, rst, shift, load, r0, s_r);
  input        clk;
  input        rst;
  input        shift;
  input        load;
  input        r0;
  output reg [15:0] s_r;
 
  always @(negedge clk) begin
    if (rst)
      s_r = 16'b0;
    else if (load)
      s_r = 16'b0;
    else begin
      if (shift) s_r = s_r << 1;
      else if (r0)    s_r[0] = 1'b1;
    end
  end
endmodule

Algoritmos/division/Core/res.v
module resta_ac (Ac, A, ac_out);
  input  [15:0] Ac;
  input  [15:0] A;
  output [15:0] ac_out;
 
  assign ac_out = Ac - A;
endmodule

Algoritmos/division/Core/Corr_acb.v
module Corrimiento_acb (clk, rst, in_B, ac_sub, shift, load, load_ac, s_acb);
  input        clk;
  input        init;
  input  [15:0] in_B;     
  input  [15:0] ac_sub;   
  input        shift;    
  input        load;      
  input        load_ac;   
  output reg [31:0] s_acb;
  
  always @(negedge clk) begin
    if (rst)
      s_acb = 32'b0;                       
    else if (load)
      s_acb = {16'b0, in_B};              
    else begin
      if (shift)   s_acb = s_acb << 1;     
      if (load_ac) s_acb[31:16] = ac_sub;  
    end
  end
endmodule

Algoritmos/division/Core/div.v
module div(clk, rst, start, A, B, cociente, done);
  input        clk, rst;   
  input        start;   
  input  [15:0] A;      
  input  [15:0] B;      
  output [15:0] cociente;
  output        done;
 
  wire w_sh;            
  wire w_load;          
  wire w_load_ac;       
  wire w_r0;            
  wire w_dec;           
  wire w_z;             
  wire w_z_co;          
  wire w_msb;           
  wire [31:0] w_acb;    
  wire [15:0] w_ac_sub; 
 
  Corrimiento_acb    corr_acb (.clk(clk), .rst(rst),.in_B(B), .ac_sub(w_ac_sub),.shift(w_sh), .load(w_load), .load_ac(w_load_ac),.s_acb(w_acb));
  resta_ac     dec (.Ac(w_acb[31:16]), .A(A), .ac_out(w_ac_sub));
  corrimiento_r      corr_r   (.clk(clk), .rst(rst),.shift(w_sh), .load(w_load), .r0(w_r0),.s_r(cociente));
  comparador_aca   comp(.Ac(w_acb[31:16]), .A(A), .z(w_z));
  contador cnt      (.clk(clk), .rst(rst),.load(w_load), .dec(w_dec), .z_co(w_z_co));
  control ctrl    (.clk(clk), .rst(rst),.start(start), .z(w_z), .z_co(w_z_co),.done(done), .sh(w_sh), .load(w_load),.load_ac(w_load_ac), .r0(w_r0), .dec(w_dec));
  
endmodule

Algoritmos/division/Core/peri_divi.v
module peripheral_div(clk , reset , d_in , cs , addr , rd , wr, d_out );
  
  input clk;
  input reset;
  input [15:0] d_in;
  input cs;
  input [4:0]  addr; // 4 LSB from j1_io_addr
  input rd;
  input wr;
  output reg [31:0]d_out;

//------------------------------------ regs and wires-------------------------------
reg [4:0] s; 	//selector mux_4  and write registers
reg [15:0] A;//---mult_32 input registers
reg [15:0] B;
reg init;
wire [31:0] result;	//mult_32 output Regs
wire done;
//------------------------------------ regs and wires-------------------------------
always @(*) begin//------address_decoder------------------------------
if (cs) begin
  case (addr)
    5'h04: s =  5'b00001; // A 
    5'h08: s =  5'b00010; // B
    5'h0C: s =  5'b00100; // init
    5'h10: s =  5'b01000; // result
    5'h14: s =  5'b10000; // done
    default: s = 5'b00000;
  endcase
end
else
  s = 5'b00000;
end//------------------address_decoder--------------------------------

always @(posedge clk) begin//-------------------- escritura de registros 

  if(reset) begin
    init = 0;
    A    = 0;
    B    = 0;
  end
  else begin
    if (cs && wr) begin
      A    = s[0] ? d_in    : A;	//Write Registers
      B    = s[1] ? d_in    : B;	//Write Registers
      init = s[2] ? d_in[0] : init;
    end
  end

end//------------------------------------------- escritura de registros

always @(posedge clk) begin//-----------------------mux_4 :  multiplexa salidas del periferico
  if(reset)
    d_out = 0;
  else 
  if (cs) begin
    case (s[4:0])
      5'b01000: d_out    =  result;
      5'b10000: d_out    = {31'b0, done};
    endcase
  end
end//-----------------------------------------------mux_4

//# ---------------------------------------#
//# ---------------------------------------#
//# Instanciacion del periferico division--#


div div1 (
 .rst(reset),
.clk(clk),
.start(init),
.done(done),
.cociente(result),
  .B(A),
.A(B)
);

endmodule

Algoritmos/division/Core/TB/peri_divi_TB.v
`timescale 1ns / 1ps

module peri_divi_TB;
  reg         clk;
  reg         reset;
  reg  [15:0] d_in;
  reg         cs;
  reg  [4:0]  addr;
  reg         rd;
  reg         wr;
  wire [31:0] d_out;

  peripheral_div uut (.clk(clk),.reset(reset),.d_in(d_in),.cs(cs),.addr(addr),.rd(rd),.wr(wr),.d_out(d_out));

  always #5 clk = ~clk;

  task write_register;
    input [4:0]  register_addr;
    input [15:0] value;
    begin
      @(negedge clk);
      cs   = 1;
      wr   = 1;
      rd   = 0;
      addr = register_addr;
      d_in = value;
      @(posedge clk);
      #1;
      @(negedge clk);
      cs   = 0;
      wr   = 0;
      addr = 0;
      d_in = 0;
    end
  endtask

  task read_register;
    input  [4:0]  register_addr;
    output [31:0] value;
    begin
      @(negedge clk);
      cs   = 1;
      wr   = 0;
      rd   = 1;
      addr = register_addr;
      @(posedge clk);
      #1 value = d_out;
      @(negedge clk);
      cs   = 0;
      rd   = 0;
      addr = 0;
    end
  endtask

  task run_case;
    input [15:0] dividend;
    input [15:0] divisor;
    input [31:0] expected;
    integer cycles;
    reg [31:0] status;
    reg [31:0] result;
    begin
      // The wrapper maps register A to the dividend and B to the divisor.
      write_register(5'h04, dividend);
      write_register(5'h08, divisor);
      write_register(5'h0c, 16'd1);

      repeat (2) @(posedge clk);
      write_register(5'h0c, 16'd0);

      cycles = 0;
      status = 0;
      while ((status[0] !== 1'b1) && (cycles < 200)) begin
        read_register(5'h14, status);
        cycles = cycles + 1;
      end

      if (status[0] !== 1'b1) begin
        $display("peri_divi_TB FAIL: timeout para %0d / %0d", dividend, divisor);
        $fatal(1);
      end

      read_register(5'h10, result);
      if (result !== expected) begin
        $display("peri_divi_TB FAIL: %0d / %0d esperado=%0d obtenido=%0d",
                 dividend, divisor, expected, result);
        $fatal(1);
      end

      $display("peri_divi_TB OK: %0d / %0d = %0d", dividend, divisor, result);
    end
  endtask

  initial begin
    $dumpfile("TB/peri_divi_TB.vcd");
    $dumpvars(0, peri_divi_TB);

    clk   = 0;
    reset = 1;
    d_in  = 0;
    cs    = 0;
    addr  = 0;
    rd    = 0;
    wr    = 0;

    repeat (2) @(posedge clk);
    @(negedge clk);
    reset = 0;

    run_case(16'd100, 16'd4,  32'd25);
    run_case(16'd27,  16'd5,  32'd5);

    $display("peri_divi_TB PASS");
    $finish;
  end
endmodule

Algoritmos/division/Core/TB/peri_divi_TB.vcd
$date
	Tue Jul 14 17:55:02 2026
$end
$version
	Icarus Verilog
$end
$timescale
	1ps
$end
$scope module peri_divi_TB $end
$var wire 32 ! d_out [31:0] $end
$var reg 5 " addr [4:0] $end
$var reg 1 # clk $end
$var reg 1 $ cs $end
$var reg 16 % d_in [15:0] $end
$var reg 1 & rd $end
$var reg 1 ' reset $end
$var reg 1 ( wr $end
$scope module uut $end
$var wire 5 ) addr [4:0] $end
$var wire 1 # clk $end
$var wire 1 $ cs $end
$var wire 16 * d_in [15:0] $end
$var wire 1 & rd $end
$var wire 1 ' reset $end
$var wire 1 ( wr $end
$var wire 32 + result [31:0] $end
$var wire 1 , done $end
$var reg 16 - A [15:0] $end
$var reg 16 . B [15:0] $end
$var reg 32 / d_out [31:0] $end
$var reg 1 0 init $end
$var reg 5 1 s [4:0] $end
$scope module div1 $end
$var wire 16 2 A [15:0] $end
$var wire 16 3 B [15:0] $end
$var wire 1 # clk $end
$var wire 1 ' rst $end
$var wire 1 0 start $end
$var wire 1 4 w_z_co $end
$var wire 1 5 w_z $end
$var wire 1 6 w_sh $end
$var wire 1 7 w_r0 $end
$var wire 1 8 w_load_ac $end
$var wire 1 9 w_load $end
$var wire 1 : w_dec $end
$var wire 32 ; w_acb [31:0] $end
$var wire 16 < w_ac_sub [15:0] $end
$var wire 1 , done $end
$var wire 16 = cociente [15:0] $end
$scope module cnt $end
$var wire 1 # clk $end
$var wire 1 ' rst $end
$var wire 1 4 z_co $end
$var wire 1 9 load $end
$var wire 1 : dec $end
$var reg 5 > count [4:0] $end
$upscope $end
$scope module comp $end
$var wire 16 ? A [15:0] $end
$var wire 16 @ Ac [15:0] $end
$var wire 1 5 z $end
$upscope $end
$scope module corr_acb $end
$var wire 1 # clk $end
$var wire 16 A in_B [15:0] $end
$var wire 1 ' rst $end
$var wire 1 6 shift $end
$var wire 1 8 load_ac $end
$var wire 1 9 load $end
$var wire 16 B ac_sub [15:0] $end
$var reg 32 C s_acb [31:0] $end
$upscope $end
$scope module corr_r $end
$var wire 1 # clk $end
$var wire 1 ' rst $end
$var wire 1 6 shift $end
$var wire 1 7 r0 $end
$var wire 1 9 load $end
$var reg 16 D s_r [15:0] $end
$upscope $end
$scope module ctrl $end
$var wire 1 # clk $end
$var wire 1 ' rst $end
$var wire 1 0 start $end
$var wire 1 5 z $end
$var wire 1 4 z_co $end
$var parameter 3 E CHECK $end
$var parameter 3 F CHK_CO $end
$var parameter 3 G END_ST $end
$var parameter 3 H SHIFT $end
$var parameter 3 I START $end
$var parameter 3 J SUB $end
$var reg 4 K count [3:0] $end
$var reg 1 : dec $end
$var reg 1 , done $end
$var reg 1 9 load $end
$var reg 1 8 load_ac $end
$var reg 1 7 r0 $end
$var reg 1 6 sh $end
$var reg 3 L state [2:0] $end
$var reg 320 M state_name [320:1] $end
$upscope $end
$scope module dec $end
$var wire 16 N A [15:0] $end
$var wire 16 O Ac [15:0] $end
$var wire 16 P ac_out [15:0] $end
$upscope $end
$upscope $end
$upscope $end
$scope task read_register $end
$var reg 5 Q register_addr [4:0] $end
$var reg 32 R value [31:0] $end
$upscope $end
$scope task run_case $end
$var reg 16 S dividend [15:0] $end
$var reg 16 T divisor [15:0] $end
$var reg 32 U expected [31:0] $end
$var reg 32 V result [31:0] $end
$var reg 32 W status [31:0] $end
$var integer 32 X cycles [31:0] $end
$upscope $end
$scope task write_register $end
$var reg 5 Y register_addr [4:0] $end
$var reg 16 Z value [15:0] $end
$upscope $end
$upscope $end
$enddefinitions $end
$comment Show the parameter values. $end
$dumpall
b11 J
b0 I
b1 H
b101 G
b100 F
b10 E
$end
#0
$dumpvars
bx Z
bx Y
bx X
bx W
bx V
bx U
bx T
bx S
bx R
bx Q
bx P
bx O
bx N
b101001101010100010000010101001001010100 M
b0 L
b0 K
b0 D
bx C
bx B
bx A
bx @
bx ?
bx >
b0 =
bx <
bx ;
0:
19
08
07
06
x5
x4
bx 3
bx 2
b0 1
x0
bx /
bx .
bx -
0,
b0 +
b0 *
b0 )
0(
1'
0&
b0 %
0$
0#
b0 "
bx !
$end
#5000
15
b0 @
b0 <
b0 B
b0 P
b0 O
b0 ;
b0 C
04
b10000 >
b0 .
b0 2
b0 ?
b0 N
b0 -
b0 3
b0 A
00
b0 !
b0 /
1#
#10000
0#
#15000
1#
#20000
b1100100 Z
b100 Y
b11001 U
b100 T
b1100100 S
0'
0#
#25000
1#
#30000
b1 1
b1100100 %
b1100100 *
b100 "
b100 )
1(
1$
0#
#35000
b1100100 -
b1100100 3
b1100100 A
1#
#40000
b0 1
b100 Z
b1000 Y
b0 %
b0 *
b0 "
b0 )
0(
0$
0#
#45000
b1100100 ;
b1100100 C
1#
#50000
b10 1
b100 %
b100 *
b1000 "
b1000 )
1(
1$
0#
#55000
05
b1111111111111100 <
b1111111111111100 B
b1111111111111100 P
b100 .
b100 2
b100 ?
b100 N
1#
#60000
b0 1
b1 Z
b1100 Y
b0 %
b0 *
b0 "
b0 )
0(
0$
0#
#65000
1#
#70000
b100 1
b1 %
b1 *
b1100 "
b1100 )
1(
1$
0#
#75000
1:
09
16
b101001101001000010010010100011001010100 M
b1 L
10
1#
#80000
b0 1
b0 %
b0 *
b0 "
b0 )
0(
0$
0#
#85000
b100001101001000010001010100001101001011 M
0:
06
b10 L
b11001000 ;
b11001000 C
b1111 >
1#
#90000
0#
#95000
b10000110100100001001011010111110100001101001111 M
b100 L
b0 Z
1#
#100000
b100 1
b1100 "
b1100 )
1(
1$
0#
#105000
b101001101001000010010010100011001010100 M
1:
16
b1 L
00
1#
#110000
b0 1
b10100 Q
b0 W
b0 X
b0 "
b0 )
0(
0$
0#
#115000
0:
06
b100001101001000010001010100001101001011 M
b10 L
b1110 >
b110010000 ;
b110010000 C
1#
#120000
b10000 1
b10100 "
b10100 )
1&
1$
0#
#125000
b10000110100100001001011010111110100001101001111 M
b100 L
1#
#126000
b0 R
#130000
b0 1
b1 X
b0 "
b0 )
0&
0$
0#
#135000
1:
16
b101001101001000010010010100011001010100 M
b1 L
1#
#140000
b10000 1
b10100 "
b10100 )
1&
1$
0#
#145000
b100001101001000010001010100001101001011 M
0:
06
b10 L
b1100100000 ;
b1100100000 C
b1101 >
1#
#150000
b0 1
b10 X
b0 "
b0 )
0&
0$
0#
#155000
b10000110100100001001011010111110100001101001111 M
b100 L
1#
#160000
b10000 1
b10100 "
b10100 )
1&
1$
0#
#165000
b101001101001000010010010100011001010100 M
1:
16
b1 L
1#
#170000
b0 1
b11 X
b0 "
b0 )
0&
0$
0#
#175000
0:
06
b100001101001000010001010100001101001011 M
b10 L
b1100 >
b11001000000 ;
b11001000000 C
1#
#180000
b10000 1
b10100 "
b10100 )
1&
1$
0#
#185000
b10000110100100001001011010111110100001101001111 M
b100 L
1#
#190000
b0 1
b100 X
b0 "
b0 )
0&
0$
0#
#195000
1:
16
b101001101001000010010010100011001010100 M
b1 L
1#
#200000
b10000 1
b10100 "
b10100 )
1&
1$
0#
#205000
b100001101001000010001010100001101001011 M
0:
06
b10 L
b110010000000 ;
b110010000000 C
b1011 >
1#
#210000
b0 1
b101 X
b0 "
b0 )
0&
0$
0#
#215000
b10000110100100001001011010111110100001101001111 M
b100 L
1#
#220000
b10000 1
b10100 "
b10100 )
1&
1$
0#
#225000
b101001101001000010010010100011001010100 M
1:
16
b1 L
1#
#230000
b0 1
b110 X
b0 "
b0 )
0&
0$
0#
#235000
0:
06
b100001101001000010001010100001101001011 M
b10 L
b1010 >
b1100100000000 ;
b1100100000000 C
1#
#240000
b10000 1
b10100 "
b10100 )
1&
1$
0#
#245000
b10000110100100001001011010111110100001101001111 M
b100 L
1#
#250000
b0 1
b111 X
b0 "
b0 )
0&
0$
0#
#255000
1:
16
b101001101001000010010010100011001010100 M
b1 L
1#
#260000
b10000 1
b10100 "
b10100 )
1&
1$
0#
#265000
b100001101001000010001010100001101001011 M
0:
06
b10 L
b11001000000000 ;
b11001000000000 C
b1001 >
1#
#270000
b0 1
b1000 X
b0 "
b0 )
0&
0$
0#
#275000
b10000110100100001001011010111110100001101001111 M
b100 L
1#
#280000
b10000 1
b10100 "
b10100 )
1&
1$
0#
#285000
b101001101001000010010010100011001010100 M
1:
16
b1 L
1#
#290000
b0 1
b1001 X
b0 "
b0 )
0&
0$
0#
#295000
0:
06
b100001101001000010001010100001101001011 M
b10 L
b1000 >
b110010000000000 ;
b110010000000000 C
1#
#300000
b10000 1
b10100 "
b10100 )
1&
1$
0#
#305000
b10000110100100001001011010111110100001101001111 M
b100 L
1#
#310000
b0 1
b1010 X
b0 "
b0 )
0&
0$
0#
#315000
1:
16
b101001101001000010010010100011001010100 M
b1 L
1#
#320000
b10000 1
b10100 "
b10100 )
1&
1$
0#
#325000
b100001101001000010001010100001101001011 M
0:
06
b10 L
b1100100000000000 ;
b1100100000000000 C
b111 >
1#
#330000
b0 1
b1011 X
b0 "
b0 )
0&
0$
0#
#335000
b10000110100100001001011010111110100001101001111 M
b100 L
1#
#340000
b10000 1
b10100 "
b10100 )
1&
1$
0#
#345000
b101001101001000010010010100011001010100 M
1:
16
b1 L
1#
#350000
b0 1
b1100 X
b0 "
b0 )
0&
0$
0#
#355000
0:
06
b100001101001000010001010100001101001011 M
b1 @
b1111111111111101 <
b1111111111111101 B
b1111111111111101 P
b1 O
b10 L
b110 >
b11001000000000000 ;
b11001000000000000 C
1#
#360000
b10000 1
b10100 "
b10100 )
1&
1$
0#
#365000
b10000110100100001001011010111110100001101001111 M
b100 L
1#
#370000
b0 1
b1101 X
b0 "
b0 )
0&
0$
0#
#375000
1:
16
b101001101001000010010010100011001010100 M
b1 L
1#
#380000
b10000 1
b10100 "
b10100 )
1&
1$
0#
#385000
b100001101001000010001010100001101001011 M
0:
06
b11 @
b1111111111111111 <
b1111111111111111 B
b1111111111111111 P
b11 O
b10 L
b110010000000000000 ;
b110010000000000000 C
b101 >
1#
#390000
b0 1
b1110 X
b0 "
b0 )
0&
0$
0#
#395000
b10000110100100001001011010111110100001101001111 M
b100 L
1#
#400000
b10000 1
b10100 "
b10100 )
1&
1$
0#
#405000
b101001101001000010010010100011001010100 M
1:
16
b1 L
1#
#410000
b0 1
b1111 X
b0 "
b0 )
0&
0$
0#
#415000
15
0:
06
b100001101001000010001010100001101001011 M
b110 @
b10 <
b10 B
b10 P
b110 O
b10 L
b100 >
b1100100000000000000 ;
b1100100000000000000 C
1#
#420000
b10000 1
b10100 "
b10100 )
1&
1$
0#
#425000
b10100110101010101000010 M
17
18
b11 L
1#
#430000
b1 +
b1 =
b1 D
b0 1
b10000 X
b0 "
b0 )
0&
0$
0#
#435000
05
07
08
b10000110100100001001011010111110100001101001111 M
b10 @
b1111111111111110 <
b1111111111111110 B
b1111111111111110 P
b10 O
b100 L
b100100000000000000 ;
b100100000000000000 C
1#
#440000
b10000 1
b10100 "
b10100 )
1&
1$
0#
#445000
b101001101001000010010010100011001010100 M
1:
16
b1 L
1#
#450000
b10 +
b10 =
b10 D
b0 1
b10001 X
b0 "
b0 )
0&
0$
0#
#455000
15
0:
06
b100001101001000010001010100001101001011 M
b100 @
b0 <
b0 B
b0 P
b100 O
b10 L
b11 >
b1001000000000000000 ;
b1001000000000000000 C
1#
#460000
b10000 1
b10100 "
b10100 )
1&
1$
0#
#465000
b10100110101010101000010 M
17
18
b11 L
1#
#470000
b11 +
b11 =
b11 D
b0 1
b10010 X
b0 "
b0 )
0&
0$
0#
#475000
05
07
08
b10000110100100001001011010111110100001101001111 M
b0 @
b1111111111111100 <
b1111111111111100 B
b1111111111111100 P
b0 O
b100 L
b1000000000000000 ;
b1000000000000000 C
1#
#480000
b10000 1
b10100 "
b10100 )
1&
1$
0#
#485000
b101001101001000010010010100011001010100 M
1:
16
b1 L
1#
#490000
b110 +
b110 =
b110 D
b0 1
b10011 X
b0 "
b0 )
0&
0$
0#
#495000
0:
06
b100001101001000010001010100001101001011 M
b1 @
b1111111111111101 <
b1111111111111101 B
b1111111111111101 P
b1 O
b10 L
b10 >
b10000000000000000 ;
b10000000000000000 C
1#
#500000
b10000 1
b10100 "
b10100 )
1&
1$
0#
#505000
b10000110100100001001011010111110100001101001111 M
b100 L
1#
#510000
b0 1
b10100 X
b0 "
b0 )
0&
0$
0#
#515000
1:
16
b101001101001000010010010100011001010100 M
b1 L
1#
#520000
b1100 +
b1100 =
b1100 D
b10000 1
b10100 "
b10100 )
1&
1$
0#
#525000
b100001101001000010001010100001101001011 M
0:
06
b10 @
b1111111111111110 <
b1111111111111110 B
b1111111111111110 P
b10 O
b10 L
b100000000000000000 ;
b100000000000000000 C
b1 >
1#
#530000
b0 1
b10101 X
b0 "
b0 )
0&
0$
0#
#535000
b10000110100100001001011010111110100001101001111 M
b100 L
1#
#540000
b10000 1
b10100 "
b10100 )
1&
1$
0#
#545000
b101001101001000010010010100011001010100 M
1:
16
b1 L
1#
#550000
b11000 +
b11000 =
b11000 D
b0 1
b10110 X
b0 "
b0 )
0&
0$
0#
#555000
15
0:
06
b100001101001000010001010100001101001011 M
b100 @
b0 <
b0 B
b0 P
b100 O
b10 L
14
b0 >
b1000000000000000000 ;
b1000000000000000000 C
1#
#560000
b10000 1
b10100 "
b10100 )
1&
1$
0#
#565000
b10100110101010101000010 M
17
18
b11 L
1#
#570000
b11001 +
b11001 =
b11001 D
b0 1
b10111 X
b0 "
b0 )
0&
0$
0#
#575000
05
07
08
b10000110100100001001011010111110100001101001111 M
b0 @
b1111111111111100 <
b1111111111111100 B
b1111111111111100 P
b0 O
b100 L
b0 ;
b0 C
1#
#580000
b10000 1
b10100 "
b10100 )
1&
1$
0#
#585000
b10001010100111001000100 M
1,
b101 L
1#
#590000
b0 1
b11000 X
b0 "
b0 )
0&
0$
0#
#595000
1#
#600000
b10000 1
b10100 "
b10100 )
1&
1$
0#
#605000
b1 !
b1 /
1#
#606000
b1 R
#610000
b0 1
b10000 Q
b11001 X
b1 W
b0 "
b0 )
0&
0$
0#
#615000
1#
#620000
b1000 1
b10000 "
b10000 )
1&
1$
0#
#625000
b11001 !
b11001 /
1#
#626000
b11001 R
#630000
b0 1
b11011 Z
b100 Y
b101 U
b101 T
b11011 S
b11001 V
b0 "
b0 )
0&
0$
0#
#635000
1#
#640000
b1 1
b11011 %
b11011 *
b100 "
b100 )
1(
1$
0#
#645000
b11011 -
b11011 3
b11011 A
1#
#650000
b0 1
b101 Z
b1000 Y
b0 %
b0 *
b0 "
b0 )
0(
0$
0#
#655000
1#
#660000
b10 1
b101 %
b101 *
b1000 "
b1000 )
1(
1$
0#
#665000
b1111111111111011 <
b1111111111111011 B
b1111111111111011 P
b101 .
b101 2
b101 ?
b101 N
1#
#670000
b0 1
b1 Z
b1100 Y
b0 %
b0 *
b0 "
b0 )
0(
0$
0#
#675000
1#
#680000
b100 1
b1 %
b1 *
b1100 "
b1100 )
1(
1$
0#
#685000
19
0,
b101001101010100010000010101001001010100 M
b0 L
10
1#
#690000
b0 +
b0 =
b0 D
b0 1
b0 %
b0 *
b0 "
b0 )
0(
0$
0#
#695000
b101001101001000010010010100011001010100 M
1:
09
16
b1 L
04
b10000 >
b11011 ;
b11011 C
1#
#700000
0#
#705000
0:
06
b100001101001000010001010100001101001011 M
b10 L
b110110 ;
b110110 C
b1111 >
b0 Z
1#
#710000
b100 1
b1100 "
b1100 )
1(
1$
0#
#715000
b10000110100100001001011010111110100001101001111 M
b100 L
00
1#
#720000
b0 1
b10100 Q
b0 W
b0 X
b0 "
b0 )
0(
0$
0#
#725000
1:
16
b101001101001000010010010100011001010100 M
b1 L
1#
#730000
b10000 1
b10100 "
b10100 )
1&
1$
0#
#735000
b100001101001000010001010100001101001011 M
0:
06
b10 L
b1110 >
b1101100 ;
b1101100 C
b0 !
b0 /
1#
#736000
b0 R
#740000
b0 1
b1 X
b0 "
b0 )
0&
0$
0#
#745000
b10000110100100001001011010111110100001101001111 M
b100 L
1#
#750000
b10000 1
b10100 "
b10100 )
1&
1$
0#
#755000
b101001101001000010010010100011001010100 M
1:
16
b1 L
1#
#760000
b0 1
b10 X
b0 "
b0 )
0&
0$
0#
#765000
0:
06
b100001101001000010001010100001101001011 M
b10 L
b11011000 ;
b11011000 C
b1101 >
1#
#770000
b10000 1
b10100 "
b10100 )
1&
1$
0#
#775000
b10000110100100001001011010111110100001101001111 M
b100 L
1#
#780000
b0 1
b11 X
b0 "
b0 )
0&
0$
0#
#785000
1:
16
b101001101001000010010010100011001010100 M
b1 L
1#
#790000
b10000 1
b10100 "
b10100 )
1&
1$
0#
#795000
b100001101001000010001010100001101001011 M
0:
06
b10 L
b1100 >
b110110000 ;
b110110000 C
1#
#800000
b0 1
b100 X
b0 "
b0 )
0&
0$
0#
#805000
b10000110100100001001011010111110100001101001111 M
b100 L
1#
#810000
b10000 1
b10100 "
b10100 )
1&
1$
0#
#815000
b101001101001000010010010100011001010100 M
1:
16
b1 L
1#
#820000
b0 1
b101 X
b0 "
b0 )
0&
0$
0#
#825000
0:
06
b100001101001000010001010100001101001011 M
b10 L
b1101100000 ;
b1101100000 C
b1011 >
1#
#830000
b10000 1
b10100 "
b10100 )
1&
1$
0#
#835000
b10000110100100001001011010111110100001101001111 M
b100 L
1#
#840000
b0 1
b110 X
b0 "
b0 )
0&
0$
0#
#845000
1:
16
b101001101001000010010010100011001010100 M
b1 L
1#
#850000
b10000 1
b10100 "
b10100 )
1&
1$
0#
#855000
b100001101001000010001010100001101001011 M
0:
06
b10 L
b1010 >
b11011000000 ;
b11011000000 C
1#
#860000
b0 1
b111 X
b0 "
b0 )
0&
0$
0#
#865000
b10000110100100001001011010111110100001101001111 M
b100 L
1#
#870000
b10000 1
b10100 "
b10100 )
1&
1$
0#
#875000
b101001101001000010010010100011001010100 M
1:
16
b1 L
1#
#880000
b0 1
b1000 X
b0 "
b0 )
0&
0$
0#
#885000
0:
06
b100001101001000010001010100001101001011 M
b10 L
b110110000000 ;
b110110000000 C
b1001 >
1#
#890000
b10000 1
b10100 "
b10100 )
1&
1$
0#
#895000
b10000110100100001001011010111110100001101001111 M
b100 L
1#
#900000
b0 1
b1001 X
b0 "
b0 )
0&
0$
0#
#905000
1:
16
b101001101001000010010010100011001010100 M
b1 L
1#
#910000
b10000 1
b10100 "
b10100 )
1&
1$
0#
#915000
b100001101001000010001010100001101001011 M
0:
06
b10 L
b1000 >
b1101100000000 ;
b1101100000000 C
1#
#920000
b0 1
b1010 X
b0 "
b0 )
0&
0$
0#
#925000
b10000110100100001001011010111110100001101001111 M
b100 L
1#
#930000
b10000 1
b10100 "
b10100 )
1&
1$
0#
#935000
b101001101001000010010010100011001010100 M
1:
16
b1 L
1#
#940000
b0 1
b1011 X
b0 "
b0 )
0&
0$
0#
#945000
0:
06
b100001101001000010001010100001101001011 M
b10 L
b11011000000000 ;
b11011000000000 C
b111 >
1#
#950000
b10000 1
b10100 "
b10100 )
1&
1$
0#
#955000
b10000110100100001001011010111110100001101001111 M
b100 L
1#
#960000
b0 1
b1100 X
b0 "
b0 )
0&
0$
0#
#965000
1:
16
b101001101001000010010010100011001010100 M
b1 L
1#
#970000
b10000 1
b10100 "
b10100 )
1&
1$
0#
#975000
b100001101001000010001010100001101001011 M
0:
06
b10 L
b110 >
b110110000000000 ;
b110110000000000 C
1#
#980000
b0 1
b1101 X
b0 "
b0 )
0&
0$
0#
#985000
b10000110100100001001011010111110100001101001111 M
b100 L
1#
#990000
b10000 1
b10100 "
b10100 )
1&
1$
0#
#995000
b101001101001000010010010100011001010100 M
1:
16
b1 L
1#
#1000000
b0 1
b1110 X
b0 "
b0 )
0&
0$
0#
#1005000
0:
06
b100001101001000010001010100001101001011 M
b10 L
b1101100000000000 ;
b1101100000000000 C
b101 >
1#
#1010000
b10000 1
b10100 "
b10100 )
1&
1$
0#
#1015000
b10000110100100001001011010111110100001101001111 M
b100 L
1#
#1020000
b0 1
b1111 X
b0 "
b0 )
0&
0$
0#
#1025000
1:
16
b101001101001000010010010100011001010100 M
b1 L
1#
#1030000
b10000 1
b10100 "
b10100 )
1&
1$
0#
#1035000
b100001101001000010001010100001101001011 M
0:
06
b1 @
b1111111111111100 <
b1111111111111100 B
b1111111111111100 P
b1 O
b10 L
b100 >
b11011000000000000 ;
b11011000000000000 C
1#
#1040000
b0 1
b10000 X
b0 "
b0 )
0&
0$
0#
