Algoritmos/bcd_binario/Core/control_bin.v
module control_bin(
    input clk,
    input rst,
    input init,
    input z,
    output reg done,
    output reg sh,
    output reg load,
    output reg ld_acc
);

    parameter START  = 3'b000;
    parameter SHIFT  = 3'b001;
    parameter CHECK1 = 3'b010;
    parameter CHECK2 = 3'b011;
    parameter ACC    = 3'b100;
    parameter END_ST = 3'b101;

    reg [2:0] state;

    initial begin
        done = 0;
        sh = 0;
        load = 0;
        ld_acc = 0;
        state = START;
    end

    always @(posedge clk) begin
        if (rst) begin
            state = START;
            done = 0;
            sh = 0;
            load = 0;
            ld_acc = 0;
        end else begin
            case(state)
                START: begin
                    done = 0;
                    sh = 0;
                    ld_acc = 0;
                    if (init) begin
                        load = 1;      
                        state = SHIFT;
                    end else begin
                        load = 0;      
                        state = START;
                    end
                end

                SHIFT: begin
                    done = 0;
                    sh = 1;
                    load = 0;
                    ld_acc = 0;
                    if (z)
                        state = END_ST;
                    else
                        state = CHECK1;
                end

                CHECK1: begin
                    done = 0;
                    sh = 0;
                    load = 0;
                    ld_acc = 0;
                    if (z)
                        state = END_ST;
                    else
                        state = CHECK2;
                end

                CHECK2: begin
                    done = 0;
                    sh = 0;
                    load = 0;
                    ld_acc = 1;
                    state = ACC;
                end

                ACC: begin
                    done = 0;
                    sh = 0;
                    load = 0;
                    ld_acc = 0;
                    state = SHIFT;
                end

                END_ST: begin
                    done = 1;          
                    sh = 0;
                    load = 0;         
                    ld_acc = 0;
                    
                    if (init) begin
                        load <= 1;      
                        state <= SHIFT;
                    end else begin
                        state <= END_ST
                end

                default: state <= START;
            endcase
        end
    end
endmodule

Algoritmos/BCD - BINARIO/Archivos Verilog/counter_bin.v
module counter_bin(
    input clk,
    input rst,
    input load,
    input dec,
    output reg [3:0] count,
    output z
);

    always @(negedge clk) begin
        if (rst) begin
            count <= 4'd8;
        end else if (load) begin
            count <= 4'd8;
        end else if (dec) begin
            count <= count - 4'd1;
        end else begin
            count <= count;
        end
    end
    assign z = (count == 4'd0) ? 1'b1 : 1'b0;

endmodule

Algoritmos/BCD - BINARIO/Archivos Verilog/comp_bin.v
module comp_bin(
    input [3:0] nibble_in,
    output [3:0] nibble_out
);
    reg [3:0] tmp;
    
    always @(*) begin
        if (nibble_in >= 4'd8)
            tmp = nibble_in - 4'd3;
        else
            tmp = nibble_in;
    end
    
    assign nibble_out = tmp;
endmodule

Algoritmos/bcd_binario/Core/rsr_bin.v
module rsr_bin(
    input clk,
    input rst,
    input load,
    input shift,
    input ld_acc,
    input [7:0] in_data,
    input [3:0] sub_high,
    input [3:0] sub_low,
    output reg [15:0] r0,
    output [7:0] result
);

    always @(negedge clk) begin
        if (rst) begin
            r0 <= 16'h0000;
        end else if (load) begin
            r0 <= {in_data, 8'h00};
        end else if (shift) begin
            r0 <= r0 >> 1;
        end else if (ld_acc) begin
            r0 <= {sub_high, sub_low, r0[7:0]};
        end else begin
            r0 <= r0;
        end
    end
    assign result = r0[7:0];

endmodule

Algoritmos/BCD - BINARIO/Archivos Verilog/bcd_to_bin.v
module bcd_to_bin(
    input clk,
    input rst,
    input init,
    input [7:0] in_data,
    output [7:0] result,
    output done
);

    wire w_sh;
    wire w_load;
    wire w_ld_acc;
    wire w_z;
    wire [15:0] w_r0;
    wire [3:0] w_sub_high;
    wire [3:0] w_sub_low;

    rsr_bin rsr0 (
        .clk(clk),
        .rst(rst),
        .load(w_load),
        .shift(w_sh),
        .ld_acc(w_ld_acc),
        .in_data(in_data),
        .sub_high(w_sub_high),
        .sub_low(w_sub_low),
        .r0(w_r0),
        .result(result)
    );

    comp_bin comp_high (
        .nibble_in(w_r0[15:12]),
        .nibble_out(w_sub_high)
    );

    comp_bin comp_low (
        .nibble_in(w_r0[11:8]),
        .nibble_out(w_sub_low)
    );

    counter_bin counter0 (
        .clk(clk),
        .rst(rst),
        .load(w_load),
        .dec(w_sh),
        .count(),
        .z(w_z)
    );

    control_bin control0 (
        .clk(clk),
        .rst(rst),
        .init(init),
        .z(w_z),
        .done(done),
        .sh(w_sh),
        .load(w_load),
        .ld_acc(w_ld_acc)
    );

endmodule

Algoritmos/bcd_binario/Core/bcd_to_bin_TB.v
`timescale 1ns / 1ps
`define SIMULATION
module bcd_to_bin_TB;
    reg clk;
    reg rst;
    reg reset;
    reg start;
    reg [7:0] in_data;
    wire [7:0] result;
    wire done;

    bcd_to_bin uut (
        .clk(clk),
        .rst(rst),
        .init(start),
        .in_data(in_data),
        .result(result),
        .done(done)
    );

    parameter PERIOD          = 20;
    parameter real DUTY_CYCLE = 0.5;
    parameter OFFSET          = 0;
    reg [20:0] i;
    event reset_trigger;
    event reset_done_trigger;

    initial begin 
        forever begin 
            @ (reset_trigger);
            @ (negedge clk);
            rst = 1;
            @ (negedge clk);
            rst = 0;
            -> reset_done_trigger;
        end
    end

    initial begin // Initialize Inputs
        clk = 0;
        reset = 1; 
        start = 0; 
        in_data = 8'h45;
    end

    initial begin // Process for clk
        #OFFSET;
        forever begin
            clk = 1'b0;
            #(PERIOD-(PERIOD*DUTY_CYCLE)) clk = 1'b1;
            #(PERIOD*DUTY_CYCLE);
        end
    end

    initial begin // Reset the system, Start test cases
        #10 -> reset_trigger;
        @ (reset_done_trigger);
        @ (posedge clk);
        start = 0;
        @ (posedge clk);
        start = 1;
        for(i=0; i<2; i=i+1) begin
            @ (posedge clk);
        end
        start = 0;
        
        for(i=0; i<25; i=i+1) begin
            @ (posedge clk);
        end

        in_data = 8'h78;
        @ (posedge clk);
        start = 1;
        for(i=0; i<2; i=i+1) begin
            @ (posedge clk);
        end
        start = 0;
        for(i=0; i<25; i=i+1) begin
            @ (posedge clk);
        end

        in_data = 8'h99;
        @ (posedge clk);
        start = 1;
        for(i=0; i<2; i=i+1) begin
            @ (posedge clk);
        end
        start = 0;
        for(i=0; i<25; i=i+1) begin
            @ (posedge clk);
        end
    end	 

    initial begin: TEST_CASE
        $dumpfile("bcd_to_bin_TB.vcd");
        $dumpvars(-1, uut);
        #((PERIOD*DUTY_CYCLE)*250) $finish;
    end
endmodule

Algoritmos/BCD - BINARIO/Archivos Verilog/bcd_to_bin_TB.vcd
$date
	Mon Jul 13 22:32:27 2026
$end
$version
	Icarus Verilog
$end
$timescale
	1ps
$end
$scope module bcd_to_bin_TB $end
$scope module uut $end
$var wire 1 ! clk $end
$var wire 8 " in_data [7:0] $end
$var wire 1 # init $end
$var wire 1 $ rst $end
$var wire 1 % w_z $end
$var wire 4 & w_sub_low [3:0] $end
$var wire 4 ' w_sub_high [3:0] $end
$var wire 1 ( w_sh $end
$var wire 16 ) w_r0 [15:0] $end
$var wire 1 * w_load $end
$var wire 1 + w_ld_acc $end
$var wire 8 , result [7:0] $end
$var wire 1 - done $end
$scope module comp_high $end
$var wire 4 . nibble_in [3:0] $end
$var wire 4 / nibble_out [3:0] $end
$var reg 4 0 tmp [3:0] $end
$upscope $end
$scope module comp_low $end
$var wire 4 1 nibble_in [3:0] $end
$var wire 4 2 nibble_out [3:0] $end
$var reg 4 3 tmp [3:0] $end
$upscope $end
$scope module control0 $end
$var wire 1 ! clk $end
$var wire 1 # init $end
$var wire 1 $ rst $end
$var wire 1 % z $end
$var parameter 3 4 ACC $end
$var parameter 3 5 CHECK1 $end
$var parameter 3 6 CHECK2 $end
$var parameter 3 7 END_ST $end
$var parameter 3 8 SHIFT $end
$var parameter 3 9 START $end
$var reg 1 - done $end
$var reg 1 + ld_acc $end
$var reg 1 * load $end
$var reg 1 ( sh $end
$var reg 3 : state [2:0] $end
$upscope $end
$scope module counter0 $end
$var wire 1 ! clk $end
$var wire 1 ( dec $end
$var wire 1 * load $end
$var wire 1 $ rst $end
$var wire 1 % z $end
$var reg 4 ; count [3:0] $end
$upscope $end
$scope module rsr0 $end
$var wire 1 ! clk $end
$var wire 8 < in_data [7:0] $end
$var wire 1 + ld_acc $end
$var wire 1 * load $end
$var wire 1 $ rst $end
$var wire 1 ( shift $end
$var wire 4 = sub_high [3:0] $end
$var wire 4 > sub_low [3:0] $end
$var wire 8 ? result [7:0] $end
$var reg 16 @ r0 [15:0] $end
$upscope $end
$upscope $end
$upscope $end
$enddefinitions $end
$comment Show the parameter values. $end
$dumpall
b0 9
b1 8
b101 7
b11 6
b10 5
b100 4
$end
#0
$dumpvars
bx @
bx ?
bx >
bx =
b1000101 <
bx ;
b0 :
bx 3
bx 2
bx 1
bx 0
bx /
bx .
0-
bx ,
0+
0*
bx )
0(
bx '
bx &
x%
x$
0#
b1000101 "
0!
$end
#10000
1!
#20000
b0 &
b0 2
b0 >
b0 3
b0 '
b0 /
b0 =
b0 0
0%
b0 ,
b0 ?
b0 1
b0 .
b1000 ;
b0 )
b0 @
1$
0!
#30000
1!
#40000
0$
0!
#50000
1!
#60000
0!
#70000
1#
1!
#80000
0!
#90000
b1 :
1*
1!
#100000
b101 &
b101 2
b101 >
b101 3
b100 '
b100 /
b100 =
b100 0
b101 1
b100 .
b100010100000000 )
b100010100000000 @
0!
#110000
b10 :
0*
1(
0#
1!
#120000
b10 &
b10 2
b10 >
b10 3
b10 '
b10 /
b10 =
b10 0
b10000000 ,
b10000000 ?
b10 1
b10 .
b10001010000000 )
b10001010000000 @
b111 ;
0!
#130000
b11 :
0(
1!
#140000
0!
#150000
b100 :
1+
1!
#160000
0!
#170000
b1 :
0+
1!
#180000
0!
#190000
b10 :
1(
1!
#200000
b1 &
b1 2
b1 >
b1 3
b1 '
b1 /
b1 =
b1 0
b1000000 ,
b1000000 ?
b1 1
b1 .
b1000101000000 )
b1000101000000 @
b110 ;
0!
#210000
b11 :
0(
1!
#220000
0!
#230000
b100 :
1+
1!
#240000
0!
#250000
b1 :
0+
1!
#260000
0!
#270000
b10 :
1(
1!
#280000
b101 &
b101 2
b101 >
b101 3
b0 '
b0 /
b0 =
b0 0
b10100000 ,
b10100000 ?
b1000 1
b0 .
b100010100000 )
b100010100000 @
b101 ;
0!
#290000
b11 :
0(
1!
#300000
0!
#310000
b100 :
1+
1!
#320000
b101 1
b10110100000 )
b10110100000 @
0!
#330000
b1 :
0+
1!
#340000
0!
#350000
b10 :
1(
1!
#360000
b10 &
b10 2
b10 >
b10 3
b11010000 ,
b11010000 ?
b10 1
b1011010000 )
b1011010000 @
b100 ;
0!
#370000
b11 :
0(
1!
#380000
0!
#390000
b100 :
1+
1!
#400000
0!
#410000
b1 :
0+
1!
#420000
0!
#430000
b10 :
1(
1!
#440000
b1 &
b1 2
b1 >
b1 3
b1101000 ,
b1101000 ?
b1 1
b101101000 )
b101101000 @
b11 ;
0!
#450000
b11 :
0(
1!
#460000
0!
#470000
b100 :
1+
1!
#480000
0!
#490000
b1 :
0+
1!
#500000
0!
#510000
b10 :
1(
1!
#520000
b0 &
b0 2
b0 >
b0 3
b10110100 ,
b10110100 ?
b0 1
b10110100 )
b10110100 @
b10 ;
0!
#530000
b11 :
0(
1!
#540000
0!
#550000
b100 :
1+
1!
#560000
0!
#570000
b1 :
0+
1!
#580000
0!
#590000
b10 :
1(
1!
#600000
b1011010 ,
b1011010 ?
b1011010 )
b1011010 @
b1 ;
0!
#610000
b11 :
0(
1!
#620000
0!
#630000
b100 :
1+
1!
#640000
0!
#650000
b1 :
0+
1!
#660000
0!
#670000
b10 :
1(
1!
#680000
b101101 ,
b101101 ?
1%
b101101 )
b101101 @
b0 ;
0!
#690000
b101 :
0(
1!
#700000
0!
#710000
1-
1!
#720000
0!
#730000
1!
#740000
0!
#750000
1!
#760000
0!
#770000
1!
#780000
0!
#790000
1!
#800000
0!
#810000
1!
#820000
0!
#830000
1!
#840000
0!
#850000
1!
#860000
0!
#870000
1!
#880000
0!
#890000
1!
#900000
0!
#910000
b1111000 "
b1111000 <
1!
#920000
0!
#930000
b1 :
1*
1#
1!
#940000
b101 &
b101 2
b101 >
b101 3
b111 '
b111 /
b111 =
b111 0
0%
b0 ,
b0 ?
b1000 1
b111 .
b1000 ;
b111100000000000 )
b111100000000000 @
0!
#950000
b10 :
0*
1(
0-
1!
#960000
b1001 &
b1001 2
b1001 >
b1001 3
b11 '
b11 /
b11 =
b11 0
b1100 1
b11 .
b11110000000000 )
b11110000000000 @
b111 ;
0!
#970000
b11 :
0(
0#
1!
#980000
0!
#990000
b100 :
1+
1!
#1000000
b110 &
b110 2
b110 >
b110 3
b1001 1
b11100100000000 )
b11100100000000 @
0!
#1010000
b1 :
0+
1!
#1020000
0!
#1030000
b10 :
1(
1!
#1040000
b1001 &
b1001 2
b1001 >
b1001 3
b1 '
b1 /
b1 =
b1 0
b10000000 ,
b10000000 ?
b1100 1
b1 .
b1110010000000 )
b1110010000000 @
b110 ;
0!
#1050000
b11 :
0(
1!
#1060000
0!
#1070000
b100 :
1+
1!
#1080000
b110 &
b110 2
b110 >
b110 3
b1001 1
b1100110000000 )
b1100110000000 @
0!
#1090000
b1 :
0+
1!
#1100000
0!
#1110000
b10 :
1(
1!
#1120000
b1001 &
b1001 2
b1001 >
b1001 3
b0 '
b0 /
b0 =
b0 0
b11000000 ,
b11000000 ?
b1100 1
b0 .
b110011000000 )
b110011000000 @
b101 ;
0!
#1130000
b11 :
0(
1!
#1140000
0!
#1150000
b100 :
1+
1!
#1160000
b110 &
b110 2
b110 >
b110 3
b1001 1
b100111000000 )
b100111000000 @
0!
#1170000
b1 :
0+
1!
#1180000
0!
#1190000
b10 :
1(
1!
#1200000
b100 &
b100 2
b100 >
b100 3
b11100000 ,
b11100000 ?
b100 1
b10011100000 )
b10011100000 @
b100 ;
0!
#1210000
b11 :
0(
1!
#1220000
0!
#1230000
b100 :
1+
1!
#1240000
0!
#1250000
b1 :
0+
1!
#1260000
0!
#1270000
b10 :
1(
1!
#1280000
b10 &
b10 2
b10 >
b10 3
b1110000 ,
b1110000 ?
b10 1
b1001110000 )
b1001110000 @
b11 ;
0!
#1290000
b11 :
0(
1!
#1300000
0!
#1310000
b100 :
1+
1!
#1320000
0!
#1330000
b1 :
0+
1!
#1340000
0!
#1350000
b10 :
1(
1!
#1360000
b1 &
b1 2
b1 >
b1 3
b111000 ,
b111000 ?
b1 1
b100111000 )
b100111000 @
b10 ;
0!
#1370000
b11 :
0(
1!
#1380000
0!
#1390000
b100 :
1+
1!
#1400000
0!
#1410000
b1 :
0+
1!
#1420000
0!
#1430000
b10 :
1(
1!
#1440000
b0 &
b0 2
b0 >
b0 3
b10011100 ,
b10011100 ?
b0 1
b10011100 )
b10011100 @
b1 ;
0!
#1450000
b11 :
0(
1!
#1460000
0!
#1470000
b100 :
1+
1!
#1480000
0!
#1490000
b1 :
0+
1!
#1500000
0!
#1510000
b10 :
1(
1!
#1520000
b1001110 ,
b1001110 ?
1%
b1001110 )
b1001110 @
b0 ;
0!
#1530000
b101 :
0(
1!
#1540000
0!
#1550000
1-
1!
#1560000
0!
#1570000
1!
#1580000
0!
#1590000
1!
#1600000
0!
#1610000
1!
#1620000
0!
#1630000
1!
#1640000
0!
#1650000
1!
#1660000
0!
#1670000
1!
#1680000
0!
#1690000
1!
#1700000
0!
#1710000
1!
#1720000
0!
#1730000
1!
#1740000
0!
#1750000
1!
#1760000
0!
#1770000
b10011001 "
b10011001 <
1!
#1780000
0!
#1790000
1#
1!
#1800000
0!
#1810000
b1 :
1*
1!
#1820000
b110 &
b110 2
b110 >
b110 3
b110 '
b110 /
b110 =
b110 0
0%
b0 ,
b0 ?
b1001 1
b1001 .
b1000 ;
b1001100100000000 )
b1001100100000000 @
0!
#1830000
b10 :
0*
1(
0-
0#
1!
#1840000
b1001 &
b1001 2
b1001 >
b1001 3
b100 '
b100 /
b100 =
b100 0
b10000000 ,
b10000000 ?
b1100 1
b100 .
b100110010000000 )
b100110010000000 @
b111 ;
0!
#1850000
b11 :
0(
1!
#1860000
0!
#1870000
b100 :
1+
1!
#1880000
b110 &
b110 2
b110 >
b110 3
b1001 1
b100100110000000 )
b100100110000000 @
0!
#1890000
b1 :
0+
1!
#1900000
0!
#1910000
b10 :
1(
1!
#1920000
b100 &
b100 2
b100 >
b100 3
b10 '
b10 /
b10 =
b10 0
b11000000 ,
b11000000 ?
b100 1
b10 .
b10010011000000 )
b10010011000000 @
b110 ;
0!
#1930000
b11 :
0(
1!
#1940000
0!
#1950000
b100 :
1+
1!
#1960000
0!
#1970000
b1 :
0+
1!
#1980000
0!
#1990000
b10 :
1(
1!
#2000000
b10 &
b10 2
b10 >
b10 3
b1 '
b1 /
b1 =
b1 0
b1100000 ,
b1100000 ?
b10 1
b1 .
b1001001100000 )
b1001001100000 @
b101 ;
0!
#2010000
b11 :
0(
1!
#2020000
0!
#2030000
b100 :
1+
1!
#2040000
0!
#2050000
b1 :
0+
1!
#2060000
0!
#2070000
b10 :
1(
1!
#2080000
b110 &
b110 2
b110 >
b110 3
b0 '
b0 /
b0 =
b0 0
b110000 ,
b110000 ?
b1001 1
b0 .
b100100110000 )
b100100110000 @
b100 ;
0!
#2090000
b11 :
0(
1!
#2100000
0!
#2110000
b100 :
1+
1!
#2120000
b110 1
b11000110000 )
b11000110000 @
0!
#2130000
b1 :
0+
1!
#2140000
0!
#2150000
b10 :
1(
1!
#2160000
b11 &
b11 2
b11 >
b11 3
b11000 ,
b11000 ?
b11 1
b1100011000 )
b1100011000 @
b11 ;
0!
#2170000
b11 :
0(
1!
#2180000
0!
#2190000
b100 :
1+
1!
#2200000
0!
#2210000
b1 :
0+
1!
#2220000
0!
#2230000
b10 :
1(
1!
#2240000
b1 &
b1 2
b1 >
b1 3
b10001100 ,
b10001100 ?
b1 1
b110001100 )
b110001100 @
b10 ;
0!
#2250000
b11 :
0(
1!
#2260000
0!
#2270000
b100 :
1+
1!
#2280000
0!
#2290000
b1 :
0+
1!
#2300000
0!
#2310000
b10 :
1(
1!
#2320000
b0 &
b0 2
b0 >
b0 3
b11000110 ,
b11000110 ?
b0 1
b11000110 )
b11000110 @
b1 ;
0!
#2330000
b11 :
0(
1!
#2340000
0!
#2350000
b100 :
1+
1!
#2360000
0!
#2370000
b1 :
0+
1!
#2380000
0!
#2390000
b10 :
1(
1!
#2400000
b1100011 ,
b1100011 ?
1%
b1100011 )
b1100011 @
b0 ;
0!
#2410000
b101 :
0(
1!
#2420000
0!
#2430000
1-
1!
