Algoritmos/multiplicador/Core/Comp.v
module comparador(rst, a, z);
  input rst;
  input [31:0] a;
  output reg   z;
  always @(*) 
    if (rst)
      z=0;
    else 
      z=(a==0)? 1'b1 : 1'b0;
endmodule

Algoritmos/multiplicador/Core/Acc.v
module acumulador(rst,clk,b,add,out_r,load);
  input rst;
  input clk;
  input [31:0] b;
  input add;
  input load;
  output reg [31:0] out_r;

  always @(posedge clk or posedge rst)
    if(rst)
      out_r<= 0;
  else
      begin
        if(load)          
          out_r <= 0;     
        else if(add)
          out_r <= out_r + b;
        else
          out_r <= out_r;
      end
endmodule

Algoritmos/multiplicador/Core/Corr_de.v
module Corrimiento_de(rst,clk,shift,load,a,out_a);
  
  input rst;  
  input clk;
  input shift;
  input load;
  input [15:0] a;
  output reg [31:0] out_a;

  always@(posedge clk)    
    if(rst)
        a_out = 0 ;
    else
    begin
      if (load)
        out_a=a;
        else if (shift)
          out_a= a>>1;
    end 
endmodule

Algoritmos/multiplicador/Core/Corr_iz.v
module Corrimiento_iz(rst,clk,shift,load,b,out_b);
  input rst;
  input clk;
  input shift;
  input load;
  input [15:0] b;
  output reg [31:0] out_b;

  always@(posedge clk) 
    if(rst)
        out_b = 0 ;
    else
      begin
        if (load)
          out_b={16'b0, b};
        else if (shift)
          out_b= out_b<<1;
    end 
endmodule

Algoritmos/multiplicador/Core/Control.v
module Control(rst,clk,init,ao,shift,load,add,z,done);

input rst;
input clk;
input init;
input z;
input ao;

output reg shift;
output reg load;
output reg add;
output reg done;

parameter START = 3'b000;
parameter CHECK = 3'b001;
parameter ACCUMULATE = 3'b010;
parameter SHIFT = 3'b011;
parameter ECHECK = 3'b100;
parameter END = 3'b101;

reg [2:0] state;
reg [3:0] count;

always @(posedge clk or posedge rst) begin
    if (rst) begin
        state <= START;
        count <= 4'b0;
    end
    else begin
      case (state)
            START: begin
              if(init)
                    state <= CHECK;
                else 
                    state <= START;
            end

            CHECK: begin 
                if(ao)
                    state <= ACCUMULATE;
                else
                    state <= SHIFT;
            end

            ACCUMULATE:
                state <= SHIFT;

            SHIFT:begin
              state <= ECHECK;
              end
              ECHECK:begin
                if(z)
                    state <= END;
                else
                    state <= CHECK; 
            end

            END: begin
                  if (init)
                    state <= START;

                else 
                    state <= END;
            end
            default: state <= START;
        endcase 
    end
end
always @(*) begin
    case (state)

        START: begin
            load = 1;
            shift = 0;
            add = 0;
            done = 0;
        end 

        CHECK: begin
            load = 0;
            shift = 0;
            add = 0;
            done = 0;
        end

        ACCUMULATE: begin
            load = 0;
            shift = 0;
            add = 1;
            done = 0;
        end

        SHIFT: begin
            load = 0;
            shift = 1;
            add = 0;
            done = 0;
        end
        ECHECK: begin
            load = 0;
            shift = 0;
            add = 0;
            done = 0;
        end

        END: begin
            load = 0;
            shift = 0;
            add = 0;
            done = 1;
        end

        default: begin
            load = 0;
            shift = 0;
            add = 0;
            done = 0;
        end
        
    endcase
end
`define BENCH
`ifdef BENCH
reg [8*40:1] state_name;
always @(*) begin
    case (state)
        START        : state_name = "START";
        CHECK        : state_name = "CHECK";
        ACCUMULATE   : state_name = "ACCUMULATE";
        SHIFT        : state_name = "SHIFT";
        ECHECK       : state_name = "ECHECK";
        END          : state_name = "END";
    endcase
end
`endif



endmodule

Algoritmos/multiplicador/Core/multiplicador.v
module multi(clk,rst,init,b,a,r,done);
  
input         rst;
input         clk;
input         init;
input [15:0]  b;
input [15:0]  a;
output[31:0]  r;
output        done;

wire w_sh;
wire w_load;
wire w_add;
wire w_z;
  
wire [31:0] w_b;
wire [31:0] w_a;

Control      ctrl     (.rst(rst), .clk(clk), .init(init),.ao(w_a[0]),.shift(w_sh), .load(w_load),.add(w_add),.z(w_z),.done(done));
Corrimiento_iz lsh      (.rst(rst), .clk(clk), .shift(w_sh), .load(w_load), .b(b), .out_b(w_b)); 
Corrimiento_de rsh      (.rst(rst), .clk(clk), .shift(w_sh), .load(w_load), .a(a), .out_a(w_a));
acumulador     acc      (.rst(rst), .clk(clk), .b(w_b), .add(w_add), .out_r(r));
comparador     comp     (.rst(rst), .a(w_a), .z(w_z));

endmodule

Algoritmos/multiplicador/Core/TB/multi_TB.v
`timescale 1ns / 1ps
`define SIMULATION
module multi_TB;
  reg         rst;
  reg         clk;
  reg         init;
  reg [15:0]  b;
  reg [15:0]  a;
  wire [31:0] r;
  wire        done;
  multi uut (.clk(clk) , .rst(rst) , .init(init) , .b(b), .a(a), .r(r), .done(done));
   parameter PERIOD          = 20;
   parameter real DUTY_CYCLE = 0.5;
   parameter OFFSET          = 0;
   reg [20:0] i;
	event reset_trigger;
	event reset_done_trigger;
	initial begin 
	  forever begin 
	   @ (reset_trigger);
		@ (negedge clk);
		rst = 1;
		@ (negedge clk);
		rst = 0;
		-> reset_done_trigger;
		end
	end
   initial begin  // Initialize Inputs
      clk = 0; rst = 1; init = 0; b = 16'h00F7; a = 16'h007F;
   end
   initial  begin  // Process for clk
     #OFFSET;
     forever
       begin
         clk = 1'b0;
         #(PERIOD-(PERIOD*DUTY_CYCLE)) clk = 1'b1;
         #(PERIOD*DUTY_CYCLE);
       end
   end
   initial begin // Reset the system, Start the image capture process
        #10 -> reset_trigger;
        @ (reset_done_trigger);
        @ (posedge clk);
        init = 0;
        @ (posedge clk);
        init = 1;
       for(i=0; i<2; i=i+1) begin
         @ (posedge clk);
       end
          init = 0;
       for(i=0; i<17; i=i+1) begin
         @ (posedge clk);
       end
   end	 
always @(posedge done) begin
    $display(" Multiplicador  : %d", a);
    $display(" Multiplicador  : %d", b);
    $display(" Resultado : %d", r);
  end
   initial begin: TEST_CASE
     $dumpfile("TB/multi_TB.vcd");
     $dumpvars(-1, uut);
     #((PERIOD*DUTY_CYCLE)*120) $finish;
   end
endmodule

Algoritmos/multiplicador/Core/TB/multi_TB.vcd
$date
	Tue Jul 14 16:21:54 2026
$end
$version
	Icarus Verilog
$end
$timescale
	1ps
$end
$scope module multi_TB $end
$scope module uut $end
$var wire 16 ! a [15:0] $end
$var wire 16 " b [15:0] $end
$var wire 1 # clk $end
$var wire 1 $ init $end
$var wire 1 % rst $end
$var wire 1 & w_z $end
$var wire 1 ' w_sh $end
$var wire 1 ( w_load $end
$var wire 32 ) w_b [31:0] $end
$var wire 1 * w_add $end
$var wire 32 + w_a [31:0] $end
$var wire 32 , r [31:0] $end
$var wire 1 - done $end
$scope module acc $end
$var wire 1 # clk $end
$var wire 1 % rst $end
$var wire 1 ( load $end
$var wire 32 . b [31:0] $end
$var wire 1 * add $end
$var reg 32 / out_r [31:0] $end
$upscope $end
$scope module comp $end
$var wire 1 % rst $end
$var wire 32 0 a [31:0] $end
$var reg 1 & z $end
$upscope $end
$scope module ctrl $end
$var wire 1 1 ao $end
$var wire 1 # clk $end
$var wire 1 $ init $end
$var wire 1 % rst $end
$var wire 1 & z $end
$var parameter 3 2 ACCUMULATE $end
$var parameter 3 3 CHECK $end
$var parameter 3 4 ECHECK $end
$var parameter 3 5 END $end
$var parameter 3 6 SHIFT $end
$var parameter 3 7 START $end
$var reg 1 * add $end
$var reg 4 8 count [3:0] $end
$var reg 1 - done $end
$var reg 1 ( load $end
$var reg 1 ' shift $end
$var reg 3 9 state [2:0] $end
$var reg 320 : state_name [320:1] $end
$upscope $end
$scope module lsh $end
$var wire 16 ; b [15:0] $end
$var wire 1 # clk $end
$var wire 1 ( load $end
$var wire 1 % rst $end
$var wire 1 ' shift $end
$var reg 32 < out_b [31:0] $end
$upscope $end
$scope module rsh $end
$var wire 16 = a [15:0] $end
$var wire 1 # clk $end
$var wire 1 ( load $end
$var wire 1 % rst $end
$var wire 1 ' shift $end
$var reg 32 > out_a [31:0] $end
$upscope $end
$upscope $end
$upscope $end
$enddefinitions $end
$comment Show the parameter values. $end
$dumpall
b0 7
b11 6
b101 5
b100 4
b1 3
b10 2
$end
#0
$dumpvars
bx >
b1111111 =
bx <
b11110111 ;
b101001101010100010000010101001001010100 :
b0 9
b0 8
x1
bx 0
b0 /
bx .
0-
b0 ,
bx +
0*
bx )
1(
0'
0&
1%
0$
0#
b11110111 "
b1111111 !
$end
#10000
01
b0 )
b0 .
b0 <
b0 +
b0 0
b0 >
1#
#20000
0#
#30000
1#
#40000
1&
0%
0#
#50000
11
0&
b11110111 )
b11110111 .
b11110111 <
b1111111 +
b1111111 0
b1111111 >
1#
#60000
0#
#70000
0(
b100001101001000010001010100001101001011 :
b1 9
1$
1#
#80000
0#
#90000
b1000001010000110100001101010101010011010101010101001100010000010101010001000101 :
1*
b10 9
1#
#100000
0#
#110000
0*
1'
b101001101001000010010010100011001010100 :
b11 9
b11110111 ,
b11110111 /
0$
1#
#120000
0#
#130000
b10001010100001101001000010001010100001101001011 :
0'
b100 9
b111101110 )
b111101110 .
b111101110 <
b111111 +
b111111 0
b111111 >
1#
#140000
0#
#150000
b100001101001000010001010100001101001011 :
b1 9
1#
#160000
0#
#170000
b1000001010000110100001101010101010011010101010101001100010000010101010001000101 :
1*
b10 9
1#
#180000
0#
#190000
0*
1'
b101001101001000010010010100011001010100 :
b11 9
b1011100101 ,
b1011100101 /
1#
#200000
0#
#210000
b10001010100001101001000010001010100001101001011 :
0'
b100 9
b1111011100 )
b1111011100 .
b1111011100 <
b11111 +
b11111 0
b11111 >
1#
#220000
0#
#230000
b100001101001000010001010100001101001011 :
b1 9
1#
#240000
0#
#250000
b1000001010000110100001101010101010011010101010101001100010000010101010001000101 :
1*
b10 9
1#
#260000
0#
#270000
0*
1'
b101001101001000010010010100011001010100 :
b11 9
b11011000001 ,
b11011000001 /
1#
#280000
0#
#290000
b10001010100001101001000010001010100001101001011 :
0'
b100 9
b11110111000 )
b11110111000 .
b11110111000 <
b1111 +
b1111 0
b1111 >
1#
#300000
0#
#310000
b100001101001000010001010100001101001011 :
b1 9
1#
#320000
0#
#330000
b1000001010000110100001101010101010011010101010101001100010000010101010001000101 :
1*
b10 9
1#
#340000
0#
#350000
0*
1'
b101001101001000010010010100011001010100 :
b11 9
b111001111001 ,
b111001111001 /
1#
#360000
0#
#370000
b10001010100001101001000010001010100001101001011 :
0'
b100 9
b111101110000 )
b111101110000 .
b111101110000 <
b111 +
b111 0
b111 >
1#
#380000
0#
#390000
b100001101001000010001010100001101001011 :
b1 9
1#
#400000
0#
#410000
b1000001010000110100001101010101010011010101010101001100010000010101010001000101 :
1*
b10 9
1#
#420000
0#
#430000
0*
1'
b101001101001000010010010100011001010100 :
b11 9
b1110111101001 ,
b1110111101001 /
1#
#440000
0#
#450000
b10001010100001101001000010001010100001101001011 :
0'
b100 9
b1111011100000 )
b1111011100000 .
b1111011100000 <
b11 +
b11 0
b11 >
1#
#460000
0#
#470000
b100001101001000010001010100001101001011 :
b1 9
1#
#480000
0#
#490000
b1000001010000110100001101010101010011010101010101001100010000010101010001000101 :
1*
b10 9
1#
#500000
0#
#510000
0*
1'
b101001101001000010010010100011001010100 :
b11 9
b11110011001001 ,
b11110011001001 /
1#
#520000
0#
#530000
b10001010100001101001000010001010100001101001011 :
0'
b100 9
b11110111000000 )
b11110111000000 .
b11110111000000 <
b1 +
b1 0
b1 >
1#
#540000
0#
#550000
b100001101001000010001010100001101001011 :
b1 9
1#
#560000
0#
#570000
b1000001010000110100001101010101010011010101010101001100010000010101010001000101 :
1*
b10 9
1#
#580000
0#
#590000
0*
1'
b101001101001000010010010100011001010100 :
b11 9
b111101010001001 ,
b111101010001001 /
1#
#600000
0#
#610000
b10001010100001101001000010001010100001101001011 :
0'
b100 9
01
1&
b111101110000000 )
b111101110000000 .
b111101110000000 <
b0 +
b0 0
b0 >
1#
#620000
0#
#630000
1-
b10001010100111001000100 :
b101 9
1#
