Algoritmos/multiplicador/Core/Comp.v
module comparador(rst, a, z);
  input rst;
  input [31:0] a;
  output reg   z;
  always @(*) 
    if (rst)
      z=0;
    else 
      z=(a==0)? 1'b1 : 1'b0;
endmodule

Algoritmos/multiplicador/Core/Acc.v
module acumulador(rst,clk,b,add,out_r,load);
  input rst;
  input clk;
  input [31:0] b;
  input add;
  input load;
  output reg [31:0] out_r;

  always @(posedge clk or posedge rst)
    if(rst)
      out_r<= 0;
  else
      begin
        if(load)          
          out_r <= 0;     
        else if(add)
          out_r <= out_r + b;
        else
          out_r <= out_r;
      end
endmodule

Algoritmos/multiplicador/Core/Corr_de.v
module Corrimiento_de(rst,clk,shift,load,a,out_a);
  
  input rst;  
  input clk;
  input shift;
  input load;
  input [15:0] a;
  output reg [31:0] out_a;

  always@(posedge clk)    
    if(rst)
        a_out = 0 ;
    else
    begin
      if (load)
        out_a=a;
        else if (shift)
          out_a= a>>1;
    end 
endmodule

Algoritmos/multiplicador/Core/Corr_iz.v
module Corrimiento_iz(rst,clk,shift,load,b,out_b);
  input rst;
  input clk;
  input shift;
  input load;
  input [15:0] b;
  output reg [31:0] out_b;

  always@(posedge clk) 
    if(rst)
        out_b = 0 ;
    else
      begin
        if (load)
          out_b={16'b0, b};
        else if (shift)
          out_b= out_b<<1;
    end 
endmodule

Algoritmos/multiplicador/Core/Control.v
module Control(rst,clk,init,ao,shift,load,add,z,done);

input rst;
input clk;
input init;
input z;
input ao;

output reg shift;
output reg load;
output reg add;
output reg done;

parameter START = 3'b000;
parameter CHECK = 3'b001;
parameter ACCUMULATE = 3'b010;
parameter SHIFT = 3'b011;
parameter ECHECK = 3'b100;
parameter END = 3'b101;

reg [2:0] state;
reg [3:0] count;

always @(posedge clk or posedge rst) begin
    if (rst) begin
        state <= START;
        count <= 4'b0;
    end
    else begin
      case (state)
            START: begin
              if(init)
                    state <= CHECK;
                else 
                    state <= START;
            end

            CHECK: begin 
                if(ao)
                    state <= ACCUMULATE;
                else
                    state <= SHIFT;
            end

            ACCUMULATE:
                state <= SHIFT;

            SHIFT:begin
              state <= ECHECK;
              end
              ECHECK:begin
                if(z)
                    state <= END;
                else
                    state <= CHECK; 
            end

            END: begin
                  if (init)
                    state <= START;

                else 
                    state <= END;
            end
            default: state <= START;
        endcase 
    end
end
always @(*) begin
    case (state)

        START: begin
            load = 1;
            shift = 0;
            add = 0;
            done = 0;
        end 

        CHECK: begin
            load = 0;
            shift = 0;
            add = 0;
            done = 0;
        end

        ACCUMULATE: begin
            load = 0;
            shift = 0;
            add = 1;
            done = 0;
        end

        SHIFT: begin
            load = 0;
            shift = 1;
            add = 0;
            done = 0;
        end
        ECHECK: begin
            load = 0;
            shift = 0;
            add = 0;
            done = 0;
        end

        END: begin
            load = 0;
            shift = 0;
            add = 0;
            done = 1;
        end

        default: begin
            load = 0;
            shift = 0;
            add = 0;
            done = 0;
        end
        
    endcase
end
`define BENCH
`ifdef BENCH
reg [8*40:1] state_name;
always @(*) begin
    case (state)
        START        : state_name = "START";
        CHECK        : state_name = "CHECK";
        ACCUMULATE   : state_name = "ACCUMULATE";
        SHIFT        : state_name = "SHIFT";
        ECHECK       : state_name = "ECHECK";
        END          : state_name = "END";
    endcase
end
`endif



endmodule

Algoritmos/multiplicador/Core/multiplicador.v
module multi(clk,rst,init,b,a,r,done);
  
input         rst;
input         clk;
input         init;
input [15:0]  b;
input [15:0]  a;
output[31:0]  r;
output        done;

wire w_sh;
wire w_load;
wire w_add;
wire w_z;
  
wire [31:0] w_b;
wire [31:0] w_a;

Control      ctrl     (.rst(rst), .clk(clk), .init(init),.ao(w_a[0]),.shift(w_sh), .load(w_load),.add(w_add),.z(w_z),.done(done));
Corrimiento_iz lsh      (.rst(rst), .clk(clk), .shift(w_sh), .load(w_load), .b(b), .out_b(w_b)); 
Corrimiento_de rsh      (.rst(rst), .clk(clk), .shift(w_sh), .load(w_load), .a(a), .out_a(w_a));
acumulador     acc      (.rst(rst), .clk(clk), .b(w_b), .add(w_add), .out_r(r));
comparador     comp     (.rst(rst), .a(w_a), .z(w_z));

endmodule

Algoritmos/multiplicador/Core/peri_multi.v
module peripheral_multi(clk , reset , d_in , cs , addr , rd , wr, d_out );
  
  input clk;
  input reset;
  input [15:0] d_in;
  input cs;
  input [4:0]  addr; // 4 LSB from j1_io_addr
  input rd;
  input wr;
  output reg [31:0]d_out;

//------------------------------------ regs and wires-------------------------------
reg [4:0] s; 	//selector mux_4  and write registers
reg [15:0] A;//---mult_32 input registers
reg [15:0] B;
reg init;
wire [31:0] result;	//mult_32 output Regs
wire done;
//------------------------------------ regs and wires-------------------------------
always @(*) begin//------address_decoder------------------------------
if (cs) begin
  case (addr)
    5'h04: s =  5'b00001; // A 
    5'h08: s =  5'b00010; // B
    5'h0C: s =  5'b00100; // init
    5'h10: s =  5'b01000; // result
    5'h14: s =  5'b10000; // done
    default: s = 5'b00000;
  endcase
end
else
  s = 5'b00000;
end//------------------address_decoder--------------------------------

always @(posedge clk) begin//-------------------- escritura de registros 

  if(reset) begin
    init = 0;
    A    = 0;
    B    = 0;
  end
  else begin
    if (cs && wr) begin
      A    = s[0] ? d_in    : A;	//Write Registers
      B    = s[1] ? d_in    : B;	//Write Registers
      init = s[2] ? d_in[0] : init;
    end
  end

end//------------------------------------------- escritura de registros

always @(posedge clk) begin//-----------------------mux_4 :  multiplexa salidas del periferico
  if(reset)
    d_out = 0;
  else 
  if (cs) begin
    case (s[4:0])
      5'b01000: d_out    =  result;
      5'b10000: d_out    = {31'b0, done};
    endcase
  end
end//-----------------------------------------------mux_4

//# ---------------------------------------#
//# ---------------------------------------#
//# Instanciacion del periferico a probar--#
//# ---------------------------------------#
//# ---------------------------------------#

multi mult1 (
.rst(reset),
  .clk(clk),
 .init(init),
.done(done),
  .r(result),
 .a(A),
 .b(B)
 );
endmodule

Algoritmos/multiplicador/Core/TB/peri_multi_TB.v
`timescale 1ns / 1ps

module peri_multi_TB;
  reg         clk;
  reg         reset;
  reg  [15:0] d_in;
  reg         cs;
  reg  [4:0]  addr;
  reg         rd;
  reg         wr;
  wire [31:0] d_out;

  peripheral_multi uut (.clk(clk),.reset(reset),.d_in(d_in),.cs(cs),.addr(addr),.rd(rd),.wr(wr),.d_out(d_out) );

  always #5 clk = ~clk;

  task write_register;
    input [4:0]  register_addr;
    input [15:0] value;
    begin
      @(negedge clk);
      cs   = 1;
      wr   = 1;
      rd   = 0;
      addr = register_addr;
      d_in = value;
      @(posedge clk);
      #1;
      @(negedge clk);
      cs   = 0;
      wr   = 0;
      addr = 0;
      d_in = 0;
    end
  endtask

  task read_register;
    input  [4:0]  register_addr;
    output [31:0] value;
    begin
      @(negedge clk);
      cs   = 1;
      wr   = 0;
      rd   = 1;
      addr = register_addr;
      @(posedge clk);
      #1 value = d_out;
      @(negedge clk);
      cs   = 0;
      rd   = 0;
      addr = 0;
    end
  endtask

  task run_case;
    input [15:0] operand_a;
    input [15:0] operand_b;
    input [31:0] expected;
    integer cycles;
    reg [31:0] status;
    reg [31:0] result;
    begin
      write_register(5'h04, operand_a);
      write_register(5'h08, operand_b);
      write_register(5'h0c, 16'd1);

      // Keep init asserted long enough to leave END and start again.
      repeat (2) @(posedge clk);
      write_register(5'h0c, 16'd0);

      cycles = 0;
      status = 0;
      while ((status[0] !== 1'b1) && (cycles < 200)) begin
        read_register(5'h14, status);
        cycles = cycles + 1;
      end

      if (status[0] !== 1'b1) begin
        $display("peri_multi_TB FAIL: timeout para %0d * %0d", operand_a, operand_b);
        $fatal(1);
      end

      read_register(5'h10, result);
      if (result !== expected) begin
        $display("peri_multi_TB FAIL: %0d * %0d esperado=%0d obtenido=%0d",
                 operand_a, operand_b, expected, result);
        $fatal(1);
      end

      $display("peri_multi_TB OK: %0d * %0d = %0d", operand_a, operand_b, result);
    end
  endtask

  initial begin
    $dumpfile("TB/peri_multi_TB.vcd");
    $dumpvars(0, peri_multi_TB);

    clk   = 0;
    reset = 1;
    d_in  = 0;
    cs    = 0;
    addr  = 0;
    rd    = 0;
    wr    = 0;

    repeat (2) @(posedge clk);
    @(negedge clk);
    reset = 0;

    run_case(16'd13,   16'd17, 32'd221);
    run_case(16'd1024, 16'd64, 32'd65536);

    $display("peri_multi_TB PASS");
    $finish;
  end
endmodule

Algoritmos/multiplicador/Core/TB/peri_multi_TB.vcd
$date
	Tue Jul 14 16:24:49 2026
$end
$version
	Icarus Verilog
$end
$timescale
	1ps
$end
$scope module peri_multi_TB $end
$var wire 32 ! d_out [31:0] $end
$var reg 5 " addr [4:0] $end
$var reg 1 # clk $end
$var reg 1 $ cs $end
$var reg 16 % d_in [15:0] $end
$var reg 1 & rd $end
$var reg 1 ' reset $end
$var reg 1 ( wr $end
$scope module uut $end
$var wire 5 ) addr [4:0] $end
$var wire 1 # clk $end
$var wire 1 $ cs $end
$var wire 16 * d_in [15:0] $end
$var wire 1 & rd $end
$var wire 1 ' reset $end
$var wire 1 ( wr $end
$var wire 32 + result [31:0] $end
$var wire 1 , done $end
$var reg 16 - A [15:0] $end
$var reg 16 . B [15:0] $end
$var reg 32 / d_out [31:0] $end
$var reg 1 0 init $end
$var reg 5 1 s [4:0] $end
$scope module mult1 $end
$var wire 16 2 a [15:0] $end
$var wire 16 3 b [15:0] $end
$var wire 1 # clk $end
$var wire 1 0 init $end
$var wire 1 ' rst $end
$var wire 1 4 w_z $end
$var wire 1 5 w_sh $end
$var wire 1 6 w_load $end
$var wire 32 7 w_b [31:0] $end
$var wire 1 8 w_add $end
$var wire 32 9 w_a [31:0] $end
$var wire 32 : r [31:0] $end
$var wire 1 , done $end
$scope module acc $end
$var wire 1 # clk $end
$var wire 1 ' rst $end
$var wire 1 6 load $end
$var wire 32 ; b [31:0] $end
$var wire 1 8 add $end
$var reg 32 < out_r [31:0] $end
$upscope $end
$scope module comp $end
$var wire 1 ' rst $end
$var wire 32 = a [31:0] $end
$var reg 1 4 z $end
$upscope $end
$scope module ctrl $end
$var wire 1 > ao $end
$var wire 1 # clk $end
$var wire 1 0 init $end
$var wire 1 ' rst $end
$var wire 1 4 z $end
$var parameter 3 ? ACCUMULATE $end
$var parameter 3 @ CHECK $end
$var parameter 3 A ECHECK $end
$var parameter 3 B END $end
$var parameter 3 C SHIFT $end
$var parameter 3 D START $end
$var reg 1 8 add $end
$var reg 4 E count [3:0] $end
$var reg 1 , done $end
$var reg 1 6 load $end
$var reg 1 5 shift $end
$var reg 3 F state [2:0] $end
$var reg 320 G state_name [320:1] $end
$upscope $end
$scope module lsh $end
$var wire 16 H b [15:0] $end
$var wire 1 # clk $end
$var wire 1 6 load $end
$var wire 1 ' rst $end
$var wire 1 5 shift $end
$var reg 32 I out_b [31:0] $end
$upscope $end
$scope module rsh $end
$var wire 16 J a [15:0] $end
$var wire 1 # clk $end
$var wire 1 6 load $end
$var wire 1 ' rst $end
$var wire 1 5 shift $end
$var reg 32 K out_a [31:0] $end
$upscope $end
$upscope $end
$upscope $end
$scope task read_register $end
$var reg 5 L register_addr [4:0] $end
$var reg 32 M value [31:0] $end
$upscope $end
$scope task run_case $end
$var reg 32 N expected [31:0] $end
$var reg 16 O operand_a [15:0] $end
$var reg 16 P operand_b [15:0] $end
$var reg 32 Q result [31:0] $end
$var reg 32 R status [31:0] $end
$var integer 32 S cycles [31:0] $end
$upscope $end
$scope task write_register $end
$var reg 5 T register_addr [4:0] $end
$var reg 16 U value [15:0] $end
$upscope $end
$upscope $end
$enddefinitions $end
$comment Show the parameter values. $end
$dumpall
b0 D
b11 C
b101 B
b100 A
b1 @
b10 ?
$end
#0
$dumpvars
bx U
bx T
bx S
bx R
bx Q
bx P
bx O
bx N
bx M
bx L
bx K
bx J
bx I
bx H
b101001101010100010000010101001001010100 G
b0 F
b0 E
x>
bx =
b0 <
bx ;
b0 :
bx 9
08
bx 7
16
05
04
bx 3
bx 2
b0 1
x0
bx /
bx .
bx -
0,
b0 +
b0 *
b0 )
0(
1'
0&
b0 %
0$
0#
b0 "
bx !
$end
#5000
0>
b0 7
b0 ;
b0 I
b0 9
b0 =
b0 K
b0 .
b0 3
b0 H
b0 -
b0 2
b0 J
00
b0 !
b0 /
1#
#10000
0#
#15000
1#
#20000
14
b1101 U
b100 T
b11011101 N
b10001 P
b1101 O
0'
0#
#25000
1#
#30000
b1 1
b1101 %
b1101 *
b100 "
b100 )
1(
1$
0#
#35000
b1101 -
b1101 2
b1101 J
1#
#40000
b0 1
b10001 U
b1000 T
b0 %
b0 *
b0 "
b0 )
0(
0$
0#
#45000
1>
04
b1101 9
b1101 =
b1101 K
1#
#50000
b10 1
b10001 %
b10001 *
b1000 "
b1000 )
1(
1$
0#
#55000
b10001 .
b10001 3
b10001 H
1#
#60000
b0 1
b1 U
b1100 T
b0 %
b0 *
b0 "
b0 )
0(
0$
0#
#65000
b10001 7
b10001 ;
b10001 I
1#
#70000
b100 1
b1 %
b1 *
b1100 "
b1100 )
1(
1$
0#
#75000
06
b100001101001000010001010100001101001011 G
b1 F
10
1#
#80000
b0 1
b0 %
b0 *
b0 "
b0 )
0(
0$
0#
#85000
b1000001010000110100001101010101010011010101010101001100010000010101010001000101 G
18
b10 F
1#
#90000
0#
#95000
08
15
b101001101001000010010010100011001010100 G
b11 F
b10001 +
b10001 :
b10001 <
b0 U
1#
#100000
b100 1
b1100 "
b1100 )
1(
1$
0#
#105000
b10001010100001101001000010001010100001101001011 G
05
b100 F
0>
b100010 7
b100010 ;
b100010 I
b110 9
b110 =
b110 K
00
1#
#110000
b0 1
b10100 L
b0 R
b0 S
b0 "
b0 )
0(
0$
0#
#115000
b100001101001000010001010100001101001011 G
b1 F
1#
#120000
b10000 1
b10100 "
b10100 )
1&
1$
0#
#125000
b101001101001000010010010100011001010100 G
15
b11 F
1#
#126000
b0 M
#130000
b0 1
b1 S
b0 "
b0 )
0&
0$
0#
#135000
05
b10001010100001101001000010001010100001101001011 G
b100 F
1>
b11 9
b11 =
b11 K
b1000100 7
b1000100 ;
b1000100 I
1#
#140000
b10000 1
b10100 "
b10100 )
1&
1$
0#
#145000
b100001101001000010001010100001101001011 G
b1 F
1#
#150000
b0 1
b10 S
b0 "
b0 )
0&
0$
0#
#155000
18
b1000001010000110100001101010101010011010101010101001100010000010101010001000101 G
b10 F
1#
#160000
b10000 1
b10100 "
b10100 )
1&
1$
0#
#165000
b101001101001000010010010100011001010100 G
08
15
b1010101 +
b1010101 :
b1010101 <
b11 F
1#
#170000
b0 1
b11 S
b0 "
b0 )
0&
0$
0#
#175000
05
b10001010100001101001000010001010100001101001011 G
b100 F
b1 9
b1 =
b1 K
b10001000 7
b10001000 ;
b10001000 I
1#
#180000
b10000 1
b10100 "
b10100 )
1&
1$
0#
#185000
b100001101001000010001010100001101001011 G
b1 F
1#
#190000
b0 1
b100 S
b0 "
b0 )
0&
0$
0#
#195000
18
b1000001010000110100001101010101010011010101010101001100010000010101010001000101 G
b10 F
1#
#200000
b10000 1
b10100 "
b10100 )
1&
1$
0#
#205000
b101001101001000010010010100011001010100 G
08
15
b11011101 +
b11011101 :
b11011101 <
b11 F
1#
#210000
b0 1
b101 S
b0 "
b0 )
0&
0$
0#
#215000
05
b10001010100001101001000010001010100001101001011 G
b100 F
0>
14
b0 9
b0 =
b0 K
b100010000 7
b100010000 ;
b100010000 I
1#
#220000
b10000 1
b10100 "
b10100 )
1&
1$
0#
#225000
b10001010100111001000100 G
1,
b101 F
1#
#230000
b0 1
b110 S
b0 "
b0 )
0&
0$
0#
#235000
1#
#240000
b10000 1
b10100 "
b10100 )
1&
1$
0#
#245000
b1 !
b1 /
1#
#246000
b1 M
#250000
b0 1
b10000 L
b111 S
b1 R
b0 "
b0 )
0&
0$
0#
#255000
1#
#260000
b1000 1
b10000 "
b10000 )
1&
1$
0#
#265000
b11011101 !
b11011101 /
1#
#266000
b11011101 M
#270000
b0 1
b10000000000 U
b100 T
b10000000000000000 N
b1000000 P
b10000000000 O
b11011101 Q
b0 "
b0 )
0&
0$
0#
#275000
1#
#280000
b1 1
b10000000000 %
b10000000000 *
b100 "
b100 )
1(
1$
0#
#285000
b10000000000 -
b10000000000 2
b10000000000 J
1#
#290000
b0 1
b1000000 U
b1000 T
b0 %
b0 *
b0 "
b0 )
0(
0$
0#
#295000
1#
#300000
b10 1
b1000000 %
b1000000 *
b1000 "
b1000 )
1(
1$
0#
#305000
b1000000 .
b1000000 3
b1000000 H
1#
#310000
b0 1
b1 U
b1100 T
b0 %
b0 *
b0 "
b0 )
0(
0$
0#
#315000
1#
#320000
b100 1
b1 %
b1 *
b1100 "
b1100 )
1(
1$
0#
#325000
0,
16
b101001101010100010000010101001001010100 G
b0 F
10
1#
#330000
b0 1
b0 %
b0 *
b0 "
b0 )
0(
0$
0#
#335000
b100001101001000010001010100001101001011 G
06
b1 F
b0 +
b0 :
b0 <
04
b10000000000 9
b10000000000 =
b10000000000 K
b1000000 7
b1000000 ;
b1000000 I
1#
#340000
0#
#345000
15
b101001101001000010010010100011001010100 G
b11 F
b0 U
1#
#350000
b100 1
b1100 "
b1100 )
1(
1$
0#
#355000
b10001010100001101001000010001010100001101001011 G
05
b100 F
00
b1000000000 9
b1000000000 =
b1000000000 K
b10000000 7
b10000000 ;
b10000000 I
1#
#360000
b0 1
b10100 L
b0 R
b0 S
b0 "
b0 )
0(
0$
0#
#365000
b100001101001000010001010100001101001011 G
b1 F
1#
#370000
b10000 1
b10100 "
b10100 )
1&
1$
0#
#375000
b101001101001000010010010100011001010100 G
15
b11 F
b0 !
b0 /
1#
#376000
b0 M
#380000
b0 1
b1 S
b0 "
b0 )
0&
0$
0#
#385000
05
b10001010100001101001000010001010100001101001011 G
b100 F
b100000000 7
b100000000 ;
b100000000 I
b100000000 9
b100000000 =
b100000000 K
1#
#390000
b10000 1
b10100 "
b10100 )
1&
1$
0#
#395000
b100001101001000010001010100001101001011 G
b1 F
1#
#400000
b0 1
b10 S
b0 "
b0 )
0&
0$
0#
#405000
15
b101001101001000010010010100011001010100 G
b11 F
1#
#410000
b10000 1
b10100 "
b10100 )
1&
1$
0#
#415000
b10001010100001101001000010001010100001101001011 G
05
b100 F
b10000000 9
b10000000 =
b10000000 K
b1000000000 7
b1000000000 ;
b1000000000 I
1#
#420000
b0 1
b11 S
b0 "
b0 )
0&
0$
0#
#425000
b100001101001000010001010100001101001011 G
b1 F
1#
#430000
b10000 1
b10100 "
b10100 )
1&
1$
0#
#435000
b101001101001000010010010100011001010100 G
15
b11 F
1#
#440000
b0 1
b100 S
b0 "
b0 )
0&
0$
0#
#445000
05
b10001010100001101001000010001010100001101001011 G
b100 F
b10000000000 7
b10000000000 ;
b10000000000 I
b1000000 9
b1000000 =
b1000000 K
1#
#450000
b10000 1
b10100 "
b10100 )
1&
1$
0#
#455000
b100001101001000010001010100001101001011 G
b1 F
1#
#460000
b0 1
b101 S
b0 "
b0 )
0&
0$
0#
#465000
15
b101001101001000010010010100011001010100 G
b11 F
1#
#470000
b10000 1
b10100 "
b10100 )
1&
1$
0#
#475000
b10001010100001101001000010001010100001101001011 G
05
b100 F
b100000 9
b100000 =
b100000 K
b100000000000 7
b100000000000 ;
b100000000000 I
1#
#480000
b0 1
b110 S
b0 "
b0 )
0&
0$
0#
#485000
b100001101001000010001010100001101001011 G
b1 F
1#
#490000
b10000 1
b10100 "
b10100 )
1&
1$
0#
#495000
b101001101001000010010010100011001010100 G
15
b11 F
1#
#500000
b0 1
b111 S
b0 "
b0 )
0&
0$
0#
#505000
05
b10001010100001101001000010001010100001101001011 G
b100 F
b1000000000000 7
b1000000000000 ;
b1000000000000 I
b10000 9
b10000 =
b10000 K
1#
#510000
b10000 1
b10100 "
b10100 )
1&
1$
0#
#515000
b100001101001000010001010100001101001011 G
b1 F
1#
#520000
b0 1
b1000 S
b0 "
b0 )
0&
0$
0#
#525000
15
b101001101001000010010010100011001010100 G
b11 F
1#
#530000
b10000 1
b10100 "
b10100 )
1&
1$
0#
#535000
b10001010100001101001000010001010100001101001011 G
05
b100 F
b1000 9
b1000 =
b1000 K
b10000000000000 7
b10000000000000 ;
b10000000000000 I
1#
#540000
b0 1
b1001 S
b0 "
b0 )
0&
0$
0#
#545000
b100001101001000010001010100001101001011 G
b1 F
1#
#550000
b10000 1
b10100 "
b10100 )
1&
1$
0#
#555000
b101001101001000010010010100011001010100 G
15
b11 F
1#
#560000
b0 1
b1010 S
b0 "
b0 )
0&
0$
0#
#565000
05
b10001010100001101001000010001010100001101001011 G
b100 F
b100000000000000 7
b100000000000000 ;
b100000000000000 I
b100 9
b100 =
b100 K
1#
#570000
b10000 1
b10100 "
b10100 )
1&
1$
0#
#575000
b100001101001000010001010100001101001011 G
b1 F
1#
#580000
b0 1
b1011 S
b0 "
b0 )
0&
0$
0#
#585000
15
b101001101001000010010010100011001010100 G
b11 F
1#
#590000
b10000 1
b10100 "
b10100 )
1&
1$
0#
#595000
b10001010100001101001000010001010100001101001011 G
05
b100 F
b10 9
b10 =
b10 K
b1000000000000000 7
b1000000000000000 ;
b1000000000000000 I
1#
#600000
b0 1
b1100 S
b0 "
b0 )
0&
0$
0#
#605000
b100001101001000010001010100001101001011 G
b1 F
1#
#610000
b10000 1
b10100 "
b10100 )
1&
1$
0#
#615000
b101001101001000010010010100011001010100 G
15
b11 F
1#
#620000
b0 1
b1101 S
b0 "
b0 )
0&
0$
0#
#625000
05
b10001010100001101001000010001010100001101001011 G
b100 F
1>
b10000000000000000 7
b10000000000000000 ;
b10000000000000000 I
b1 9
b1 =
b1 K
1#
#630000
b10000 1
b10100 "
b10100 )
1&
1$
0#
#635000
b100001101001000010001010100001101001011 G
b1 F
1#
#640000
b0 1
b1110 S
b0 "
b0 )
0&
0$
0#
#645000
18
b1000001010000110100001101010101010011010101010101001100010000010101010001000101 G
b10 F
1#
#650000
b10000 1
b10100 "
b10100 )
1&
1$
0#
#655000
b101001101001000010010010100011001010100 G
08
15
b11 F
b10000000000000000 +
b10000000000000000 :
b10000000000000000 <
1#
#660000
b0 1
b1111 S
b0 "
b0 )
0&
0$
0#
#665000
05
b10001010100001101001000010001010100001101001011 G
b100 F
0>
14
b100000000000000000 7
b100000000000000000 ;
b100000000000000000 I
b0 9
b0 =
b0 K
1#
#670000
b10000 1
b10100 "
b10100 )
1&
1$
0#
#675000
b10001010100111001000100 G
1,
b101 F
1#
#680000
b0 1
b10000 S
b0 "
b0 )
0&
0$
0#
#685000
1#
#690000
b10000 1
b10100 "
b10100 )
1&
1$
0#
#695000
b1 !
b1 /
1#
#696000
b1 M
#700000
b0 1
b10000 L
b10001 S
b1 R
b0 "
b0 )
0&
0$
0#
#705000
1#
#710000
b1000 1
b10000 "
b10000 )
1&
1$
0#
#715000
b10000000000000000 !
b10000000000000000 /
1#
#716000
b10000000000000000 M
#720000
b0 1
b10000000000000000 Q
b0 "
b0 )
0&
0$
0#
