Algoritmos/Raiz_Cuadrada/Core/Control.v
module control(clk,rst,start,z,z_a,load_ra,shift_ra,sub_ra,shift_b,set_b0,load_c,calc_c,done);
    input      clk, rst, start;
    input      z;
    input      z_a;
    output reg load_ra, shift_ra, sub_ra;
    output reg shift_b, set_b0;
    output reg load_c, calc_c;
    output reg done;
  
    parameter START  = 3'b000;
    parameter SHIFT_RA  = 3'b001; 
    parameter SHIFT_CB  = 3'b010; 
    parameter CHECK = 3'b011; 
    parameter DECB0 = 3'b100;
    parameter CHECK_F  = 3'b101; 
    parameter END     = 3'b111;

reg [2:0] state;
reg [3:0] count;

    always @(posedge clk or posedge rst) begin
        if (rst) begin
        state <= START;
        count <= 4'b0;
    end
   else begin
      case (state)
            START: begin
              if(start)
                    state <= SHIFT_RA;
                else 
                    state <= START;
            end

            SHIFT_RA: 
                  state <= SHIFT_CB;
               

            SHIFT_CB:
                state <=CHECK;

            CHECK:begin
                if(z)
                    state <= DECB0;
                else
                    state <= CHECK_F; 
            end
            DECB0:
                state <=CHECK_F;

            CHECK_F:begin
                if(z_a)
                    state <= END;
                else
                    state <= SHIFT_RA; 
            end
            END: begin
                  if (start)
                    state <= START;

                else 
                    state <= END;
            end

            default: state <= START;
        endcase 
    end
end
   always @(*) begin
    case (state)

        START: begin
            load_ra = 1;  
        shift_ra = 0;
        sub_ra = 0;
        shift_b = 0;  
        set_b0 = 0;
        load_c  = 0;
        calc_c = 0; 
        done = 0;
        end 

        SHIFT_RA: begin
            load_ra = 0;  
        shift_ra = 1;
        sub_ra = 0;
        shift_b = 0;  
        set_b0 = 0;
        load_c  = 1;
        calc_c = 0; 
        done = 0;
        end

       SHIFT_CB: begin
            load_ra = 0;  
        shift_ra = 0;
        sub_ra = 0;
        shift_b = 1;  
        set_b0 = 0;
        load_c  = 0;
        calc_c = 1; 
        done = 0;
        end

        CHECK: begin
            load_ra = 0;  
        shift_ra = 0;
        sub_ra = 0;
        shift_b = 0;  
        set_b0 = 0;
        load_c  = 0;
        calc_c = 0; 
        done = 0;
        end
        DECB0: begin
            load_ra = 0;  
        shift_ra = 0;
        sub_ra = 1;
        shift_b = 0;  
        set_b0 = 1;
        load_c  = 0;
        calc_c = 0; 
        done = 0;
        end

        CHECK_F: begin
            load_ra = 0;  
        shift_ra = 0;
        sub_ra = 0;
        shift_b = 0;  
        set_b0 = 0;
        load_c  = 0;
        calc_c = 0; 
        done = 0;
        end
        END: begin
        load_ra = 0;  
        shift_ra = 0;
        sub_ra = 0;
        shift_b = 0;  
        set_b0 = 0;
        load_c  = 0;
        calc_c = 0; 
        done = 1;
        end

        default: begin
         load_ra = 0;  
        shift_ra = 0;
        sub_ra = 0;
        shift_b = 0;  
        set_b0 = 0;
        load_c  = 0;
        calc_c = 0; 
        done = 0;
        end
        
    endcase
end
   

`define BENCH
`ifdef BENCH
  reg [8*40:1] state_name;
  always @(*) begin
    case (state)
      START:      state_name = "START";
      SHIFT_RA: state_name = "SHIFT_RA";
      SHIFT_CB: state_name = "SHIFT_CB";
      DECB0:       state_name = "DECB0";
      CHECK:       state_name = "CHECK";
      CHECK_F:     state_name = "CHK_CO";
      END:     state_name = "END";
    endcase
  end
`endif
endmodule

Algoritmos/Raiz_Cuadrada/Core/Corr_c.v
module Corrimiento_c (clk,rst,load_b,B,calc_c,C);
    input            clk;
    input            rst;
    input            load_b;
    input      [4:0] B;
    input            calc_c;
    output reg [7:0] C;
    
    always @(posedge clk or posedge rst) begin
        if (rst) begin
            C <= 8'b0;
        end 
      else begin
            if (load_b) 
                C <= {3'b0, B};          
            else if (calc_c) 
                C <= (C << 2) | 8'b1;    
        end
    end
endmodule

Algoritmos/Raiz_Cuadrada/Core/Corr_b.v
module Corr_b (clk,start,shift,b0,B);
    input            clk;
    input            start;
    input            shift;
    input            b0;
  output reg [4:0] B;
always @(posedge clk or posedge start) begin
if (start) begin
            B = 5'b0;
        end 
else begin
    if (shift)  B <= B << 1;   
            if (b0) B[0] <= 1'b1;  
        end
    end
endmodule

Algoritmos/Raiz_Cuadrada/Core/Corr_ra.v
module Corrimiento_ra (clk,rst,load,radical_in, shift,sub_en,C,A,R);
    input            clk;
    input            rst;
    input            load;
    input      [7:0] radical_in;
    input            shift;
    input            sub_en;
    input      [7:0] C;
    output reg [8:0] A;
    output reg [7:0] R;

    always @(posedge clk or posedge rst) begin
        if (rst ) begin
            A <= 9'b0;
            R <= 8'b0;
        end 
      else if (load) begin
          A <= {radical_in, 1'b1};
            R <= 8'b0;
        end 
      else begin
            if (shift) 
                {R, A} <= {R, A} << 2; 
            else if (sub_en) 
                R <= R - C;            
        end
    end
endmodule

Algoritmos/Raiz_Cuadrada/Core/Comp.v
module comparador (R,C,z);
    input  [7:0] R;
    input  [7:0] C;
    output       z;
    
    assign z = (R >= C);
endmodule

Algoritmos/Raiz_Cuadrada/Core/raiz.v
module raiz (clk, rst, start,radical,resultado,done);
input        clk, rst, start;
    input  [7:0] radical;
    output [4:0] resultado;
    output       done;
    wire w_z, w_z_a;
    wire w_load_ra, w_shift_ra, w_sub_ra;
    wire w_shift_b, w_set_b0;
    wire w_load_c, w_calc_c;
    wire [8:0] w_A;
    wire [7:0] w_R, w_C;
    wire [4:0] w_B;

    assign w_z_a     = (w_A == 9'b100000000); 
    assign resultado = w_B;
    


    comparador comp   (.R(w_R), .C(w_C), .z(w_z));
    Corrimiento_ra   corr_ra(.clk(clk), .rst(rst), .load(w_load_ra),.radical_in(radical), .shift(w_shift_ra), .sub_en(w_sub_ra), .C(w_C), .A(w_A), .R(w_R));
    Corr_b      corr_b(.clk(clk), .start(start),.shift(w_shift_b), .b0(w_set_b0), .B(w_B));                
    Corrimiento_c      corr_c (.clk(clk), .rst(rst), .load_b(w_load_c),.B(w_B), .calc_c(w_calc_c), .C(w_C));                  
    control  ctrl(.clk(clk), .rst(rst), .start(start), .z(w_z), .z_a(w_z_a), .load_ra(w_load_ra), .shift_ra(w_shift_ra), .sub_ra(w_sub_ra), 
                     .shift_b(w_shift_b), .set_b0(w_set_b0), .load_c(w_load_c), .calc_c(w_calc_c), .done(done));
endmodule

Algoritmos/Raiz_Cuadrada/Core/TB/raiz_TB.v
`timescale 1ns / 1ps
`define SIMULATION

module raiz_TB;
  reg        rst;
  reg        clk;
  reg        init;
  reg        start;
  reg  [7:0] radical;
  
  wire [4:0] resultado;
  wire [7:0] residuo;
  wire       done;

  raiz uut ( .clk(clk), .rst(rst), .start(start), .radical(radical), .resultado(resultado), .done(done));

  parameter PERIOD         = 20;
  parameter real DUTY_CYCLE = 0.5;
  parameter OFFSET         = 0;
  reg [20:0] i;

  event reset_trigger;
  event reset_done_trigger;

  initial begin 
    forever begin 
      @ (reset_trigger);
      @ (negedge clk);
      rst = 1;
      @ (negedge clk);
      rst = 0;
      -> reset_done_trigger;
    end
  end

  initial begin  
    clk = 0; rst = 1; init = 0; start = 0;
    radical = 8'd121; 
  end

  initial begin  
    #OFFSET;
    forever begin
      clk = 1'b0;
      #(PERIOD-(PERIOD*DUTY_CYCLE)) clk = 1'b1;
      #(PERIOD*DUTY_CYCLE);
    end
  end

  initial begin 
    #10 -> reset_trigger;
    @ (reset_done_trigger);
    
    @ (posedge clk);
    init = 1;
    @ (posedge clk);
    init = 0;
    
    for(i=0; i<2; i=i+1) begin
      @ (posedge clk);
    end
    
    start = 1;
    @ (posedge clk);
    start = 0;
    
  
    @ (posedge done);
    #20;
    $finish;
  end     

  
  always @(posedge done) begin
    $display(" Valor Radical  : %d", radical);
    $display(" RESULTADO FINAL : %d", resultado);
  end

  initial begin: TEST_CASE
    $dumpfile("TB/raiz_TB.vcd");
    $dumpvars(-1, uut);
  end
endmodule

Algoritmos/Raiz_Cuadrada/Core/TB/raiz_TB.vcd
$date
	Tue Jul 14 18:05:40 2026
$end
$version
	Icarus Verilog
$end
$timescale
	1ps
$end
$scope module raiz_TB $end
$scope module uut $end
$var wire 1 ! clk $end
$var wire 8 " radical [7:0] $end
$var wire 5 # resultado [4:0] $end
$var wire 1 $ rst $end
$var wire 1 % start $end
$var wire 1 & w_z_a $end
$var wire 1 ' w_z $end
$var wire 1 ( w_sub_ra $end
$var wire 1 ) w_shift_ra $end
$var wire 1 * w_shift_b $end
$var wire 1 + w_set_b0 $end
$var wire 1 , w_load_ra $end
$var wire 1 - w_load_c $end
$var wire 1 . w_calc_c $end
$var wire 8 / w_R [7:0] $end
$var wire 8 0 w_C [7:0] $end
$var wire 5 1 w_B [4:0] $end
$var wire 9 2 w_A [8:0] $end
$var wire 1 3 done $end
$scope module comp $end
$var wire 1 ' z $end
$var wire 8 4 R [7:0] $end
$var wire 8 5 C [7:0] $end
$upscope $end
$scope module corr_b $end
$var wire 1 ! clk $end
$var wire 1 % start $end
$var wire 1 * shift $end
$var wire 1 + b0 $end
$var reg 5 6 B [4:0] $end
$upscope $end
$scope module corr_c $end
$var wire 5 7 B [4:0] $end
$var wire 1 ! clk $end
$var wire 1 $ rst $end
$var wire 1 - load_b $end
$var wire 1 . calc_c $end
$var reg 8 8 C [7:0] $end
$upscope $end
$scope module corr_ra $end
$var wire 8 9 C [7:0] $end
$var wire 1 ! clk $end
$var wire 8 : radical_in [7:0] $end
$var wire 1 $ rst $end
$var wire 1 ( sub_en $end
$var wire 1 ) shift $end
$var wire 1 , load $end
$var reg 9 ; A [8:0] $end
$var reg 8 < R [7:0] $end
$upscope $end
$scope module ctrl $end
$var wire 1 ! clk $end
$var wire 1 $ rst $end
$var wire 1 % start $end
$var wire 1 ' z $end
$var wire 1 & z_a $end
$var parameter 3 = CHECK $end
$var parameter 3 > CHECK_F $end
$var parameter 3 ? DECB0 $end
$var parameter 3 @ END $end
$var parameter 3 A SHIFT_CB $end
$var parameter 3 B SHIFT_RA $end
$var parameter 3 C START $end
$var reg 1 . calc_c $end
$var reg 4 D count [3:0] $end
$var reg 1 3 done $end
$var reg 1 - load_c $end
$var reg 1 , load_ra $end
$var reg 1 + set_b0 $end
$var reg 1 * shift_b $end
$var reg 1 ) shift_ra $end
$var reg 3 E state [2:0] $end
$var reg 320 F state_name [320:1] $end
$var reg 1 ( sub_ra $end
$upscope $end
$upscope $end
$upscope $end
$enddefinitions $end
$comment Show the parameter values. $end
$dumpall
b0 C
b1 B
b10 A
b111 @
b100 ?
b101 >
b11 =
$end
#0
$dumpvars
b101001101010100010000010101001001010100 F
b0 E
b0 D
b0 <
b0 ;
b1111001 :
b0 9
b0 8
bx 7
bx 6
b0 5
b0 4
03
b0 2
bx 1
b0 0
b0 /
0.
0-
1,
0+
0*
0)
0(
1'
0&
0%
1$
bx #
b1111001 "
0!
$end
#10000
1!
#20000
0!
#30000
1!
#40000
0$
0!
#50000
b11110011 2
b11110011 ;
1!
#60000
0!
#70000
1!
#80000
0!
#90000
1!
#100000
0!
#110000
1-
1)
0,
b101001101001000010010010100011001010100010111110101001001000001 F
b1 E
b0 #
b0 1
b0 6
b0 7
1%
1!
#120000
0!
#130000
b101001101001000010010010100011001010100010111110100001101000010 F
1.
0-
1*
0)
b10 E
b1 /
b1 4
b1 <
b111001100 2
b111001100 ;
0%
1!
#140000
0!
#150000
0.
0*
b100001101001000010001010100001101001011 F
b1 0
b1 5
b1 8
b1 9
b11 E
1!
#160000
0!
#170000
b100010001000101010000110100001000110000 F
1+
1(
b100 E
1!
#180000
0!
#190000
0+
0(
b10000110100100001001011010111110100001101001111 F
b1 #
b1 1
b1 6
b1 7
0'
b0 /
b0 4
b0 <
b101 E
1!
#200000
0!
#210000
b101001101001000010010010100011001010100010111110101001001000001 F
1-
1)
b1 E
1!
#220000
0!
#230000
1.
0-
1*
0)
b101001101001000010010010100011001010100010111110100001101000010 F
1'
b11 /
b11 4
b11 <
b100110000 2
b100110000 ;
b10 E
1!
#240000
0!
#250000
b100001101001000010001010100001101001011 F
0.
0*
b10 #
b10 1
b10 6
b10 7
b11 E
0'
b101 0
b101 5
b101 8
b101 9
1!
#260000
0!
#270000
b10000110100100001001011010111110100001101001111 F
b101 E
1!
#280000
0!
#290000
b101001101001000010010010100011001010100010111110101001001000001 F
1-
1)
b1 E
1!
#300000
0!
#310000
1.
0-
1*
0)
b101001101001000010010010100011001010100010111110100001101000010 F
b1110 /
b1110 4
b1110 <
b11000000 2
b11000000 ;
1'
b10 0
b10 5
b10 8
b10 9
b10 E
1!
#320000
0!
#330000
b100001101001000010001010100001101001011 F
0.
0*
b100 #
b100 1
b100 6
b100 7
b11 E
b1001 0
b1001 5
b1001 8
b1001 9
1!
#340000
0!
#350000
1+
1(
b100010001000101010000110100001000110000 F
b100 E
1!
#360000
0!
#370000
b10000110100100001001011010111110100001101001111 F
0+
0(
b101 #
b101 1
b101 6
b101 7
b101 E
0'
b101 /
b101 4
b101 <
1!
#380000
0!
#390000
1-
1)
b101001101001000010010010100011001010100010111110101001001000001 F
b1 E
1!
#400000
0!
#410000
b101001101001000010010010100011001010100010111110100001101000010 F
1.
0-
1*
0)
b10 E
b101 0
b101 5
b101 8
b101 9
1'
b10101 /
b10101 4
b10101 <
1&
b100000000 2
b100000000 ;
1!
#420000
0!
#430000
0.
0*
b100001101001000010001010100001101001011 F
b1010 #
b1010 1
b1010 6
b1010 7
b10101 0
b10101 5
b10101 8
b10101 9
b11 E
1!
#440000
0!
#450000
b100010001000101010000110100001000110000 F
1+
1(
b100 E
1!
#460000
0!
#470000
0+
0(
b10000110100100001001011010111110100001101001111 F
b1011 #
b1011 1
b1011 6
b1011 7
0'
b0 /
b0 4
b0 <
b101 E
1!
#480000
0!
#490000
b10001010100111001000100 F
13
b111 E
1!
